Workbook

Sheet Receivables list
A1: Receiveabl List
A3: S.NO | B3: PARTY NAME | C3: BALANCE
A5: 1 | B5: Al Bayan Water | C5: ='Al Bayan Water '!F8 -> 0
A6: 2 | B6: Ab e Rose Water | C6: ='Ab e Rose Water'!F8 -> 27468
A7: 3 | B7: Aqua Musafi | C7: ='Aqua Musafi'!F25 -> 30578
A8: 4 | B8: Al Javaid Ice Factory | C8: ='Al Javed Ice Factory'!F10 -> 26550
A9: 5 | B9: Al Maida Water | C9: ='Al Maida Water'!F24 -> 35552
A10: 6 | B10: Ahmed N-One Water | C10: ='Ahmed N One water'!F52 -> 581570
A11: 8 | B11: Al Khidmat Lodhran | C11: ='Al Khidmat lodhran '!F10 -> 51024
A12: 9 | B12: Al Khidmat BWP | C12: ='Al Khidmat Bwp'!F23 -> 79945
A13: 10 | B13: Al Shafi Water | C13: ='Al Shafi Water (Younas sb)'!F20 -> 2150
A14: 11 | B14: Aqua Refine | C14: ='Aqua Refine '!G142 -> 350
A15: 12 | B15: Abshar Water | C15: ='Abshar Water'!F12 -> 15450
A16: 13 | B16: Aqua Marine | C16: ='Aqua Marine '!F10 -> 73127
A17: 14 | B17: Ab e Hayat Plus | C17: ='Ab e Hayat Plus'!F16 -> 253
A18: 15 | B18: Aqsa Water Chishti Sb | C18: ='Aqsa Water'!F9 -> 51181
A19: 16 | B19: Al Azam Water | C19: ='Al Azam Water'!F30 -> 95940
A20: 17 | B20: Aqua Santa | C20: ='Aqua Santa'!F8 -> 9684
A21: 18 | B21: Ahmed Ice Factory(LD) | C21: ='Ahmed Ice Factory '!F27 -> 106514
A22: 19 | B22: Aqua Shereen | C22: ='Aqua Shereen '!F8 -> 54965
A23: 20 | B23: Alien Water Lodhran | C23: ='Alien Water( Lodhran)'!F14 -> 11800
A24: 21 | B24: Alien Water Bwp | C24: ='Alien Water( Bwp)'!F10 -> 0
A25: 22 | B25: A.F Water | C25: ='A.F Water'!F10 -> 10351
A26: 23 | B26: Aswad Sb | C26: ='Aswad Sb'!F34 -> 1775
A27: 24 | B27: Asia Homeo Store | C27: ='Asia Homeyo Store'!F10 -> 11250
A28: 25 | B28: Ahsas Water | C28: ='Ahsas Water '!F8 -> 0
A29: 26 | B29: Al Subhan Water | C29: ='Al Subhan Water'!F12 -> 0
A30: 27 | B30: Barcly Water | C30: ='Barcly Water'!F77 -> 137250
A31: 28 | B31: Bling Water | C31: ='Bling Water'!F17 -> 32830
A32: 29 | B32: Bissmillah Senitary | C32: ='Bissimillah Senitary '!F8 -> 3624
A33: 30 | B33: BWP Water | C33: ='Bwp Water'!F10 -> 7415
A34: 31 | B34: Berg Water | C34: ='Berg Water'!F22 -> 0
A35: 32 | B35: BWMC | C35: =BWMC!F12 -> 1000
A36: 33 | B36: Chand Agro | C36: ='Chand Agro'!F69 -> 2500
A37: 34 | B37: Candy Water | C37: ='Candy Water'!F30 -> -2320
A38: 35 | B38: Clean And Clean | C38: ='Clean & Clean'!F13 -> 37270
A39: 36 | B39: Dar E Arqam | C39: ='Dar e Arqam '!F9 -> 0
A40: 37 | B40: Dr Aqua Water | C40: ='1'!F17 -> -164770
A41: 38 | B41: Ever Best | C41: ='Ever Best'!F8 -> 16664
A42: 39 | B42: Gysing Pak Water | C42: ='Gysing Pak Water'!F346 -> 298774
A43: 40 | B43: Glorious Plus | C43: ='2'!F6 -> 69000
A44: 41 | B44: Hunza water | C44: ='Hunza Water '!F12 -> 8500
A45: 42 | B45: Haji Yousaf Sb | C45: ='Haji Yousaf Sb'!F8 -> 39838
A46: 43 | B46: Ice Mountain | C46: ='Ice Mountain '!F9 -> 6600
A47: 44 | B47: Just Pure | C47: ='Just Pure'!F36 -> 300050
A48: 45 | B48: J Smart Water | C48: ='J Smart '!F8 -> 62799
A49: 46 | B49: Kashif Sb-Water Shine | C49: ='Usman Zubair.'!#REF! -> #REF!
A50: 47 | B50: Lasani Pure Water | C50: ='HB Water.'!F103 -> 90777
A51: 48 | B51: Hayat Royal Water | C51: ='Hayat Royal Water'!F35 -> 1000
A52: 49 | B52: Mateen Sb | C52: ='Mateen Sb'!F36 -> 8677
A53: 50 | B53: Moen Sb | C53: ='Moen Sb'!F34 -> 20475
A54: 51 | B54: Nonari Water | C54: =Nonari!F15 -> 0
A55: 52 | B55: Nero Water | C55: ='Nero Water'!F8 -> 429389
A56: 53 | B56: National water | C56: ='National Water'!F8 -> 0
A57: 54 | B57: Nestle Pure Water | C57: 0
A58: 55 | B58: Naeem Crystal water | C58: ='Crystal Water Bagouchi Pull'!F8 -> 5570
A59: 56 | B59: Nayab Water | C59: ='Nayab Water'!F15 -> 57300
A60: 57 | B60: Qari Ajmal Sb | C60: ='Qari ajmal Sb'!F19 -> 3978
A61: 58 | B61: Rohi Water | C61: ='Rohi Water'!F17 -> 1500
A62: 59 | B62: Sheikh usman Sb | C62: ='Sheikh Usman Sb'!F74 -> 21052
A63: 60 | B63: Shafi Water | C63: =' Shafi Water (Adnan sb)'!F24 -> 21515
A64: 61 | B64: Sawan Water | C64: =#REF! -> #REF!
A65: 62 | B65: Smart Water | C65: ='Dr.Jameel Sab'!F21 -> 5670
A66: 63 | B66: Tma Shamas Sb | C66: =#REF! -> #REF!
A67: 64 | B67: Tma Ali Sb | C67: ='TMA Ali Sb'!F8 -> 2500
A68: 65 | B68: Tanveer Chugtai Sb | C68: =#REF! -> #REF!
A69: 66 | B69: Umer Awan Sb | C69: ='Umer Awan Sb'!F9 -> 35772
A70: 67 | B70: Waleed Sb BVH | C70: ='Waleed Sb BVH'!F58 -> 19405
A71: 68 | B71: Yes Water | C71: ='Yes Water'!J39 -> 0
A72: 69 | B72: Yasir Water | C72: ='Yasir Sb'!F10 -> 231338
A73: 70 | B73: Zyng | C73: ='ZYNG '!F11 -> 29000
A74: 71 | B74: Zain Water | C74: ='Zain Water'!F8 -> 0
A75: 72 | B75: Saboor Sb Opal Water | C75: 2659
A76: 73 | B76: Star Light | C76: 62773
A77: 74 | B77: New SalSabeel BWP | C77: 22765
A78: 75 | B78: Aqua Need | C78: 66632
A79: 76 | B79: Honey Water Jameel Sb | C79: 11574
A85: TOTAL BALANCE | C85: =SUM(C5:C84) -> #REF!

Sheet Aqua Refine 
A1: LEDGER
A3: Account Holder's Name | E3: Aqua Refine
A4: Pg # | C4: New Reg (96)
A5: Date | B5: Ref No. | C5: Description | D5: Description | E5: Debit | F5: Credit | G5: Balance
A6: 23/05/24 | B6: F1859 | C6: 1.5L Bottle,.. | F6: 25850 | G6: =F6-E6 -> 25850
A7: 23/05/24 | B7: F1876 | C7: 1.5L Shoper | F7: 6800 | G7: =G6-E7+F7 -> 32650
A8: 30/05/24 | B8: F1977 | C8: 30 mm Seal | F8: 5100 | G8: =G7-E8+F8 -> 37750
A9: 30/05/24 | B9: F1986 | C9: 1.5L Bottle,.. | F9: 56438 | G9: =G8-E9+F9 -> 94188
A10: 23/05/24 | C10: IBFT | E10: 40000 | G10: =G9-E10+F10 -> 54188
A11: 30/05/24 | C11: Cash in Hand | E11: 25000 | G11: =G10-E11+F11 -> 29188
A12: 45418 | B12: G58 | C12: 30 mm Caps,.. | F12: 7000 | G12: =G11-E12+F12 -> 36188 | BY12: 8330
A13: 45449 | C13: 1.5L Bottle Return 7/-@10.80 | E13: 5292 | G13: =G12-E13+F13 -> 30896
A14: 45632 | B14: G123 | C14: 1.5L Bottle,.. | F14: 43675 | G14: =G13-E14+F14 -> 74571
A15: 13/06/24 | C15: IBFT | E15: 50000 | G15: =G14-E15+F15 -> 24571
A16: 16/06/24 | B16: G182 | C16: 1.5L Bottle,.. | F16: 17190 | G16: =G15-E16+F16 -> 41761
A17: 20/6/24 | B17: G193 | C17: 500ml-Caps,1.5 Bottle-Caps,.. | F17: 9616 | G17: =G16-E17+F17 -> 51377
A18: 20/6/24 | B18: G195 | C18: 30mm Caps | F18: 5500 | G18: =G17-E18+F18 -> 56877
A19: 20/6/24 | C19: IBFT | E19: 50000 | G19: =G18-E19+F19 -> 6877
A20: 22/6/24 | B20: G206 | C20: 1.5L-Caps,30mm caps,1.5L shoper | F20: 13820 | G20: =G19-E20+F20 -> 20697
A21: 25/6/24 | B21: G237 | C21: 30mm caps,30mm seal, jumbo PPF, PPF 10" | F21: 9600 | G21: =G20-E21+F21 -> 30297
A22: 26/6/24 | C22: IBFT | E22: 20000 | G22: =G21-E22+F22 -> 10297
A23: 29/6/24 | B23: G271 | C23: 30mm caps, 30mm seal | F23: 6200 | G23: =G22-E23+F23 -> 16497
A24: 45298 | B24: G290 | C24: 1.5L-Caps,30mm seal,1.5L shoper,500ml-caps,500ml shoper | F24: 25477 | G24: =G23-E24+F24 -> 41974
A25: 45329 | B25: G313 | C25: 19L caps,1.5L- caps,500ml- caps | F25: 9570 | G25: =G24-E25+F25 -> 51544
A26: 45358 | B26: G326 | C26: 30mmcaps,30mm seal, 1.5L shoper,500ml shoper | F26: 7300 | G26: =G25-E26+F26 -> 58844
A27: 45419 | C27: IBFT | E27: 30000 | G27: =G26-E27+F27 -> 28844
A28: 45542 | B28: G396 | C28: 19L Caps | F28: 1100 | G28: =G27-E28+F28 -> 29944
A29: 18/7/24 | B29: G450 | C29: 500ml-Caps,500ml shoper,30mm caps | F29: 25900 | G29: =G28-E29+F29 -> 55844
A30: 15/7/24 | C30: IBFT | E30: 29900 | G30: =G29-E30+F30 -> 25944
A31: 45391 | B31: G643 | C31: 1.5L E, 500L, Shoper | F31: 625 | G31: =G30-E31+F31 -> 26569
A32: 45361 | B32: G1137 | C32: Remaining Amount | F32: 590 | G32: =G31-E32+F32 -> 27159
A33: 23/10/2024 | B33: G1307 | C33: Remaining Amount | F33: 630 | G33: =G32-E33+F33 -> 27789
A34: 29/10/24 | B34: G1358 | C34: 500ml - Caps, 500ml Shoper, 30mm Caps | F34: 5230 | G34: =G33-E34+F34 -> 33019
A35: 31/10/24 | C35: Amount Cancelled from IBFT | F35: 7950 | G35: =G34-E35+F35 -> 40969
A36: 45362 | B36: G1408 | C36: 500ml E | F36: 3225 | G36: =G35-E36+F36 -> 44194
A37: 45333 | B37: G1399 | C37: Remaining Amount | D37: IBFT received 10900 total amount is 11650 | F37: 750 | G37: =G36-E37+F37 -> 44944
A38: 45393 | B38: G1428 | C38: Remaining Amount | D38: Total amount Bill G1428 39200 from which 20000 IBFT | F38: 19200 | G38: =G37-E38+F38 -> 64144
A39: 45546 | B39: G1460 | C39: 1.5L - Caps | F39: 5390 | G39: =G38-E39+F39 -> 69534
A40: 45423 | B40: Exp Sheet | C40: Cash Deposit | E40: 19500 | G40: =G39-E40+F40 -> 50034
A41: 19/10/24 | B41: Exp Sheet | C41: Cash Deposit | E41: 4830 | G41: =G40-E41+F41 -> 45204
A42: 45607 | B42: Exp Sheet | C42: Cash Deposit | D42: Bill G1485 IBFT received 12500 from which 7120 Paid remaining amount deposit as old balance | E42: 5390 | G42: =G41-E42+F42 -> 39814
C43: Filled Pet 500ml | E43: 11000 | G43: =G42-E43+F43 -> 28814
A44: 17/11/24 | B44: G1550 | C44: 1.5L- Caps, 500ml - Caps | D44: 3500 received remaining amount from bill G1550 | F44: 10150 | G44: =G43-E44+F44 -> 38964
A45: 18/11/24 | C45: IBFT | E45: 15000 | G45: =G44-E45+F45 -> 23964
G46: =G45-E46+F46 -> 23964
A47: 23/11/24 | B47: G1593 | C47: 1.5L - Caps | F47: 3390 | G47: =G46-E47+F47 -> 27354
A48: 24/11/24 | B48: G1611 | C48: 500ml - Caps,1.5L - Caps | F48: 7490 | G48: =G47-E48+F48 -> 34844
A49: 24/11/24 | C49: IBFT | E49: 7490 | G49: =G48-E49+F49 -> 27354
A50: 25/11/24 | B50: G1626 | C50: Remaining Amount | F50: 2955 | G50: =G49-E50+F50 -> 30309
A51: 28/11/24 | B51: G1643 | C51: Remaining Amount | F51: 1285 | G51: =G50-E51+F51 -> 31594
A52: 28/11/24 | B52: G1649 | C52: 1.5L - Caps, 500ml - Caps | F52: 5810 | G52: =G51-E52+F52 -> 37404
A53: 30/11/24 | B53: G1654 | C53: 500ml- Caps | F53: 8330 | G53: =G52-E53+F53 -> 45734
A54: 30/11/24 | B54: G1655 | C54: Cash Deposit | E54: 3350 | G54: =G53-E54+F54 -> 42384
G55: =G54-E55+F55 -> 42384
A56: 45303 | B56: G1671 | C56: 1.5L - Caps, 500ml - Caps,30mm seal,… | F56: 28290 | G56: =G55-E56+F56 -> 70674
A57: 45303 | B57: Exp Sheet | C57: Cash Deposit | E57: 12075 | G57: =G56-E57+F57 -> 58599
A58: 28/11/24 | B58: G1643 | C58: Remaining Amount from Bill G1643 | D58: Total amount received IBFT 10000 from which 2955 paid from Previous Bill G1626 and 8330 paid from bill G1643 | F58: 1285 | G58: =G57-E58+F58 -> 59884
A59: 45363 | C59: IBFT | E59: 18000 | G59: =G58-E59+F59 -> 41884
A60: 45363 | B60: G1685 | C60: IBFT + Cash | D60: Total amount received IBFT 18000 + Cash 2000 from which 7920 paid in Bill G1685 Remaining Amount deposit as old balance | E60: 12080 | G60: =G59-E60+F60 -> 29804
A61: 45363 | B61: G1693 | C61: 1.5-Caps,500ml- Caps, 19L Bottle Pet,….. | F61: 18780 | G61: =G60-E61+F61 -> 48584
A62: 45394 | B62: exp sh | C62: IBFT | E62: 25000 | G62: =G61-E62+F62 -> 23584
A63: 45394 | B63: G1706 | C63: 1.5L - Caps, 500ml - Caps | F63: 8960 | G63: =G62-E63+F63 -> 32544
A64: 45334 | B64: G1677 | C64: Cash Deposit | E64: 1420 | G64: =G63-E64+F64 -> 31124
A65: 45424 | B65: G1717 | C65: Remaining Amount | F65: 6780 | G65: =G64-E65+F65 -> 37904
A66: 45485 | B66: G1724 | C66: Remaining Amount | F66: 2140 | G66: =G65-E66+F66 -> 40044
A67: 45516 | B67: G1734 | C67: Remaining Amount | F67: 8700 | G67: =G66-E67+F67 -> 48744
A68: 45516 | B68: G1737 | C68: Remaining Amount | F68: 650 | G68: =G67-E68+F68 -> 49394
A69: 45547 | B69: G1742 | C69: 1.5L- Caps, 1.5L Shoper | F69: 5940 | G69: =G68-E69+F69 -> 55334
A70: 45547 | B70: exp sh | C70: Cash + E.P | E70: 26450 | G70: =G69-E70+F70 -> 28884
A71: 45547 | B71: G1742 | C71: 1.5L- Caps, 1.5L Shoper | F71: 5940 | G71: =G70-E71+F71 -> 34824
A72: 45608 | B72: G1754 | C72: 1.5L - Caps | F72: 1390 | G72: =G71-E72+F72 -> 36214
A73: 45638 | B73: G1756 | C73: Cash Deposit | E73: 258 | G73: =G72-E73+F73 -> 35956
A74: 45638 | C74: IBFT | E74: 10000 | G74: =G73-E74+F74 -> 25956
A75: 14/12/24 | B75: G1775 | C75: Remaining Amount | F75: 5920 | G75: =G74-E75+F75 -> 31876
A76: 15/12/24 | B76: G1783 | C76: 1.5L- Caps, 500ml - Caps | F76: 8960 | G76: =G75-E76+F76 -> 40836
A77: 16/12/24 | C77: IBFT | E77: 14880 | G77: =G76-E77+F77 -> 25956
A78: 16/12/24 | B78: G1793 | C78: 1.5L- Caps,30mm Caps | F78: 6140 | G78: =G77-E78+F78 -> 32096
A79: 17/12/24 | B79: exp sh | C79: Cash Deposit | E79: 6140 | G79: =G78-E79+F79 -> 25956
A80: 17/12/24 | B80: G1803 | C80: Remaining Amount | F80: 7330 | G80: =G79-E80+F80 -> 33286
A81: 17/12/24 | B81: G1812 | C81: Remaining Amount | F81: 6460 | G81: =G80-E81+F81 -> 39746
A82: 19/12/24 | B82: G1826 | C82: R.A Cash Deposit | D82: Total amount received 15000 from which 11415 paid in Bill G1826 Remaining Amount deposit as old balance | E82: 3585 | G82: =G81-E82+F82 -> 36161
A83: 19/12/24 | B83: G1830 | C83: Remaining Amount | F83: 6380 | G83: =G82-E83+F83 -> 42541
A84: 21/12/24 | B84: G1832 | C84: 1.5L- Caps, 500ml - Caps,1.5L Shoper, 500ml Shoper | F84: 11710 | G84: =G83-E84+F84 -> 54251
A85: 21/12/24 | B85: G1839 | C85: Cash Deposit | D85: Total amount received 19000 from which 12940 paid in Bill G1839 Remaining Amount deposit as old balance | E85: 6060 | G85: =G84-E85+F85 -> 48191
A86: 22/12/2024 | B86: G1847 | C86: 1.5L-Caps, 500ml- Caps,6L+ Caps | F86: 11840 | G86: =G85-E86+F86 -> 60031
A87: 23/12/24 | C87: IBFT | E87: 15000 | G87: =G86-E87+F87 -> 45031
A88: 23/12/2024 | B88: G1856 | C88: Cash Deposit | D88: Total amount received 12000 from which 8170 paid in Bill G1856 Remaining Amount deposit as old balance | E88: 3830 | G88: =G87-E88+F88 -> 41201
A89: 23/12/24 | B89: G1863 | C89: 30mm Seal | F89: 900 | G89: =G88-E89+F89 -> 42101
A90: 23/12/24 | B90: G1865 | C90: 6L+ Caps | F90: 1440 | G90: =G89-E90+F90 -> 43541
A91: 24/12/24 | B91: G1878 | C91: Remaining Amount | F91: 180 | G91: =G90-E91+F91 -> 43721
A92: 25/12/24 | B92: G1880 | C92: Remaining Amount | F92: 4590 | G92: =G91-E92+F92 -> 48311
A93: 26/12/24 | C93: IBFT | E93: 4950 | G93: =G92-E93+F93 -> 43361
A94: 28/12/24 | B94: G1896 | C94: 1.5L- Caps, 500ml - Caps, 6L + Caps,1.5L Shoper,….. | F94: 19270 | G94: =G93-E94+F94 -> 62631
A95: 26/12/24 | B95: G1892 | C95: 1.5L 500ml 6L,… | F95: 8804 | G95: =G94-E95+F95 -> 71435
A96: 28/12/24 | B96: G1908 | C96: Cash Deposit | D96: Total amount received 15000 from which 8160 paid in Bill G1908 Remaining Amount deposit as old balance | E96: 6840 | G96: =G95-E96+F96 -> 64595
A97: 29/12/24 | B97: G1911 | C97: 1.5L-Caps,1.5L Shoper,30mm Caps | F97: 9240 | G97: =G96-E97+F97 -> 73835
A98: 29/12/24 | B98: G1914 | C98: IBFT | D98: Total amount received 12400 from which 7380 paid in Bill G1914 Remaining Amount deposit as old balance | E98: 5020 | G98: =G97-E98+F98 -> 68815
A99: 30/12/24 | B99: G1917 | C99: 1.5L-Caps,1.5L Shoper,30mm Caps | F99: 7880 | G99: =G98-E99+F99 -> 76695
A100: 30/12/24 | B100: G1922 | C100: Remaining Amount | F100: 4580 | G100: =G99-E100+F100 -> 81275
A101: 30/12/24 | B101: Exp Sh | C101: IBFT | E101: 7400 | G101: =G100-E101+F101 -> 73875
...

Sheet Al Bayan Water 
A1: LEDGER
A3: Account Holder's Name | D3: Al Bayan Water
A4: Pg # | C4: New Reg(70)
A5: Date | B5: Ref No. | C5: Description | D5: Debit | E5: Credit | F5: Balance
A6: 44599 | C6: Old Balnace | E6: 161205 | F6: =E6-D6 -> 161205
F7: =E7-D7 -> 0
A8: GRAND TOTAL | F8: =F7-D8+E8 -> 0

Sheet Aqua Need
A1: LEDGER
A3: Account Holder's Name | D3: Aqua Need
A4: Pg # | C4: New Reg (186)
A5: Date | B5: Ref No. | C5: Description | D5: Debit | E5: Credit | F5: Balance
A6: 45749 | B6: H426 | C6: Remaining Amount | E6: 4000 | F6: =E6-D6 -> 4000
A7: 45810 | B7: H448 | C7: Remaining Amount | E7: 12250 | F7: =E7-D7+F6 -> 16250
A8: 45810 | B8: H446 | C8: 1.5L-Caps, 500ml- Caps, 6L + Caps | E8: 19600 | F8: =E8-D8+F7 -> 35850
A9: 45810 | B9: H447 | C9: Remaining Amount | E9: 5340 | F9: =E9-D9+F8 -> 41190
A10: 45871 | B10: H460 | C10: 1.5L-Caps, 500ml- Caps, 6L + Caps | E10: 12140 | F10: =E10-D10+F9 -> 53330
A11: 45871 | B11: Exp Sh | C11: Cash deposit | D11: 5880 | F11: =E11-D11+F10 -> 47450
A12: 45871 | B12: Exp Sh | C12: Cash deposit | D12: 31300 | F12: =E12-D12+F11 -> 16150
A13: 45779 | B13: H434 | C13: Old Balance Received | D13: 4000 | F13: =E13-D13+F12 -> 12150
A14: 45902 | B14: Exp Sh | C14: Cash deposit | D14: 12150 | F14: =E14-D14+F13 -> 0
A15: 45932 | B15: H472 | C15: 1.5L -Caps, 500ml - Caps | E15: 17972 | F15: =E15-D15+F14 -> 17972
A16: 45963 | B16: H488 | C16: 1.5L- Caps, 500ml - caps, 6L+ Caps | E16: 25420 | F16: =E16-D16+F15 -> 43392
A17: 45963 | B17: Exp Sh | C17: Cash deposit | D17: 17500 | F17: =E17-D17+F16 -> 25892
A18: 45993 | C18: IBFT 50,000 deposited remaining amount deposit for plant | D18: 50000 | F18: =E18-D18+F17 -> -24108
A19: 45993 | B19: H504 | C19: 1.5L-Caps, 500ml- Caps, 6L + Caps | E19: 17250 | F19: =E19-D19+F18 -> -6858
A20: 13/2/25 | B20: H524 | C20: 1.5L-Caps, 500ml- Caps | E20: 15120 | F20: =E20-D20+F19 -> 8262
A21: 16/2/25 | B21: H547 | C21: 30mm Seal | E21: 1800 | F21: =E21-D21+F20 -> 10062
A22: 16/2/25 | B22: H544 | C22: Remaining Amount | E22: 4600 | F22: =E22-D22+F21 -> 14662
A23: 18/2/25 | B23: Exp Sh | C23: Cash deposit | D23: 6400 | F23: =E23-D23+F22 -> 8262
A24: 20/2/25 | B24: H593 | C24: 1.5L-Caps, 500ml-Caps,500ml Seal | E24: 23050 | F24: =E24-D24+F23 -> 31312
A25: 19/2/25 | B25: H586 | C25: 1.5L-Caps, | E25: 1540 | F25: =E25-D25+F24 -> 32852
A26: 25/2/25 | B26: Exp Sh | C26: Cash deposit | D26: 1800 | F26: =E26-D26+F25 -> 31052
A27: 25/2/25 | B27: Exp Sh | C27: Cash deposit | D27: 18790 | F27: =E27-D27+F26 -> 12262
A28: 25/2/25 | B28: H644 | C28: Remaining Amount | E28: 10000 | F28: =E28-D28+F27 -> 22262
A29: 26/2/25 | B29: H660 | C29: 6L+ Caps, 1.5L-Caps | E29: 5140 | F29: =E29-D29+F28 -> 27402
A30: 27/2/25 | B30: H667 | C30: Remaining Amount | E30: 9880 | F30: =E30-D30+F29 -> 37282
A31: 45691 | B31: H693 | C31: Remaining Amount | E31: 7500 | F31: =E31-D31+F30 -> 44782
A32: 45780 | C32: Cash deposit | D32: 20000 | F32: =E32-D32+F31 -> 24782
A33: 45780 | B33: H728 | C33: 1.5L-Caps, 500ml -Caps | E33: 8340 | F33: =E33-D33+F32 -> 33122
A34: 45811 | B34: H736 | C34: 1.5L-Caps, 500ml-Caps, Ca, Na | E34: 3500 | F34: =E34-D34+F33 -> 36622
A35: 45872 | B35: H741 | C35: Remaining Amount | E35: 12380 | F35: =E35-D35+F34 -> 49002
A36: 45933 | B36: H768 | C36: Remaining Amount | E36: 15000 | F36: =E36-D36+F35 -> 64002
A37: 45994 | B37: H789 | C37: Remaining Amount | E37: 23530 | F37: =E37-D37+F36 -> 87532
A38: 16/3/25 | B38: H830 | C38: Remaining Amount | E38: 7490 | F38: =E38-D38+F37 -> 95022
A39: 16/3/25 | B39: H832 | C39: 30mm Caps | E39: 4200 | F39: =E39-D39+F38 -> 99222
A40: 18/3/25 | B40: H858 | C40: 1.5L-Caps, 500ml-Caps, 1.5L Shoper, 500ml Shoper | E40: 19260 | F40: =E40-D40+F39 -> 118482
A41: 19/3/25 | B41: Exp Sh | C41: Cash deposit | D41: 25000 | F41: =E41-D41+F40 -> 93482
A42: 23/3/25 | C42: Ledger Nill 100,000 received and 38000 discount | D42: 93482 | F42: =E42-D42+F41 -> 0
A43: 20/3/25 | B43: H881 | C43: 1.5L-Caps, 500ml-Caps, 1.5L Shoper, 500ml Shoper | E43: 19260 | F43: =E43-D43+F42 -> 19260
A44: 22/3/25 | B44: H885 | C44: 500ml-Caps, 1.5L-Caps, 1.5L Shoper,500ml Shoper, 30mm Caps | E44: 26680 | F44: =E44-D44+F43 -> 45940
A45: 24/3/25 | B45: H906 | C45: Remaining Amount | E45: 12880 | F45: =E45-D45+F44 -> 58820
A46: 24/3/25 | B46: H907 | C46: Fill Pet Received | D46: 4050 | F46: =E46-D46+F45 -> 54770
A47: 25/3/25 | B47: H923 | C47: 500ml-Caps, 1.5L-Caps, 1.5L Shoper,500ml Shoper, 30mmseal | E47: 25240 | F47: =E47-D47+F46 -> 80010
A48: 25/3/25 | B48: H927 | C48: 1.5L-Caps, 500ml-Caps,… | E48: 18070 | F48: =E48-D48+F47 -> 98080
A49: 26/3/25 | B49: Exp Sh | C49: Cash deposit | D49: 40000 | F49: =E49-D49+F48 -> 58080
A50: 26/3/25 | B50: Exp Sh | C50: Cash deposit | D50: 10000 | F50: =E50-D50+F49 -> 48080
A51: 26/3/25 | B51: H941 | C51: 500ml, 1.5L, Shoper | E51: 22480 | F51: =E51-D51+F50 -> 70560
A52: 27/3/25 | B52: H957 | C52: Remaining Amount | E52: 15320 | F52: =E52-D52+F51 -> 85880
A53: 29/3/25 | B53: H961 | C53: 1.5L-Caps, 500ml-Caps, 30mm caps,…. | E53: 27760 | F53: =E53-D53+F52 -> 113640
A54: 29/3/25 | B54: H977 | C54: 1.5L-Caps, 500ml-Caps, … | E54: 31490 | F54: =E54-D54+F53 -> 145130
A55: 30/3/25 | B55: H979 | C55: 1.5L-Caps, 500ml-Caps,.. | E55: 25490 | F55: =E55-D55+F54 -> 170620
A56: 30/3/25 | B56: H984 | C56: 500ml-caps, 6L+Caps | E56: 11660 | F56: =E56-D56+F55 -> 182280
A57: 45720 | B57: Exp Sh | C57: Cash deposit | D57: 30000 | F57: =E57-D57+F56 -> 152280
A58: 45720 | B58: H998 | C58: 1.5L, 500ml 1.5LShoper | E58: 25850 | F58: =E58-D58+F57 -> 178130
A59: 45720 | B59: Exp Sh | C59: Cash deposit | D59: 30000 | F59: =E59-D59+F58 -> 148130
A60: 28/3/25 | C60: Cash Recevied in Hand | D60: 25000 | F60: =E60-D60+F59 -> 123130
A61: 45720 | B61: Exp Sh | C61: Cash deposit | D61: 20000 | F61: =E61-D61+F60 -> 103130
A62: 45720 | B62: H1010 | C62: Remaining Amount | E62: 12550 | F62: =E62-D62+F61 -> 115680
A63: 45781 | B63: H1019 | C63: cash change remaining | D63: 750 | F63: =E63-D63+F62 -> 114930
A64: 45842 | B64: H1050 | C64: 6L+ Caps, 1.5L-Caps, Shoper | E64: 52220 | F64: =E64-D64+F63 -> 167150
A65: 45812 | B65: H1046 | C65: Jumbo PPF Quard | E65: 4300 | F65: =E65-D65+F64 -> 171450
A66: 45842 | B66: Exp Sh | C66: Cash deposit | D66: 17000 | F66: =E66-D66+F65 -> 154450
A67: 45842 | C67: Cash in Hand | D67: 34000 | F67: =E67-D67+F66 -> 120450
A68: 45812 | B68: Exp Sh | C68: Cash deposit | D68: 20000 | F68: =E68-D68+F67 -> 100450
A69: 45812 | B69: Exp Sh | C69: Cash deposit | D69: 6550 | F69: =E69-D69+F68 -> 93900
A70: 45873 | B70: H1078 | C70: 500ml - Caps | E70: 17850 | F70: =E70-D70+F69 -> 111750
A71: 45873 | B71: H1073 | C71: Remaining Amount | E71: 120 | F71: =E71-D71+F70 -> 111870
A72: 45904 | B72: H1092 | C72: 500ml - Caps | E72: 6375 | F72: =E72-D72+F71 -> 118245
A73: 45934 | C73: Cash in Hand | D73: 3000 | F73: =E73-D73+F72 -> 115245
A74: 45934 | B74: Exp Sh | C74: Cash deposit | D74: 15000 | F74: =E74-D74+F73 -> 100245
A75: 45904 | B75: H1102 | C75: Remaining Amount | E75: 6540 | F75: =E75-D75+F74 -> 106785
A76: 45934 | B76: Exp Sh | C76: Cash deposit | D76: 9000 | F76: =E76-D76+F75 -> 97785
A77: 13/4/25 | B77: Exp Sh | C77: Cash deposit | D77: 18000 | F77: =E77-D77+F76 -> 79785
A78: 45934 | B78: H1115 | C78: Shoper, Half liter packets,… | E78: 48660 | F78: =E78-D78+F77 -> 128445
A79: 13/4/25 | B79: Exp Sh | C79: Cash deposit | D79: 12000 | F79: =E79-D79+F78 -> 116445
A80: 13/4/25 | B80: H1152 | C80: 1.5L-Caps | E80: 53900 | F80: =E80-D80+F79 -> 170345
A81: 14/4/25 | B81: Exp Sh | C81: Cash deposit | D81: 74000 | F81: =E81-D81+F80 -> 96345
A82: 14/4/25 | B82: Exp Sh | C82: Cash deposit | D82: 11000 | F82: =E82-D82+F81 -> 85345
A83: 14/4/25 | B83: H1177 | C83: 1.5L-Caps | E83: 11025 | F83: =E83-D83+F82 -> 96370
A84: 17/4/25 | B84: Exp Sh | C84: Cash deposit | D84: 10000 | F84: =E84-D84+F83 -> 86370
A85: 17/4/25 | C85: IBFT | D85: 50000 | F85: =E85-D85+F84 -> 36370
A86: 17/4/25 | B86: Text message | C86: Cash in Hand received by Dodh Wala | D86: 20000 | F86: =E86-D86+F85 -> 16370
A87: 17/4/25 | B87: H1225 | C87: 1.5L-Caps, 500ml-Caps | E87: 92925 | F87: =E87-D87+F86 -> 109295
A88: 16/4/25 | B88: H1193 | C88: 30mm Caps | E88: 1550 | F88: =E88-D88+F87 -> 110845
A89: 17/4/25 | B89: H1237 | C89: 500ml Shoper, Na, Mg | E89: 6050 | F89: =E89-D89+F88 -> 116895
A90: 19/4/25 | B90: H1253 | C90: 1.5LShoper, 19L Caps | E90: 2900 | F90: =E90-D90+F89 -> 119795
A91: 19/4/25 | B91: H1257 | C91: 6L+Caps | E91: 10800 | F91: =E91-D91+F90 -> 130595
A92: 19/4/25 | B92: H1263 | C92: 1.5LShoper, 30mm Caps | E92: 9000 | F92: =E92-D92+F91 -> 139595
A93: 19/4/25 | B93: Exp Sh | C93: Cash deposit | D93: 55000 | F93: =E93-D93+F92 -> 84595
A94: 20/4/25 | B94: H1267 | C94: 1.5L-Caps, 500ml-Caps, 30mm caps,…. | E94: 97052 | F94: =E94-D94+F93 -> 181647
A95: 19/4/25 | B95: IBFT | C95: Amount Received | D95: 50000 | F95: =E95-D95+F94 -> 131647
A96: 21/4/25 | B96: H1293 | C96: 1.5L-Caps, 500ml-Caps | E96: 54260 | F96: =E96-D96+F95 -> 185907
A97: 21/4/25 | B97: H1296 | C97: 30mmCaps, 1.5LShoper, 30mm caps. | E97: 11300 | F97: =E97-D97+F96 -> 197207
A98: 21/4/25 | B98: H1297 | C98: 1.5LSeal | E98: 4000 | F98: =E98-D98+F97 -> 201207
A99: 21/4/25 | B99: Exp Sh | C99: Cash deposit | D99: 43500 | F99: =E99-D99+F98 -> 157707
A100: 22/4/2025 | B100: Exp Sh | C100: Cash deposit | D100: 50000 | F100: =E100-D100+F99 -> 107707
A101: 22/4/25 | B101: H1322 | C101: Shoper Pure Seal,.. | E101: 7100 | F101: =E101-D101+F100 -> 114807
...

Sheet Ab e Rose Water
A1: LEDGER
A3: Account Holder's Name | D3: Ab e Rose Water
A4: Pg # | C4: Old Reg(178)
A5: Date | B5: Ref No. | C5: Description | D5: Debit | E5: Credit | F5: Balance
A6: 44599 | C6: Old Balnace | E6: 27468 | F6: =E6-D6 -> 27468
F7: =F6-D7+E7 -> 27468
A8: GRAND TOTAL | F8: =F7-D8+E8 -> 27468

Sheet Aqua Musafi
A1: LEDGER
A3: Account Holder's Name | D3: Aqua Musafi
A4: Pg # | C4: New Reg (141)
A5: Date | B5: Ref No. | C5: Description | D5: Debit | E5: Credit | F5: Balance
C6: Old Balance | E6: 41490 | F6: =E6-D6 -> 41490
A7: 24/01/24 | B7: Exp Sh | C7: Cash Deposit | D7: 500 | F7: =F6-D7+E7 -> 40990
A8: 45445 | B8: Exp Sh | C8: Cash Deposit | D8: 500 | F8: =F7-D8+E8 -> 40490
A9: 14/02/24 | B9: F739 | C9: 1.5L Bottle | E9: 400 | F9: =F8-D9+E9 -> 40890
A10: 14/02/24 | B10: F742 | C10: 1.5L Bottle,.. | E10: 240 | F10: =F9-D10+E10 -> 41130
A11: 15/02/24 | B11: F759 | C11: Cash Deposit | D11: 680 | F11: =F10-D11+E11 -> 40450
A12: 19/02/24 | B12: F794 | C12: 6L Bottle | E12: 1200 | F12: =F11-D12+E12 -> 41650
A13: 13/06/24 | B13: G149 | C13: 1.5 L Bottle,.. | E13: 150 | F13: =F12-D13+E13 -> 41800
A14: 13/06/24 | B14: Exp Sh | C14: Cash Deposit | D14: 2000 | F14: =F13-D14+E14 -> 39800
A15: 45602 | B15: G149 | C15: 500 ml Bottle,.. | E15: 2000 | F15: =F14-D15+E15 -> 41800
A16: 27/7/24 | B16: G529 | C16: 1.5L + caps, 500ml + caps,.. | E16: 519 | F16: =F15-D16+E16 -> 42319
A17: 45299 | B17: G580 | C17: 5L+ caps, 500ml - caps, 1.5L-caps,… | E17: 469 | F17: =F16-D17+E17 -> 42788
A18: 45542 | C18: IBFT | D18: 2700 | F18: =F17-D18+E18 -> 40088
A19: 45299 | B19: Exp Sh | C19: Cash Deposit | D19: 510 | F19: =F18-D19+E19 -> 39578
C20: 19L Used Bottle Purchase | D20: 9000 | F20: =F19-D20+E20 -> 30578
F21: =F20-D21+E21 -> 30578
F22: =F21-D22+E22 -> 30578
F23: =F22-D23+E23 -> 30578
F24: =F23-D24+E24 -> 30578
A25: GRAND TOTAL | F25: =F24-D25+E25 -> 30578

Sheet Al Javed Ice Factory
A1: LEDGER
A3: Account Holder's Name | D3: Al Javed Ice Factory
A4: Pg # | C4: New Reg(147)
A5: Date | B5: Ref No. | C5: Description | D5: Debit | E5: Credit | F5: Balance
A6: 15/08/23 | C6: Old Balnace | E6: 17200 | F6: =E6-D6 -> 17200
A7: 45326 | B7: F1247 | C7: Sand,Jambo PPf,.. | E7: 8500 | F7: =F6-D7+E7 -> 25700
A8: 45296 | B8: F1592 | C8: PPF 10",. | E8: 850 | F8: =F7-D8+E8 -> 26550
F9: =F8-D9+E9 -> 26550
A10: GRAND TOTAL | F10: =F9-D10+E10 -> 26550

Sheet Al Maida Water
A1: LEDGER
A3: Account Holder's Name | D3: Al Maida Water
A4: Pg # | C4: New Reg(156)
A5: Date | B5: Ref No. | C5: Description | D5: Debit | E5: Credit | F5: Balance
A6: 45383 | C6: Old Balnace | E6: 9560 | F6: =E6-D6 -> 9560
A7: 45414 | C7: IBFT | D7: 9560 | F7: =F6-D7+E7 -> 0
A8: 17/02/24 | B8: F770 | C8: 19L Bottle | E8: 13000 | F8: =F7-D8+E8 -> 13000
A9: 45386 | B9: Exp Sh | C9: 36 Leak Bottle @85/- | D9: 3060 | F9: =F8-D9+E9 -> 9940
A10: 18/04/24 | B10: F1436 | C10: 19L Bottle | E10: 13000 | F10: =F9-D10+E10 -> 22940
A11: 18/04/24 | C11: IBFT | D11: 20000 | F11: =F10-D11+E11 -> 2940
A12: 28/05/24 | B12: F1939 | C12: 19L Bottle | E12: 28000 | F12: =F11-D12+E12 -> 30940
A13: 45812 | B13: H1039 | C13: Extra amount received through IBFT | D13: 500 | F13: =F12-D13+E13 -> 30440
A14: 31/12/25 | B14: j600 | C14: 19lbrush...... | E14: 5112 | F14: =F13-D14+E14 -> 35552
F15: =F14-D15+E15 -> 35552
F16: =F15-D16+E16 -> 35552
F17: =F16-D17+E17 -> 35552
F18: =F17-D18+E18 -> 35552
F19: =F18-D19+E19 -> 35552
F20: =F19-D20+E20 -> 35552
F21: =F20-D21+E21 -> 35552
F22: =F21-D22+E22 -> 35552
F23: =F22-D23+E23 -> 35552
A24: GRAND TOTAL | F24: =F23-D24+E24 -> 35552

Sheet Ahmed N One water
A1: LEDGER
A3: Account Holder's Name | D3: Ahmed N One water
A4: Pg # | C4: New Reg(124)
A5: Date | B5: Ref No. | C5: Description | D5: Debit | E5: Credit | F5: Balance
A6: 23/01/24 | C6: Old Balance | E6: 85000 | F6: =E6-D6 -> 85000
A7: 23/01/24 | B7: F542 | C7: Cash Deposit | D7: 160 | F7: =F6-D7+E7 -> 84840
A8: 27/01/24 | B8: F566 | C8: 6L Bottle,.. | E8: 2000 | F8: =F7-D8+E8 -> 86840
A9: 30/01/24 | B9: F593 | C9: 1.5L Bottle,.. | E9: 1450 | F9: =F8-D9+E9 -> 88290
A10: 45293 | B10: F608 | C10: 1.5L Bottle,.. | E10: 12000 | F10: =F9-D10+E10 -> 100290
A11: 45353 | B11: F626 | C11: 1.5L Bottle,.. | E11: 20770 | F11: =F10-D11+E11 -> 121060
A12: 45414 | B12: F655 | C12: 1.5L Bottle,.. | E12: 13850 | F12: =F11-D12+E12 -> 134910
A13: 45475 | B13: F677 | C13: 1.5L Bottle,.. | E13: 33000 | F13: =F12-D13+E13 -> 167910
A14: 45567 | B14: F694 | C14: 1.5L Bottle,.. | E14: 16680 | F14: =F13-D14+E14 -> 184590
A15: 45628 | B15: F719 | C15: 1.5L Bottle,.. | E15: 12480 | F15: =F14-D15+E15 -> 197070
A16: 14/2/24 | B16: F749 | C16: 1.5L Bottle,.. | E16: 3550 | F16: =F15-D16+E16 -> 200620
A17: 18/02/4 | B17: F778 | C17: 1.5L Bottle,.. | E17: 820 | F17: =F16-D17+E17 -> 201440
A18: 18/02/24 | B18: F784 | C18: 19L Bottle | E18: 1350 | F18: =F17-D18+E18 -> 202790
A19: 17/02/24 | B19: F767 | C19: 6L Bottle,.. | E19: 410 | F19: =F18-D19+E19 -> 203200
A20: 21/02/24 | B20: F820 | C20: 1.5L Shoper | E20: 100 | F20: =F19-D20+E20 -> 203300
A21: 24/02/24 | B21: F845 | C21: 1.5L Bottle,.. | E21: 50 | F21: =F20-D21+E21 -> 203350
C22: Loader Rickshaw | E22: 50000 | F22: =F21-D22+E22 -> 253350
A23: 27/02/24 | B23: F888 | C23: Calculation Mistake | D23: 1660 | F23: =F22-D23+E23 -> 251690
A24: 45325 | B24: F934 | C24: 1.5L Bottle,.. | E24: 14550 | F24: =F23-D24+E24 -> 266240
A25: 45385 | B25: F952 | C25: 1.5L Bottle,.. | E25: 9620 | F25: =F24-D25+E25 -> 275860
A26: 45446 | B26: F976 | C26: 1.5L Bottle,.. | E26: 14550 | F26: =F25-D26+E26 -> 290410
A27: 45476 | B27: F1005 | C27: 1.5L Bottle,.. | E27: 12010 | F27: =F26-D27+E27 -> 302420
A28: 45568 | B28: F1017 | C28: 1.5L Bottle,.. | E28: 19830 | F28: =F27-D28+E28 -> 322250
A29: 16/03/24 | B29: F1082 | C29: 1.5L Bottle,.. | E29: 21980 | F29: =F28-D29+E29 -> 344230
A30: 26/03/24 | B30: F1178 | C30: 19L Bottle,.. | E30: 34000 | F30: =F29-D30+E30 -> 378230
A31: 45295 | B31: F1231 | C31: 1.5L Bottle,.. | E31: 14160 | F31: =F30-D31+E31 -> 392390
A32: 04/04/024 | B32: F1273 | C32: 1.5L Bottle,.. | E32: 13250 | F32: =F31-D32+E32 -> 405640
A33: 45477 | B33: F1305 | C33: 1.5L Bottle,.. | E33: 10870 | F33: =F32-D33+E33 -> 416510
A34: 45508 | B34: F1317 | C34: 1.5L Bottle,.. | E34: 15390 | F34: =F33-D34+E34 -> 431900
A35: 13/04/24 | B35: F1338 | C35: 1.5L Bottle,.. | E35: 28620 | F35: =F34-D35+E35 -> 460520
A36: 14/04/24 | B36: F1359 | C36: 1.5L Bottle,.. | E36: 20220 | F36: =F35-D36+E36 -> 480740
A37: 18/04/24 | B37: F1430 | C37: 500 ml Bottle | E37: 400 | F37: =F36-D37+E37 -> 481140
A38: 21/04/24 | B38: F1463 | C38: 1.5L Bottle,.. | E38: 16450 | F38: =F37-D38+E38 -> 497590
A39: 22/04/24 | B39: Exp Sh | C39: Cash Deposit | D39: 12000 | F39: =F38-D39+E39 -> 485590
A40: 45296 | B40: F1597 | C40: 1.5L Shoper,. | E40: 28790 | F40: =F39-D40+E40 -> 514380
A41: 45387 | B41: F1626 | C41: 1.5L Bottle,.. | E41: 38100 | F41: =F40-D41+E41 -> 552480
A42: 45387 | B42: Exp Sh | C42: Cash Deposit | D42: 28790 | F42: =F41-D42+E42 -> 523690
A43: 45509 | B43: F1697 | C43: 1.5L Bottle,.. | E43: 14130 | F43: =F42-D43+E43 -> 537820
A44: 16/05/24 | B44: F1781 | C44: 1.5L Bottle,.. | E44: 30350 | F44: =F43-D44+E44 -> 568170
A45: 26/05/24 | B45: F1302 | C45: 1.5L Bottle,.. | E45: 13300 | F45: =F44-D45+E45 -> 581470
A46: 25/8/24 | B46: G929 | C46: Jumboo Houzing, PPF Jimbo,.. | E46: 12600 | F46: =F45-D46+E46 -> 594070
A47: 15/8/24 | C47: Cash Deposit | D47: 15000 | F47: =F46-D47+E47 -> 579070
C48: Plant Maintainence | E48: 2500 | F48: =F47-D48+E48 -> 581570
F49: =F48-D49+E49 -> 581570
F50: =F49-D50+E50 -> 581570
F51: =F50-D51+E51 -> 581570
A52: GRAND TOTAL | F52: =F51-D52+E52 -> 581570

Sheet Al Shafi Water (Younas sb)
A1: LEDGER
A3: Account Holder's Name | D3: Al Shafi Water (Younas sb)
A4: Pg # | C4: New Reg(110)
A5: Date | B5: Ref No. | C5: Description | D5: Debit | E5: Credit | F5: Balance
A6: 23/08/23 | B6: E905 | C6: 19L Bottle,.. | E6: 4350 | F6: =E6-D6 -> 4350
A7: 26/08/23 | B7: E953 | C7: Flim Tech Memb,.. | E7: 60500 | F7: =F6-D7+E7 -> 64850
C8: Loader Rickshaw | D8: 40000 | F8: =F7-D8+E8 -> 24850
A9: 45328 | B9: G12 | C9: 19L Bottle | E9: 400 | F9: =F8-D9+E9 -> 25250
A10: 14/7/24 | B10: G426 | D10: 1900 | F10: =F9-D10+E10 -> 23350
A11: 23/3/25 | B11: H902 | C11: Amount Received by CCard=100,000 Cash they received =35000, Tax deducted=1800 (1.8%) | D11: 63200 | F11: =F10-D11+E11 -> -39850
A12: 23/3/25 | B12: H902 | C12: 19L Bottle | E12: 42000 | F12: =F11-D12+E12 -> 2150
F13: =F12-D13+E13 -> 2150
F14: =F13-D14+E14 -> 2150
F15: =F14-D15+E15 -> 2150
F16: =F15-D16+E16 -> 2150
F17: =F16-D17+E17 -> 2150
F18: =F17-D18+E18 -> 2150
F19: =F18-D19+E19 -> 2150
A20: GRAND TOTAL | F20: =F19-D20+E20 -> 2150

Sheet Al Khidmat lodhran 
A1: LEDGER
A3: Account Holder's Name | D3: Al Khidmat lodhran
A4: Pg # | C4: Old reg(76)
A5: Date | B5: Ref No. | C5: Description | D5: Debit | E5: Credit | F5: Balance
A6: 18/01/24 | C6: Old Balnace | E6: 71024 | F6: =E6-D6 -> 71024
A7: 15/12/2024 | B7: Exp sh | C7: Installment of plant | D7: 10000 | F7: =F6-D7+E7 -> 61024
C8: total payment nill in haf ton plant
A9: 45608 | B9: Exp sh | C9: Installment of plant | D9: 10000 | F9: =F7-D9+E9 -> 51024
A10: GRAND TOTAL | F10: =F9-D10+E10 -> 51024

Sheet Al Khidmat Bwp
A1: LEDGER
A3: Account Holder's Name | D3: Al Khidmat Bwp
A4: Pg # | C4: New Reg (23)
A5: Date | B5: Ref No. | C5: Description | D5: Debit | E5: Credit | F5: Balance
C6: Old Balance | E6: 27105 | F6: =E6-D6 -> 27105
A7: 45415 | B7: F966 | C7: Jambo PPf,.. | E7: 1950 | F7: =F6+E7-D7 -> 29055
A8: 45326 | B8: Exp Sh | C8: Net Cash Dep | D8: 6750 | F8: =F7+E8-D8 -> 22305
A9: 45326 | B9: Exp Sh | C9: Cheque | D9: 11340 | F9: =F8+E9-D9 -> 10965
A10: 45387 | B10: F1625 | C10: 1.5L Bottle,.. | E10: 2000 | F10: =F9+E10-D10 -> 12965
A11: 14/05/24 | B11: Exp Sh | C11: Net Cash Dep | D11: 2000 | F11: =F10+E11-D11 -> 10965
A12: 45329 | B12: G304 | C12: TDS meter claim | E12: 500 | F12: =F11+E12-D12 -> 11465
C13: cash deposit | D13: 500 | F13: =F12+E13-D13 -> 10965
A14: 17/4/25 | B14: Exp Sh | C14: cash deposit | F14: =F13+E14-D14 -> 10965
A15: 25/5/25 | B15: H1778 | C15: 19L Caps | E15: 500 | F15: =F14+E15-D15 -> 11465
A16: 45694 | D16: 500 | F16: =F15+E16-D16 -> 10965
A17: 19/6/25 | B17: I 35 | C17: 30mm Seal | E17: 170 | F17: =F16+E17-D17 -> 11135
A18: 30/6/25 | B18: I 164 | C18: Plant Maintance | E18: 31500 | F18: =F17+E18-D18 -> 42635
A19: 22/7/25 | B19: Exp Sh | C19: Cash deposit | D19: 500 | F19: =F18+E19-D19 -> 42135
A20: 45878 | B20: I 1089 | C20: 500ml+caps…. | E20: 31800 | F20: =F19+E20-D20 -> 73935
A21: 28/9/2025 | B21: I 1423 | E21: 2950 | F21: =F20+E21-D21 -> 76885
A22: 45911 | B22: j7 | C22: flunch+membrane bush | E22: 3060 | F22: =F21+E22-D22 -> 79945
A23: GRAND TOTAL | F23: =F22+E23-D23 -> 79945

Sheet Abshar Water
A1: LEDGER
A3: Account Holder's Name | D3: Abshar Water
A4: Pg # | C4: New Reg(58)
A5: Date | B5: Ref No. | C5: Description | D5: Debit | E5: Credit | F5: Balance
A6: 45116 | B6: E1103 | C6: 1.5L Bottle with Caps | E6: 5450 | F6: =E6-D6 -> 5450
C7: Plant Remaing Amount | E7: 10000 | F7: =F6-D7+E7 -> 15450
F8: =F7-D8+E8 -> 15450
F9: =F8-D9+E9 -> 15450
F10: =F9-D10+E10 -> 15450
F11: =F10-D11+E11 -> 15450
A12: GRAND TOTAL | F12: =F11-D12+E12 -> 15450

Sheet Aqua Marine 
A1: LEDGER
A3: Account Holder's Name | D3: Aqua Marine
A4: Pg # | C4: New Reg(150)
A5: Date | B5: Ref No. | C5: Description | D5: Debit | E5: Credit | F5: Balance
A6: 45268 | C6: Opening Balnace | E6: 73127 | F6: =E6-D6 -> 73127 | H6: `
A7: 45414 | B7: F652 | C7: 1.5L Shoper,.. | E7: 6500 | F7: =F6-D7+E7 -> 79627
A8: 45538 | B8: F1010 | C8: Cash Dep | D8: 6500 | F8: =F7-D8+E8 -> 73127
F9: =F8-D9+E9 -> 73127
A10: GRAND TOTAL | F10: =F9-D10+E10 -> 73127

Sheet Ab e Hayat Plus
A1: LEDGER
A3: Account Holder's Name | D3: Ab e Hayat Plus
A4: Pg # | C4: New reg(27)
A5: Date | B5: Ref No. | C5: Description | D5: Debit | E5: Credit | F5: Balance
C6: Old Balnace | E6: 15763 | F6: =E6-D6 -> 15763
A7: 18/10/24 | C7: Add 20 L Can | D7: 23500 | F7: =F6-D7+E7 -> -7737
C8: add , Diff | D8: 1000 | F8: =F7-D8+E8 -> -8737
C9: Add | D9: 710 | F9: =F8-D9+E9 -> -9447
C10: Bill Diff | D10: 300 | F10: =F9-D10+E10 -> -9747
A11: 14/04/24 | B11: F1355 | C11: 500 ml Bottle | E11: 10000 | F11: =F10-D11+E11 -> 253
F12: =F11-D12+E12 -> 253
F13: =F12-D13+E13 -> 253
F14: =F13-D14+E14 -> 253
F15: =F14-D15+E15 -> 253
A16: GRAND TOTAL | F16: =F15-D16+E16 -> 253

Sheet Ajwah Water
A1: LEDGER
A3: Account Holder's Name | D3: Ajwah Water
A4: Pg #
A5: Date | B5: Ref No. | C5: Description | D5: Debit | E5: Credit | F5: Balance
A6: 29/4/25 | B6: 1565 | C6: Jumbo PPFGold, H.P Pump repairing,…Oold balance 3000, bill amount 22400, deposited 10,000 | E6: 12400 | F6: =E6-D6 -> 12400
A7: 19/10/25 | B7: I 1703 | C7: Jumbo PPF | E7: 2400 | F7: =F6-D7+E7 -> 14800
F8: =F7-D8+E8 -> 14800
A9: GRAND TOTAL | F9: =F8-D9+E9 -> 14800

Sheet Aqsa Water
A1: LEDGER
A3: Account Holder's Name | D3: Aqsa Water
A4: Pg # | C4: Old Reg(179)
A5: Date | B5: Ref No. | C5: Description | D5: Debit | E5: Credit | F5: Balance
A6: 18/10/21 | C6: Old Balnace | E6: 41181 | F6: =E6-D6 -> 41181
C7: Payment Rcv /cheq ky badly | E7: 10000 | F7: =F6-D7+E7 -> 51181
F8: =F7-D8+E8 -> 51181
A9: GRAND TOTAL | F9: =F8-D9+E9 -> 51181

Sheet Al Azam Water
A1: LEDGER
A3: Account Holder's Name | D3: Al Azam Water
A4: Pg # | C4: New Reg(165)
A5: Date | B5: Ref No. | C5: Description | D5: Debit | E5: Credit | F5: Balance
A6: 20/11/23 | C6: Old Balnace | E6: 42100 | F6: =E6-D6 -> 42100
A7: 28/11/23 | B7: F35 | C7: Ca, Mg, Na, | E7: 1100 | F7: =F6-D7+E7 -> 43200
A8: 29/01/24 | B8: F580 | C8: Antiscaler | E8: 2200 | F8: =F7-D8+E8 -> 45400
A9: 15/02/24 | C9: 1.5L Bottle ,Q=11200 | E9: 117600 | F9: =F8-D9+E9 -> 163000
A10: 15/02/24 | C10: 0.5L Bottle,Q=8500 | E10: 54400 | F10: =F9-D10+E10 -> 217400
A11: 15/02/24 | C11: IBFT | D11: 135000 | F11: =F10-D11+E11 -> 82400
A12: 20/02/24 | C12: IBFT | D12: 40000 | F12: =F11-D12+E12 -> 42400
A13: 45568 | B13: F1025 | C13: 30 mm Caps,.. | E13: 28040 | F13: =F12-D13+E13 -> 70440
A14: 23/03/24 | B14: F1141 | C14: Less price witten in bill #F1141 | E14: 510 | F14: =F13-D14+E14 -> 70950
A15: 28/04/24 | C15: Discount | D15: 2450 | F15: =F14-D15+E15 -> 68500
A16: 28/04/24 | C16: Net Cash in Hand | D16: 50000 | F16: =F15-D16+E16 -> 18500
A17: 28/04/24 | C17: wall socket1 1/2",.. | E17: 42160 | F17: =F16-D17+E17 -> 60660
C18: Return Feed Pump in Bill #F1558 | D18: 35000 | F18: =F17-D18+E18 -> 25660
A19: 24/7/24 | C19: Cash Deposit | D19: 20000 | F19: =F18-D19+E19 -> 5660
A20: 15/9/24 | B20: G840 | C20: 500ml - caps, 30mm caps, 500ml Shoper | E20: 40125 | F20: =F19-D20+E20 -> 45785
A21: 45839 | B21: H58 | C21: Remaining Amount from 1875 after paying 1500 | E21: 375 | F21: =F20-D21+E21 -> 46160
C22: Remaining Amount of RO Plant (Haji) | E22: 70000 | F22: =F21-D22+E22 -> 116160
A23: 26/3/25 | B23: H935 | C23: Jumbo PPY 10 | E23: 1500 | F23: =F22-D23+E23 -> 117660
C24: Cash Deposit | D24: 70000 | F24: =F23-D24+E24 -> 47660
A25: 45845 | B25: I 255 | C25: Jumbo PPF, Antiscalar, Ball Valve1", Sodium, Mg | E25: 51030 | F25: =F24-D25+E25 -> 98690
A26: 45816 | B26: I 641 | C26: 1.5LShoper | D26: 2750 | F26: =F25-D26+E26 -> 95940
F27: =F26-D27+E27 -> 95940
F28: =F27-D28+E28 -> 95940
F29: =F28-D29+E29 -> 95940
A30: GRAND TOTAL | F30: =F29-D30+E30 -> 95940

Sheet Aqua Santa
A1: LEDGER
A3: Account Holder's Name | D3: Aqua Santa & Dolce
A4: Pg # | C4: Old Reg(180)
A5: Date | B5: Ref No. | C5: Description | D5: Debit | E5: Credit | F5: Balance
A6: 23/05/3 | C6: Old Balnace | E6: 9684 | F6: =E6-D6 -> 9684
F7: =F6-D7+E7 -> 9684
A8: GRAND TOTAL | F8: =F7-D8+E8 -> 9684

Sheet Ahmed Ice Factory 
A1: LEDGER
A3: Account Holder's Name | D3: Ahmed Ice Factory (LD)
A4: Pg # | C4: Old Reg(182)
A5: Date | B5: Ref No. | C5: Description | D5: Debit | E5: Credit | F5: Balance
A6: 15/07/3 | C6: Old Balnace | E6: 274413 | F6: =E6-D6 -> 274413
A7: 15/7/23 | B7: E404 | C7: IBFT | D7: 50000 | F7: =F6-D7+E7 -> 224413
A8: 24/7/23 | B8: Exp Sh | C8: Cash Deposit | D8: 50000 | F8: =F7-D8+E8 -> 174413
A9: 45602 | B9: Purchase | C9: Memb Shell & Feed Pump | D9: 50000 | F9: =F8-D9+E9 -> 124413
A10: 30/7/24 | B10: Pump Difference | E10: 5000 | F10: =F9-D10+E10 -> 129413
A11: 30/7/24 | B11: IBFT | D11: 64500 | F11: =F10-D11+E11 -> 64913
A12: 45330 | B12: IBFT | D12: 40000 | F12: =F11-D12+E12 -> 24913
B13: Cash Deposit | D13: 24913 | F13: =F12-D13+E13 -> 0
A14: 45482 | C14: Fittings High Pressure Pump Online TDS Meter | E14: 160204 | F14: =F13-D14+E14 -> 160204
A15: 45512 | C15: Cash Deposit | D15: 8000 | F15: =F14-D15+E15 -> 152204
A16: 45512 | C16: Cash Deposit | D16: 50000 | F16: =F15-D16+E16 -> 102204
A17: 45512 | C17: 4 Sand Bags | E17: 4000 | F17: =F16-D17+E17 -> 106204
A18: 17/4/25 | B18: H1217 | C18: Jumbo PPF | D18: 1500 | F18: =F17-D18+E18 -> 104704
A19: 17/4/25 | B19: H1239 | C19: Elbow , Union, Plane socket,… | E19: 5460 | F19: =F18-D19+E19 -> 110164
A20: 22/4/25 | C20: IBFT | D20: 10000 | F20: =F19-D20+E20 -> 100164
A21: 22/4/25 | B21: H1302 | C21: wall socket 1", F socket1", Mem washing chemical | E21: 6350 | F21: =F20-D21+E21 -> 106514
F22: =F21-D22+E22 -> 106514
F23: =F22-D23+E23 -> 106514
F24: =F23-D24+E24 -> 106514
F25: =F24-D25+E25 -> 106514
F26: =F25-D26+E26 -> 106514
A27: GRAND TOTAL | F27: =F26-D27+E27 -> 106514

Sheet Aqua Shereen 
A1: LEDGER
A3: Account Holder's Name | D3: Aqua Shereen
A4: Pg # | C4: Old Reg(73)
A5: Date | B5: Ref No. | C5: Description | D5: Debit | E5: Credit | F5: Balance
A6: 29/3/23 | C6: Old Balnace | E6: 54965 | F6: =E6-D6 -> 54965
F7: =F6-D7+E7 -> 54965
A8: GRAND TOTAL | F8: =F7-D8+E8 -> 54965

Sheet Alien Water( Bwp)
A1: LEDGER
A3: Account Holder's Name | D3: Alien Water( Bwp)
A4: Pg # | C4: Old Reg (122)
A5: Date | B5: Ref No. | C5: Description | D5: Debit | E5: Credit | F5: Balance
C6: Opening Balnace | F6: =E6-D6 -> 0
F7: =F6-D7+E7 -> 0
F8: =F7-D8+E8 -> 0
F9: =F8-D9+E9 -> 0
A10: GRAND TOTAL | F10: =F9-D10+E10 -> 0

Sheet Al Safina Water
A1: LEDGER
A3: Account Holder's Name | D3: Al Safina Water
A4: Pg #
A5: Date | B5: Ref No. | C5: Description | D5: Debit | E5: Credit | F5: Balance
C6: Opening Balnace | F6: =E6-D6 -> 0
F7: =F6-D7+E7 -> 0
F8: =F7-D8+E8 -> 0
F9: =F8-D9+E9 -> 0
F10: =F9-D10+E10 -> 0
F11: =F10-D11+E11 -> 0
F12: =F11-D12+E12 -> 0
F13: =F12-D13+E13 -> 0
F14: =F13-D14+E14 -> 0
F15: =F14-D15+E15 -> 0
F16: =F15-D16+E16 -> 0
F17: =F16-D17+E17 -> 0
F18: =F17-D18+E18 -> 0
... F100: =F99-D100+E100 -> 0
A101: GRAND TOTAL | F101: =F100-D101+E101 -> 0

Sheet Alien Water( Lodhran)
A1: LEDGER
A3: Account Holder's Name | D3: Alien Water( Lodhran)
A4: Pg # | C4: Old reg(127)
A5: Date | B5: Ref No. | C5: Description | D5: Debit | E5: Credit | F5: Balance
A6: 21/04/24 | B6: F1453 | C6: Flim tech R.O Memb | E6: 52100 | F6: =E6-D6 -> 52100
A7: 45540 | C7: E.P | D7: 10000 | F7: =F6-D7+E7 -> 42100
A8: 14/9/24 | C8: cash deposit | D8: 10000 | F8: =F7-D8+E8 -> 32100
A9: 16/7/24 | C9: cash deposit | D9: 10000 | F9: =F8-D9+E9 -> 22100
A10: 13/4/25 | B10: H1133 | C10: Mem Shell Seal (2) | E10: 9700 | F10: =F9-D10+E10 -> 31800
A11: 13/4/25 | C11: IBFT | D11: 20000 | F11: =F10-D11+E11 -> 11800
F12: =F11-D12+E12 -> 11800
F13: =F12-D13+E13 -> 11800
A14: GRAND TOTAL | F14: =F13-D14+E14 -> 11800

Sheet Al Nemat Water
A1: LEDGER
A3: Account Holder's Name | D3: Al Nemat Water
A4: Pg #
A5: Date | B5: Ref No. | C5: Description | D5: Debit | E5: Credit | F5: Balance
C6: Opening Balnace | F6: =E6-D6 -> 0
F7: =F6-D7+E7 -> 0
F8: =F7-D8+E8 -> 0
F9: =F8-D9+E9 -> 0
F10: =F9-D10+E10 -> 0
A11: GRAND TOTAL | F11: =F10-D11+E11 -> 0

Sheet A.F Water
A1: LEDGER
A3: Account Holder's Name | D3: A.F Water
A4: Pg # | C4: Old Reg(172)
A5: Date | B5: Ref No. | C5: Description | D5: Debit | E5: Credit | F5: Balance
A6: 20/7/22 | C6: Old Balnace | E6: 10351 | F6: =E6-D6 -> 10351
F7: =F6-D7+E7 -> 10351
F8: =F7-D8+E8 -> 10351
F9: =F8-D9+E9 -> 10351
A10: GRAND TOTAL | F10: =F9-D10+E10 -> 10351

Sheet Aswad Sb
A1: LEDGER
A3: Account Holder's Name | D3: Aswad Sb
A4: Pg # | C4: Old Reg(106)
A5: Date | B5: Ref No. | C5: Description | D5: Debit | E5: Credit | F5: Balance
A6: 44571 | C6: PPF + PPF | E6: 270 | F6: =E6-D6 -> 270
A7: 18/1/23 | B7: 306 | C7: PPF | E7: 450 | F7: =E7-D7+F6 -> 720
A8: 44960 | B8: 911 | C8: GAC, CTO | E8: 1000 | F8: =E8-D8+F7 -> 1720
A9: 23/3/23 | B9: 1300 | C9: membrane100G | E9: 10550 | F9: =E9-D9+F8 -> 12270
A10: 45020 | B10: Exp Sh | C10: Cash Deposit | D10: 2000 | F10: =E10-D10+F9 -> 10270
A11: 44931 | B11: Exp Sh | C11: Cash Deposit | D11: 2000 | F11: =E11-D11+F10 -> 8270
A12: 44931 | B12: 1740 | C12: PPF | E12: 300 | F12: =E12-D12+F11 -> 8570
A13: 45177 | B13: E739 | C13: Cash Deposit | D13: 100 | F13: =E13-D13+F12 -> 8470
A14: 45086 | B14: E1092 | C14: Cash Deposit | D14: 1500 | F14: =E14-D14+F13 -> 6970
A15: 45148 | B15: Exp Sh | C15: Cash Deposit | D15: 1500 | F15: =E15-D15+F14 -> 5470
A16: 44968 | B16: E1808 | C16: Cash Deposit | D16: 1700 | F16: =E16-D16+F15 -> 3770
A17: 15/02/24 | B17: F762 | C17: PPF 10" | E17: 400 | F17: =E17-D17+F16 -> 4170
A18: 45385 | B18: Exp Sh | C18: Cash Deposit | D18: 400 | F18: =E18-D18+F17 -> 3770
A19: 45388 | B19: G50 | C19: Cash Deposit | D19: 1500 | F19: =E19-D19+F18 -> 2270
A20: 21/8/24 | B20: G897 | C20: Membrane100G, flow Valve,.. | E20: 9500 | F20: =E20-D20+F19 -> 11770
A21: 45300 | B21: Exp Sh | C21: Cash Deposit | D21: 5000 | F21: =E21-D21+F20 -> 6770
A22: 45361 | B22: Exp Sh | C22: Cash Deposit | D22: 3500 | F22: =E22-D22+F21 -> 3270
A23: 14/10/24 | B23: G1233 | C23: Simple Valve 6mm | E23: 600 | F23: =E23-D23+F22 -> 3870
A24: 15/1/25 | B24: H243 | C24: R.O Filteration | E24: 1700 | F24: =E24-D24+F23 -> 5570
A25: 13/3/25 | C25: Discount | D25: 1000 | F25: =E25-D25+F24 -> 4570
E26: 500 | F26: =E26-D26+F25 -> 5070
C27: Cash Deposit | D27: 2000 | F27: =E27-D27+F26 -> 3070
C28: Discount | D28: 70 | F28: =E28-D28+F27 -> 3000
A29: 45781 | B29: Exp Sh | C29: Cash Deposit | D29: 1500 | F29: =E29-D29+F28 -> 1500
A30: 45842 | B30: H1060 | C30: Flow Wall, Pipe6mm , R.O Set | E30: 2075 | F30: =E30-D30+F29 -> 3575
A31: 45753 | B31: H1944 | C31: PPF 10" | E31: 200 | F31: =E31-D31+F30 -> 3775
A32: 45753 | B32: Exp Sh | C32: Cash Deposit | D32: 1000 | F32: =E32-D32+F31 -> 2775
A33: 45696 | B33: Exp Sh | C33: Cash Deposit | D33: 1000 | F33: =E33-D33+F32 -> 1775
A34: GRAND TOTAL | F34: =E34-D34+F33 -> 1775

Sheet Ahsas Water 
A1: LEDGER
A3: Account Holder's Name | D3: Ahsas Water
A4: Pg # | C4: Old Reg (70)
A5: Date | B5: Ref No. | C5: Description | D5: Debit | E5: Credit | F5: Balance
A6: 45203 | C6: Old Balnace | E6: 100371 | F6: =E6-D6 -> 100371
F7: =E7-D7 -> 0
A8: GRAND TOTAL | F8: =E8-D8 -> 0

Sheet Asia Homeyo Store
A1: LEDGER
A3: Account Holder's Name | D3: Asia Homeo Store
A4: Pg # | C4: Old Reg (64)
A5: Date | B5: Ref No. | C5: Description | D5: Debit | E5: Credit | F5: Balance
A6: 15/06/22 | C6: Old Balnace | E6: 11250 | F6: =E6-D6 -> 11250
F7: =F6-D7+E7 -> 11250
F8: =F7-D8+E8 -> 11250
F9: =F8-D9+E9 -> 11250
A10: GRAND TOTAL | F10: =F9-D10+E10 -> 11250

Sheet Al Subhan Water
A1: LEDGER
A3: Account Holder's Name | D3: Al Subhan Water
A4: Pg # | C4: New Reg (28)
A5: Date | B5: Ref No. | C5: Description | D5: Debit | E5: Credit | F5: Balance
A6: 27/12/23 | B6: F320 | C6: 1.5L Bottle | E6: 10120 | F6: =E6-D6 -> 10120
B7: P | C7: 19L Bottle | D7: 13000 | F7: =F6-D7+E7 -> -2880
A8: 20/01/24 | B8: F521(Rashid) | C8: 1.5L Shoper,.. | E8: 1100 | F8: =F7-D8+E8 -> -1780
C9: adding 19L Bottle | E9: 1780 | F9: =F8-D9+E9 -> 0
F10: =F9-D10+E10 -> 0
F11: =F10-D11+E11 -> 0
A12: GRAND TOTAL | F12: =F11-D12+E12 -> 0

Sheet Barcly Water
A1: LEDGER
A3: Account Holder's Name | D3: Barcly
A4: Pg # | C4: New Reg (137)
A5: Date | B5: Ref No. | C5: Description | D5: Debit | E5: Credit | F5: Balance
C6: Old Balnace | E6: 217850 | F6: 217850
A7: 23/01/24 | B7: F543 | C7: 1.5L Bottle,.. | E7: 25450 | F7: =F6-D7+E7 -> 243300
A8: 24/01/24 | B8: F547 | C8: 1.5L+500 ml fill Pet | D8: 14250 | F8: =F7-D8+E8 -> 229050
A9: 29/01/24 | B9: F584 | C9: 500 ml Btl,.. | E9: 11080 | F9: =F8-D9+E9 -> 240130
A10: 45353 | B10: F618 | C10: 1.5L Bottle,.. | E10: 10450 | F10: =F9-D10+E10 -> 250580
A11: 45445 | B11: F664 | C11: Ca,30mm Caps,. | E11: 12600 | F11: =F10-D11+E11 -> 263180
A12: 45475 | B12: F671 | C12: 500 ml Btl,.. | E12: 42400 | F12: =F11-D12+E12 -> 305580
C13: Shahid Turbine Net Deposit | D13: 20000 | F13: =F12-D13+E13 -> 285580
C14: Uncle Farooq | D14: 125000 | F14: =F13-D14+E14 -> 160580
C15: Cash Dep to Customer Minus From Ledger | D15: 50000 | F15: =F14-D15+E15 -> 110580
A16: 45567 | C16: Net Cash Deposit | D16: 15000 | F16: =F15-D16+E16 -> 95580
C17: Mobile & Commision | D17: 50000 | F17: =F16-D17+E17 -> 45580
C18: Discount | D18: 6580 | F18: =F17-D18+E18 -> 39000
C19: Deposit | D19: 3000 | F19: =F18-D19+E19 -> 36000
A20: 45567 | B20: F690 | C20: Ca,Mg,Na,… | E20: 13500 | F20: =F19-D20+E20 -> 49500
A21: 45598 | B21: F702 | C21: 1.5L Bottle,.. | E21: 26740 | F21: =F20-D21+E21 -> 76240
A22: 15/02/24 | B22: F755 | C22: Ca,500 ml Bottle,.. | E22: 27170 | F22: =F21-D22+E22 -> 103410
A23: 17/02/24 | B23: F774 | C23: Washing Membrane with all chemicals,lab | E23: 5500 | F23: =F22-D23+E23 -> 108910
A24: 18/02/24 | B24: Purchase | C24: Fill Pet | D24: 14500 | F24: =F23-D24+E24 -> 94410
A25: 22/02/24 | B25: F842 | C25: Caps,Shoper,… | E25: 7262 | F25: =F24-D25+E25 -> 101672
C26: 6mm Wire | E26: 8000 | F26: =F25-D26+E26 -> 109672
A27: 29/02/24 | C27: Rcv From Bor | D27: 80000 | F27: =F26-D27+E27 -> 29672
A28: 29/02/24 | B28: F908 | C28: 1.5L Bottle,.. | E28: 6450 | F28: =F27-D28+E28 -> 36122
A29: 45354 | B29: F947 | C29: 1.5L Bottle,.. | E29: 56620 | F29: =F28-D29+E29 -> 92742
A30: 45385 | B30: F958 | C30: 1.5L Bottle,.. | E30: 17620 | F30: =F29-D30+E30 -> 110362
A31: 45446 | B31: F981 | C31: Ca,1.5L Shoper | E31: 3950 | F31: =F30-D31+E31 -> 114312
A32: 45446 | B32: F985 | C32: 500 ml Fill Pet (Purchase) | D32: 7000 | F32: =F31-D32+E32 -> 107312
A33: 45446 | B33: F985 | C33: 500 ml Bottle(Return) | D33: 3698 | F33: =F32-D33+E33 -> 103614
A34: 45446 | B34: F985 | C34: Rickshaw Rent | E34: 600 | F34: =F33-D34+E34 -> 104214
A35: 45476 | B35: F1002 | C35: 1.5L Bottle | E35: 11810 | F35: =F34-D35+E35 -> 116024
A36: 45538 | B36: F1026 | C36: Plant Washing Chemical +Labr | E36: 5500 | F36: =F35-D36+E36 -> 121524
A37: 23/02/24 | C37: Jazz Cash | D37: 7250 | F37: =F36-D37+E37 -> 114274
A38: 14/03/24 | B38: F1070 | C38: Washing with Chemicals+1abr | E38: 6000 | F38: =F37-D38+E38 -> 120274
C39: 19L Bottle(Rehan ) | E39: 5600 | F39: =F38-D39+E39 -> 125874
A40: 45599 | B40: F1039 | C40: 30 mm Caps,.. | E40: 3400 | F40: =F39-D40+E40 -> 129274
A41: 45568 | B41: F1021 | C41: 1.5L Bottle,.. | E41: 10000 | F41: =F40-D41+E41 -> 139274
A42: 45568 | C42: Return 7 Pet of 500 ml Bottle | D42: 8628 | F42: =F41-D42+E42 -> 130646
A43: 28/03/24 | B43: F1190 | C43: Ca,Mg | E43: 1800 | F43: =F42-D43+E43 -> 132446
A44: 31/03/24 | B44: F1216 | C44: Memb washing with chemical,.. | E44: 6550 | F44: =F43-D44+E44 -> 138996
A45: 45477 | C45: Remaining Pyment of 8 Panels | E45: 25000 | F45: =F44-D45+E45 -> 163996
A46: 45539 | B46: F1334 | C46: Ca, mg, Na | E46: 400 | F46: =F45-D46+E46 -> 164396
A47: 15/04/24 | B47: F1375 | C47: Ca, mg | E47: 1800 | F47: =F46-D47+E47 -> 166196
A48: 15/04/24 | B48: F1375 | C48: Paid Bill #F1375 when Deposited 30000 for 19L Pet Bottle | D48: 1800 | F48: =F47-D48+E48 -> 164396
C49: Pyment of Solar Panels | D49: 25000 | F49: =F48-D49+E49 -> 139396
A50: 23/04/24 | B50: F1481 | C50: Ca | E50: 1200 | F50: =F49-D50+E50 -> 140596
A51: 24/04/24 | B51: F1507 | C51: 19L Caps,.. | E51: 2850 | F51: =F50-D51+E51 -> 143446
A52: 25/04/24 | B52: F1510 | C52: 1.5L Bottle,.. | E52: 1670 | F52: =F51-D52+E52 -> 145116
A53: 24/04/24 | B53: F1497 | C53: Jambo PPF,.. | E53: 350 | F53: =F52-D53+E53 -> 145466
A54: 29/04/24 | B54: Exp Sh | C54: Cash Dep. | D54: 350 | F54: =F53-D54+E54 -> 145116
A55: 45417 | B55: F1643 | C55: Ca,Mg | E55: 1800 | F55: =F54-D55+E55 -> 146916
A56: 45509 | B56: F1696 | C56: Ca,Mg,Na | E56: 3000 | F56: =F55-D56+E56 -> 149916
C57: Nill | D57: 149916 | F57: =F56-D57+E57 -> 0
A58: 16/05/24 | B58: F1783 | C58: Na | E58: 600 | F58: =F57-D58+E58 -> 600
A59: 23/05/24 | B59: F1853 | C59: 19L Caps | E59: 500 | F59: =F58-D59+E59 -> 1100
A60: 23/05/24 | B60: F1877 | C60: Ca,na,Mg | E60: 1800 | F60: =F59-D60+E60 -> 2900
A61: 23/05/24 | B61: F1878 | C61: 19L pet bottle | E61: 35000 | F61: =F60-D61+E61 -> 37900
A62: 45450 | B62: G349 | C62: jinko mono 590W, 590*45, stand L2,L3 | E62: 147750 | F62: =F61-D62+E62 -> 185650
A63: 45450 | B63: G349 | C63: Deduct from Solar Commission | D63: 35000 | F63: =F62-D63+E63 -> 150650
A64: 28/7/24 | B64: Exp Sh | D64: 5000 | F64: =F63-D64+E64 -> 145650
A65: 25/8/24 | B65: G926 | C65: Remaining payment | E65: 1000 | F65: =F64-D65+E65 -> 146650
A66: 24/8/24 | B66: G919 | C66: Ca, Mg | E66: 1950 | F66: =F65-D66+E66 -> 148600
A67: 45361 | B67: G1129 | C67: 19L Caps, 19L Lids, Ca, Mg, Na, Antiscalar, PPF Slim | E67: 5000 | F67: =F66-D67+E67 -> 153600
A68: 45422 | C68: E.P | D68: 5000 | F68: =F67-D68+E68 -> 148600
C69: Old Balance of Solar | D69: 50000 | F69: =F68-D69+E69 -> 98600
A70: 22/1/25 | B70: H303 | C70: Remaining Amount | E70: 650 | F70: =F69-D70+E70 -> 99250
A71: 25/1/25 | C71: Repairing of Inverters 2 times | E71: 18000 | F71: =F70-D71+E71 -> 117250
C72: Mobile Installment | E72: 20000 | F72: =F71-D72+E72 -> 137250
F73: =F72-D73+E73 -> 137250
F74: =F73-D74+E74 -> 137250
F75: =F74-D75+E75 -> 137250
F76: =F75-D76+E76 -> 137250
A77: GRAND TOTAL | F77: =F76-D77+E77 -> 137250

Sheet Bling Water
A1: LEDGER
A3: Account Holder's Name | D3: Bling Water
A4: Pg # | C4: Old Reg(96)
A5: Date | B5: Ref No. | C5: Description | D5: Debit | E5: Credit | F5: Balance
A6: 21/01/24 | B6: F527 | C6: 1.5L Shoper,.. | E6: 12500 | F6: =E6-D6 -> 12500
A7: 21/01/24 | C7: Easypaisa | D7: 12000 | F7: =F6-D7+E7 -> 500
A8: 45475 | B8: F676 | C8: 500 ml Shoper | E8: 5370 | F8: =F7-D8+E8 -> 5870
A9: 45568 | B9: F1029 | C9: 6L Bottle,.. | E9: 7400 | F9: =F8-D9+E9 -> 13270
A10: 45476 | B10: F1030 | C10: 1.5L Bottle | E10: 1190 | F10: =F9-D10+E10 -> 14460
A11: 19/03/24 | B11: Exp Sh | C11: Net Cash Dep | D11: 10000 | F11: =F10-D11+E11 -> 4460
A12: 23/04/24 | B12: F1495 | C12: 1.5L Shoper,.. | E12: 2700 | F12: =F11-D12+E12 -> 7160
A13: 24/04/24 | B13: F1505 | C13: 1.5L, Ozonator new | E13: 98370 | F13: =F12-D13+E13 -> 105530
A14: 24/04/24 | B14: F1505 | C14: IBFT (1000 Cash) | D14: 75000 | F14: =F13-D14+E14 -> 30530
A15: 23/05/24 | B15: F1862 | C15: 19L Pet Bottle,.. | E15: 2300 | F15: =F14-D15+E15 -> 32830
F16: =F15-D16+E16 -> 32830
A17: GRAND TOTAL | F17: =F16-D17+E17 -> 32830

Sheet Bissimillah Senitary 
A1: LEDGER
A3: Account Holder's Name | D3: Bissimillah Senitary
A4: Pg # | C4: Old Reg(154)
A5: Date | B5: Ref No. | C5: Description | D5: Debit | E5: Credit | F5: Balance
A6: 44843 | B6: 3668 | C6: 10" PPF Local | E6: 3624 | F6: 3624
F7: =F6-D7+E7 -> 3624
A8: GRAND TOTAL | F8: =F7-D8+E8 -> 3624

Sheet Berg Water New
A1: LEDGER
A3: Account Holder's Name | D3: Berg Water
A4: Pg # | C4: old Reg(146)
A5: Date | B5: Ref No. | C5: Description | D5: Debit | E5: Credit | F5: Balance
A6: 45694 | B6: H1901 | C6: Remaining Amount of Ampler, Bot Seal, Labour | E6: 7500 | F6: =E6-D6 -> 7500
A7: 22/6/25 | B7: I 69 | C7: Remaining Amount | E7: 7000 | F7: =F6-D7+E7 -> 14500
F12: =F7-D12+E12 -> 14500
A13: GRAND TOTAL | F13: =F12-D13+E13 -> 14500

Sheet Berg Water
A1: LEDGER
A3: Account Holder's Name | D3: Berg Water
A4: Pg # | C4: old Reg(146)
A5: Date | B5: Ref No. | C5: Description | D5: Debit | E5: Credit | F5: Balance
A6: 23/10/23 | C6: Old Balnace | E6: 57984 | F6: =E6 -> 57984
C7: Window work | D7: 13000 | F7: =E7 -> 0
A8: 18/9/24 | B8: G863 | C8: 19L Caps, 19L Lids, 19L Seal | E8: 2750 | F8: =E8 -> 2750
A9: 30/10/24 | B9: G1370 | C9: 19L Caps | E9: 550 | F9: =E9 -> 550
A10: 31/10/24 | B10: G1376 | C10: 19L Caps, 19L Lids, 19L Seal, 19L Bush | E10: 9050 | F10: =E10 -> 9050
A11: 31/10/24 | B11: G1383 | C11: 1.5L - Caps | E11: 3450 | F11: =E11 -> 3450
A12: 45576 | C12: Discount | D12: 15784 | F12: =E12 -> 0
A13: 45576 | C13: Amount Deposited from Machine | D13: 20000 | F13: =E13 -> 0
A14: 16/11/24 | D14: 25000 | F14: =E14 -> 0
A15: 45694 | B15: H1901 | C15: Remaining Amount of Ampler, Bot Seal, Labour | E15: 7500 | F15: =E15 -> 7500
A16: 22/6/25 | B16: I 69 | C16: Remaining Amount | E16: 7000 | F16: =E16 -> 7000
F17: =E17 -> 0
F18: =E18 -> 0
F19: =E19 -> 0
F20: =E20 -> 0
F21: =E21 -> 0
A22: GRAND TOTAL | F22: =E22 -> 0

Sheet Blue Ice 
A1: LEDGER
A3: Account Holder's Name | D3: Blue Ice
A4: Pg #
A5: Date | B5: Ref No. | C5: Description | D5: Debit | E5: Credit | F5: Balance
C6: Opening Balnace | F6: =E6-D6 -> 0
A7: 16/7/24 | B7: G440 | C7: Jumbo hozing, antiscaler | E7: 4050 | F7: =F6-D7+E7 -> 4050
F8: =F7-D8+E8 -> 4050
A9: GRAND TOTAL | F9: =F8-D9+E9 -> 4050

Sheet Bwp Water
A1: LEDGER
A3: Account Holder's Name | D3: Bwp Water
A4: Pg # | C4: Old Reg(109)
A5: Date | B5: Ref No. | C5: Description | D5: Debit | E5: Credit | F5: Balance
A6: 28/5/21 | C6: Old Balnace | E6: 5240 | F6: =E6-D6 -> 5240
A7: 21/11/24 | B7: G1588 | C7: 1.5L + Caps, 1.5L Shoper | E7: 3175 | F7: =F6-D7+E7 -> 8415
A8: 45902 | B8: Exp Sh | C8: Cash deposit | D8: 1000 | F8: =F7-D8+E8 -> 7415
F9: =F8-D9+E9 -> 7415
A10: GRAND TOTAL | F10: =F9-D10+E10 -> 7415

Sheet BWMC
A1: LEDGER
A3: Account Holder's Name | D3: BWMC
A4: Pg # | C4: New Reg (59)
A5: Date | B5: Ref No. | C5: Description | D5: Debit | E5: Credit | F5: Balance
A6: 26/06/23 | B6: E92 | C6: F.M Socket,.. | E6: 13000 | F6: =E6-D6 -> 13000
A7: 45206 | B7: E355 | C7: Gate Valve,… | E7: 2500 | F7: =F6-D7+E7 -> 15500
A8: 45267 | B8: E383 | C8: PPf Slim,.. | E8: 2500 | F8: =F7-D8+E8 -> 18000
A9: 45267 | C9: IBFT | D9: 10000 | F9: =F8-D9+E9 -> 8000
A10: 21/10/23 | C10: IBFT | D10: 7000 | F10: =F9-D10+E10 -> 1000
F11: =F10-D11+E11 -> 1000
A12: GRAND TOTAL | F12: =F11-D12+E12 -> 1000

Sheet Chand Agro
A1: LEDGER
A3: Account Holder's Name | D3: Chand Agro Chemicals
A4: Pg # | C4: New Reg(167)
A5: Date | B5: Ref No. | C5: Description | D5: Debit | E5: Credit | F5: Balance
A6: 44754 | B6: 723 | C6: PPF 10",.. | E6: 1300 | F6: =E6-D6 -> 1300
A7: 44753 | B7: 724 | C7: PPF 10",.. | E7: 1300 | F7: =F6-D7+E7 -> 2600
A8: 44815 | B8: 759 | C8: Carbon Stage,.. | E8: 7700 | F8: =F7-D8+E8 -> 10300
A9: 15/11/22 | B9: 846 | C9: Jambo PPf,.. | E9: 8080 | F9: =F8-D9+E9 -> 18380
A10: 16/11/22 | B10: 857 | C10: Slim PPf,.. | E10: 2500 | F10: =F9-D10+E10 -> 20880
A11: 13/12/22 | B11: 1236 | E11: 10600 | F11: =F10-D11+E11 -> 31480
A12: 20/02/23 | B12: 756 | C12: Half Ton Plant Membrane Washing | E12: 5000 | F12: =F11-D12+E12 -> 36480
A13: 45233 | B13: 1052 | C13: Jambo PPf,.. | E13: 6500 | F13: =F12-D13+E13 -> 42980
A14: 18/03/23 | B14: 1564 | C14: 2 Ton RO Plant | E14: 850000 | F14: =F13-D14+E14 -> 892980
A15: 45082 | B15: 1813 | C15: Jambo PPf | E15: 15000 | F15: =F14-D15+E15 -> 907980
A16: 44964 | B16: E172 | C16: HP Pump4*12,.. | E16: 20000 | F16: =F15-D16+E16 -> 927980
A17: 44966 | B17: E1022 | C17: PPF 10",.. | E17: 1500 | F17: =F16-D17+E17 -> 929480
B18: Solar Bills | C18: Office Solar Plant | E18: 1695700 | F18: =F17-D18+E18 -> 2625180
C19: Usman Sb(House) | E19: 772700 | F19: =F18-D19+E19 -> 3397880
C20: CAC 61DB(Madrasa) | E20: 483100 | F20: =F19-D20+E20 -> 3880980
C21: Ch Sarwar House | E21: 755650 | F21: =F20-D21+E21 -> 4636630
C22: Chand Agro Lab | E22: 97300 | F22: =F21-D22+E22 -> 4733930
C23: Net Metring Factory+Home | E23: 375000 | F23: =F22-D23+E23 -> 5108930
C24: Cheque Rcv | D24: 500000 | F24: =F23-D24+E24 -> 4608930
C25: Cheque Rcv | D25: 500000 | F25: =F24-D25+E25 -> 4108930
C26: Cash Rcv | D26: 400000 | F26: =F25-D26+E26 -> 3708930
C27: Car | D27: 725000 | F27: =F26-D27+E27 -> 2983930
A28: 27/09/23 | B28: F1389 | C28: washing Chemical,.. | E28: 7000 | F28: =F27-D28+E28 -> 2990930
A29: 30/09/23 | B29: F1418 | C29: 500 ml Bottle,.. | E29: 3200 | F29: =F28-D29+E29 -> 2994130
A30: 45056 | B30: F1510 | C30: Chemicals,.. | E30: 13500 | F30: =F29-D30+E30 -> 3007630
A31: 14/11/23 | B31: F1928 | C31: Pump Amparrel,.. | E31: 13500 | F31: =F30-D31+E31 -> 3021130
A32: 18/11/23 | B32: F1951 | C32: Union 1",.. | E32: 1240 | F32: =F31-D32+E32 -> 3022370
A33: 45089 | B33: F112 | C33: PPF 10",.. | E33: 1500 | F33: =F32-D33+E33 -> 3023870
A34: 17/01/24 | B34: F528 | C34: washing Chemical,.. | E34: 9500 | F34: =F33-D34+E34 -> 3033370
A35: 17/01/24 | B35: F528 | C35: Cash Deposit | D35: 10000 | F35: =F34-D35+E35 -> 3023370
C36: Vagan R | D36: 1750000 | F36: =F35-D36+E36 -> 1273370
C37: Discount | D37: 173370 | F37: =F36-D37+E37 -> 1100000
A38: 28/02/24 | B38: F901 | C38: Wasing Chemical+Labr | E38: 9000 | F38: =F37-D38+E38 -> 1109000
A39: 45415 | C39: Baba Khursheed wala jo abhi ana ha | D39: 100000 | F39: =F38-D39+E39 -> 1009000
C40: Cheque Rcv Already | D40: 100000 | F40: =F39-D40+E40 -> 909000
C41: Garu Vagan R | D41: 125000 | F41: =F40-D41+E41 -> 784000
C42: Tracktor 2 adad | D42: 40000 | F42: =F41-D42+E42 -> 744000
C43: Tracktor fee 2 Garian | D43: 14000 | F43: =F42-D43+E43 -> 730000
C44: Cheque Rcv | D44: 736000 | F44: =F43-D44+E44 -> -6000
C45: Nill | E45: 6000 | F45: =F44-D45+E45 -> 0
A46: 45568 | B46: F1027 | C46: New vessel 16*65,.. | E46: 38500 | F46: =F45-D46+E46 -> 38500
A47: 16/04/24 | B47: F1388 | C47: Memb washing Chemical,.. | E47: 5500 | F47: =F46-D47+E47 -> 44000
A48: 28/04/24 | B48: F1551 | C48: washing memb 137,.. | E48: 52100 | F48: =F47-D48+E48 -> 96100
A49: 45478 | B49: F1671 | C49: Multi Port Valve | E49: 9000 | F49: =F48-D49+E49 -> 105100
A50: 23/05/24 | B50: F1852 | C50: Wall Socket 1*1/4",.. | E50: 870 | F50: =F49-D50+E50 -> 105970
A51: 23/05/24 | B51: F1855 | C51: Wall Socket 1*1/2",.. | E51: 2470 | F51: =F50-D51+E51 -> 108440
A52: 26/05/24 | B52: F1312 | C52: Memb washing Chemical,.. | E52: 5500 | F52: =F51-D52+E52 -> 113940
A53: 30/05/24 | B53: F1985 | C53: Inverter Rep Fronus | E53: 4000 | F53: =F52-D53+E53 -> 117940
A54: 45602 | B54: G110 | C54: Jumbo PPF | E54: 1500 | F54: =F53-D54+E54 -> 119440
A55: 20/6/24 | B55: G198 | C55: 500ml B+C+L | E55: 10000 | F55: =F54-D55+E55 -> 129440
A56: 20/7/24 | B56: G454 | C56: PPF 10",.. | E56: 1100 | F56: =F55-D56+E56 -> 130540
C57: Received from Car Amount | D57: 130540 | F57: =F56-D57+E57 -> 0
A58: 45660 | B58: H687 | C58: R.O Set | E58: 1500 | F58: =F57-D58+E58 -> 1500
A59: 45660 | B59: H688 | C59: Solar Labour | E59: 1000 | F59: =F58-D59+E59 -> 2500
F60: =F59-D60+E60 -> 2500
F61: =F60-D61+E61 -> 2500
F62: =F61-D62+E62 -> 2500
F63: =F62-D63+E63 -> 2500
F64: =F63-D64+E64 -> 2500
F65: =F64-D65+E65 -> 2500
F66: =F65-D66+E66 -> 2500
F67: =F66-D67+E67 -> 2500
F68: =F67-D68+E68 -> 2500
A69: GRAND TOTAL | F69: =F68-D69+E69 -> 2500

Sheet Clean & Clean
A1: LEDGER
A3: Account Holder's Name | D3: Clean & Clean
A4: Pg # | C4: Old Reg(97)
A5: Date | B5: Ref No. | C5: Description | D5: Debit | E5: Credit | F5: Balance
A6: 45088 | C6: Old Balance | E6: 37270 | F6: =E6-D6 -> 37270
F7: =F6-D7+E7 -> 37270
F8: =F7-D8+E8 -> 37270
F9: =F8-D9+E9 -> 37270
F10: =F9-D10+E10 -> 37270
F11: =F10-D11+E11 -> 37270
F12: =F11-D12+E12 -> 37270
A13: GRAND TOTAL | F13: =F12-D13+E13 -> 37270

Sheet Candy Water
A1: LEDGER
A3: Account Holder's Name | D3: Candy Water
A4: Pg # | C4: Old Reg(159)
A5: Date | B5: Ref No. | C5: Description | D5: Debit | E5: Credit | F5: Balance
A6: 23/11/23 | C6: Old Balance | E6: 26950 | F6: =E6-D6 -> 26950
A7: 18/01/24 | B7: F507 | C7: Auto Switch | E7: 8000 | F7: =F6-D7+E7 -> 34950
A8: 29/01/24 | B8: Purchase | C8: 5L Bottle (4000 btl,Rate=32/-) | D8: 128000 | F8: =F7-D8+E8 -> -93050
A9: 45384 | C9: IBFT(Send to customer acc) | E9: 100000 | F9: =F8-D9+E9 -> 6950
A10: 20/02/24 | B10: F816 | C10: Jambo PPF,.. | E10: 7450 | F10: =F9-D10+E10 -> 14400
A11: 45325 | B11: F940 | C11: 19L Caps | E11: 13300 | F11: =F10-D11+E11 -> 27700
A12: 45325 | B12: Exp Sh | C12: Cash Deposit | D12: 20000 | F12: =F11-D12+E12 -> 7700
A13: 19/05/24 | C13: Plant Rep, New Memb ,etc | E13: 91500 | F13: =F12-D13+E13 -> 99200
A14: 45357 | B14: G31 | C14: Mg,Na | E14: 2200 | F14: =F13-D14+E14 -> 101400
A15: 45389 | B15: G341 | C15: Chlorine tab, Mg,Na | E15: 6500 | F15: =F14-D15+E15 -> 107900
A16: 26/9/24 | B16: G1064 | E16: 5500 | F16: =F15-D16+E16 -> 113400
D17: 5000 | F17: =F16-D17+E17 -> 108400
A18: 17/10/24 | B18: G1265 | E18: 4500 | F18: =F17-D18+E18 -> 112900
A19: 45516 | B19: Qazi sb | C19: IBFT received | D19: 50000 | F19: =F18-D19+E19 -> 62900
A20: 18/5/25 | B20: H1692 | C20: Absolute 20", Jumbo PPF | E20: 4750 | F20: =F19-D20+E20 -> 67650
A21: 24/6/2025 | B21: We Recived | C21: 1.5L Bottles 70*30 Packet | D21: 22260 | F21: =F20-D21+E21 -> 45390
C22: 0.5L Bottles 170*15 Packet | D22: 16830 | F22: =F21-D22+E22 -> 28560
B23: We Recived | C23: 6L Bottles 18*120 Packet | D23: 82080 | F23: =F22-D23+E23 -> -53520
C24: 5L bottles 20*30 Packet | D24: 22200 | F24: =F23-D24+E24 -> -75720 | G24: 143370
A25: 45881 | C25: IBFT | E25: 50000 | F25: =F24-D25+E25 -> -25720
A26: 45667 | B26: I 1474 | C26: 30mm caps…. | E26: 23400 | F26: =F25-D26+E26 -> -2320
F27: =F26-D27+E27 -> -2320
F28: =F27-D28+E28 -> -2320
F29: =F28-D29+E29 -> -2320
A30: GRAND TOTAL | F30: =F29-D30+E30 -> -2320

Sheet Crystal Water Bagouchi Pull
A1: LEDGER
A3: Account Holder's Name | D3: Crystal Water Bagouchi Pull
A4: Pg # | C4: Old Reg(94)
A5: Date | B5: Ref No. | C5: Description | D5: Debit | E5: Credit | F5: Balance
A6: 45241 | C6: Old Balance | E6: 5570 | F6: =E6-D6 -> 5570
F7: =F6-D7+E7 -> 5570
A8: GRAND TOTAL | F8: =F7-D8+E8 -> 5570

Sheet Dar e Arqam 
A1: LEDGER
A3: Account Holder's Name | D3: Dar e Arqam
A4: Pg # | C4: New Reg(24)
A5: Date | B5: Ref No. | C5: Description | D5: Debit | E5: Credit | F5: Balance
C6: Opening Balnace | E6: 3050 | F6: =E6-D6 -> 3050
C7: Kids School fees | D7: 3050 | F7: =F6-D7+E7 -> 0
F8: =F7-D8+E8 -> 0
A9: GRAND TOTAL | F9: =F8-D9+E9 -> 0

Sheet 1
A1: LEDGER
A3: Account Holder's Name | D3: Chand Agro
A4: Pg #
A5: Date | B5: Ref No. | C5: Description | D5: Debit | E5: Credit | F5: Balance
C6: Car Vaganr Amount | D6: 1800000 | F6: =E6-D6 -> -1800000
A7: 20/7/2024 | C7: Costomer Ledger | E7: 130540 | F7: =F6-D7+E7 -> -1669460
A8: 45603 | C8: Membranes 8*40 | E8: 250000 | F8: =F7-D8+E8 -> -1419460
A9: 45603 | C9: Media Change with Iron Removal, Gravels+Sand | E9: 25000 | F9: =F8-D9+E9 -> -1394460
A10: 15/5/2025 | C10: Old Balance of Cheque | E10: 736000 | F10: =F9-D10+E10 -> -658460
A11: 30/7/2024 | C11: Remaining Amount from Quotation for Zubair sb Yazman Madarsa | E11: 402820 | F11: =F10-D11+E11 -> -255640
A12: 45893 | C12: Solar Remaning Amount of Usman sb House Yazman | E12: 72000 | F12: =F11-D12+E12 -> -183640
A13: 45660 | B13: H 687 | C13: R.O Filtration | E13: 1500 | F13: =F12-D13+E13 -> -182140
A14: 45660 | B14: H 688 | C14: Solar Labour | E14: 1000 | F14: =F13-D14+E14 -> -181140
A15: 20/4/2025 | B15: H 1280 | C15: Mem 100G, Flow Valve, R.O Filtration System | E15: 7700 | F15: =F14-D15+E15 -> -173440
A16: 45783 | B16: H1965 | C16: 500ml + Caps | E16: 8670 | F16: =F15-D16+E16 -> -164770
C17: Total Payable Amount= 164770 | F17: =F16-D17+E17 -> -164770

Sheet Ever Best
A1: LEDGER
A3: Account Holder's Name | D3: Ever Best
A4: Pg # | C4: Old Reg(104)
A5: Date | B5: Ref No. | C5: Description | D5: Debit | E5: Credit | F5: Balance
A6: 17/04/22 | C6: Old Balnace | E6: 16664 | F6: =E6-D6 -> 16664
F7: =F6-D7+E7 -> 16664
A8: GRAND TOTAL | F8: =F7-D8+E8 -> 16664

Sheet Qari ajmal Sb
A1: LEDGER
A3: Account Holder's Name | D3: Qari Ajmal sb
A4: Pg # | C4: New Reg (60)
A5: Date | B5: Ref No. | C5: Description | D5: Debit | E5: Credit | F5: Balance
C6: Old Balance | E6: 3070 | F6: =E6-D6 -> 3070
A7: 13/02/24 | B7: Exp Sh | C7: Cash Deposit | D7: 1300 | F7: =F6-D7+E7 -> 1770
A8: 25/05/24 | B8: F1881 | C8: 1.5L Botthle | E8: 200 | F8: =F7-D8+E8 -> 1970
A9: 45421 | B9: G644 | C9: 500ml + Caps, 500ml Shoper | E9: 340 | F9: =F8-D9+E9 -> 2310
A10: 45422 | B10: G1139 | C10: Remaining Amount | E10: 515 | F10: =F9-D10+E10 -> 2825
A11: 21/10/24 | B11: G1287 | C11: Remaining Amount | E11: 700 | F11: =F10-D11+E11 -> 3525
A12: 45362 | B12: G1410 | C12: 5L E+ C | E12: 83 | F12: =F11-D12+E12 -> 3608
A13: 16/2/25 | B13: H546 | C13: Remaining Amount | E13: 545 | F13: =F12-D13+E13 -> 4153
A14: 20/2/25 | B14: Exp Sh | C14: Cash Deposit | D14: 550 | F14: =F13-D14+E14 -> 3603
A15: 45720 | B15: H1004 | C15: Remaining Amount | E15: 160 | F15: =F14-D15+E15 -> 3763
A16: 29/4/25 | B16: H1409 | C16: Remaining Amount | E16: 215 | F16: =F15-D16+E16 -> 3978
F17: =F16-D17+E17 -> 3978
F18: =F17-D18+E18 -> 3978
A19: GRAND TOTAL | F19: =F18-D19+E19 -> 3978

Sheet 2
A1: LEDGER
A3: Account Holder's Name | D3: Chand Agro
A4: Pg #
A5: Date | B5: Ref No. | C5: Description | D5: Debit | E5: Credit | F5: Balance
C6: 3 Cars dobule Biomatric | E6: 69000 | F6: =E6-D6 -> 69000
C7: 1 Car Single Biomatric | E7: 27000 | F7: =E7-D7 -> 27000
C8: Total | E8: 92000 | F8: =E8-D8 -> 92000
C9: Number Plates | E9: 150000 | F9: =E9-D9 -> 150000
C10: Biscuts (Chases Number Plates 2 Cars | E10: 50000 | F10: =E10-D10 -> 50000
C11: Total | E11: 296000 | F11: =E11-D11 -> 296000
C12: Total Receivable Amount = 296,000 | F12: =E12-D12 -> 0

Sheet Haji Yousaf Sb
A1: LEDGER
A3: Account Holder's Name | D3: Haji Yousaf Sb
A4: Pg # | C4: New Reg(89)
A5: Date | B5: Ref No. | C5: Description | D5: Debit | E5: Credit | F5: Balance
A6: 45022 | C6: Old Balance | E6: 39838 | F6: =E6-D6 -> 39838
F7: =F6-D7+E7 -> 39838
A8: GRAND TOTAL | F8: =F7-D8+E8 -> 39838

Sheet Honey Water Dr Jameel
A1: LEDGER
A3: Account Holder's Name | D3: Honey Water Dr Jameel
A4: Pg # | C4: New Reg(90)
A5: Date | B5: Ref No. | C5: Description | D5: Debit | E5: Credit | F5: Balance
A6: 28/10/24 | B6: G1354 | E6: 15415 | F6: =E6-D6 -> 15415
D7: 6500 | F7: =F6-D7+E7 -> 8915
A8: 14/6/25 | B8: Exp Sh | C8: Cash deposited | D8: 1250 | F8: =F7-D8+E8 -> 7665
A9: 15/6/25 | B9: H155 | C9: Remaining Amount | E9: 13575 | F9: =F8-D9+E9 -> 21240
A10: 17/6/25 | B10: H200 | C10: 500ml-Caps, 1.5L-Caps, 1.5L Shoper, 500ml Shoper, 30mm Caps | E10: 22087 | F10: =F9-D10+E10 -> 43327
A11: 17/6/25 | B11: Exp Sh | C11: Cash deposited | D11: 10000 | F11: =F10-D11+E11 -> 33327
A12: 17/6/25 | B12: Exp Sh | C12: Cash deposited | D12: 3000 | F12: =F11-D12+E12 -> 30327
A13: 17/6/25 | B13: Exp Sh | C13: Cash deposited | D13: 500 | F13: =F12-D13+E13 -> 29827
A14: 19/6/25 | B14: I 39 | C14: 1.5L Caps, 500ml Caps,1.5L shoper,…. | E14: 14599 | F14: =F13-D14+E14 -> 44426
A15: 19/6/25 | B15: Exp Sh | C15: Cash deposited | D15: 22000 | F15: =F14-D15+E15 -> 22426
A16: 21/6/25 | B16: I59 | C16: 1.5L Shoper, 500ml Seal | E16: 1900 | F16: =F15-D16+E16 -> 24326
A17: 22/6/25 | B17: Exp Sh | C17: Cash deposited | D17: 7600 | F17: =F16-D17+E17 -> 16726
A18: 22/6/25 | B18: Exp Sh | C18: IBFT | D18: 5400 | F18: =F17-D18+E18 -> 11326
A19: 24/6/25 | B19: I 72 | C19: 1.5L Seal, 1.5L Shoper | E19: 2800 | F19: =F18-D19+E19 -> 14126
A20: 24/6/25 | B20: Exp Sh | C20: Cash deposited | D20: 3500 | F20: =F19-D20+E20 -> 10626
A21: 25/6/25 | B21: Exp Sh | C21: IBFT+ Cash | D21: 2800 | F21: =F20-D21+E21 -> 7826
A22: 25/6/25 | B22: I 93 | C22: Remaining Amount | E22: 6932 | F22: =F21-D22+E22 -> 14758
A23: 30/6/25 | B23: Exp Sh | C23: Cash deposited | D23: 6000 | F23: =F22-D23+E23 -> 8758
A24: 45723 | B24: I 209 | C24: 500ml seal, 1.5L Seal | E24: 2600 | F24: =F23-D24+E24 -> 11358
A25: 45876 | B25: I 266 | C25: 30mm Caps, 1.5L Shoper, 500nl Shoper | E25: 4250 | F25: =F24-D25+E25 -> 15608
A26: 45876 | B26: Exp Sh | C26: Cash deposited | D26: 2600 | F26: =F25-D26+E26 -> 13008
A27: 45876 | B27: Exp Sh | C27: IBFT | D27: 6000 | F27: =F26-D27+E27 -> 7008
A28: 45937 | B28: I 299 | C28: Remaining Amount | E28: 4566 | F28: =F27-D28+E28 -> 11574
A29: 45998 | B29: I 327 | C29: 1.5L-Caps, 1.5L Seal, 1.5L Shoper | E29: 7777 | F29: =F28-D29+E29 -> 19351
A30: 45998 | B30: Exp Sh | C30: IBFT + Cash | D30: 4500 | F30: =F29-D30+E30 -> 14851
A31: 16/7/25 | B31: I 374 | C31: Remaining Amount | E31: 5480 | F31: =F30-D31+E31 -> 20331
A32: 15/7/25 | B32: Exp Sh | C32: IBFT | D32: 2700 | F32: =F31-D32+E32 -> 17631
A33: 20/7/25 | B33: I 417 | C33: Cash deposited | D33: 1371 | F33: =F32-D33+E33 -> 16260
A34: 26/7/25 | B34: I 493 | C34: Remaining Amount | E34: 11009 | F34: =F33-D34+E34 -> 27269
A35: 26/7/25 | B35: Exp Sh | C35: Cash deposited | D35: 4300 | F35: =F34-D35+E35 -> 22969
A36: 26/7/25 | B36: Exp Sh | C36: Cash deposited | D36: 2500 | F36: =F35-D36+E36 -> 20469
A37: 28/7/25 | B37: I 524 | C37: 1.5L -Caps, 500ml -Caps, 1.5L Shoper,… | E37: 16929 | F37: =F36-D37+E37 -> 37398
A38: 28/7/25 | B38: Exp Sh | C38: Cash deposited | D38: 8000 | F38: =F37-D38+E38 -> 29398
F39: =F38-D39+E39 -> 29398
F40: =F39-D40+E40 -> 29398
F41: =F40-D41+E41 -> 29398
F42: =F41-D42+E42 -> 29398
A43: GRAND TOTAL | F43: =F42-D43+E43 -> 29398

Sheet Hunza Water 
A1: LEDGER
A3: Account Holder's Name | D3: Hunza Water
A4: Pg # | C4: New Reg(73)
A5: Date | B5: Ref No. | C5: Description | D5: Debit | E5: Credit | F5: Balance
A6: 45231 | C6: Old Balance | E6: 8200 | F6: =E6-D6 -> 8200
A7: 45567 | B7: F695 | C7: 19L Caps | E7: 1100 | F7: =F6-D7+E7 -> 9300
A8: 27/02/24 | B8: F883 | C8: Cash Deposit | D8: 800 | F8: =F7-D8+E8 -> 8500
F9: =F8-D9+E9 -> 8500
F10: =F9-D10+E10 -> 8500
F11: =F10-D11+E11 -> 8500
A12: GRAND TOTAL | F12: =F11-D12+E12 -> 8500

Sheet Hayat Royal Water
A1: Ledger | M1: L+B23+A1+A1:F20
A3: Account Holder's Name | D3: Hayat Royal Water | M3: Account Holder's Name | P3: Hayat Royal Water
A4: Pg # | C4: New Reg(178) | M4: Pg # | O4: old Reg(83)
A5: Date | B5: Ref No. | C5: Description | D5: Debit | E5: Credit | F5: Balance | M5: Date | N5: Ref No. | O5: Description | P5: Debit | Q5: Credit | R5: Balance
C6: Old Balance | E6: 91551
M7: 45180 | O7: Old Balance | Q7: 91121 | R7: =Q7-P7 -> 91121
A8: 45394 | B8: G1700 | C8: Remaining amount | F8: =F7-D8+E8 -> 0 | M8: 25/01/24 | N8: F553 | O8: 500 ml Btl,.. | Q8: 6140 | R8: =R7-P8+Q8 -> 97261
A9: 20/11/24 | B9: G1569 | C9: Remaining amount | E9: 4525 | F9: =F8-D9+E9 -> 4525 | M9: 27/01/24 | N9: Exp Sh | O9: Cash Deposit | P9: 4000 | R9: =R8-P9+Q9 -> 93261
A10: 23/11/24 | B10: exp sh | C10: Cash deposited | D10: 1200 | F10: =F9-D10+E10 -> 3325
A11: 45516 | B11: exp sh | C11: Cash deposited | D11: 4000 | F11: =F10-D11+E11 -> -675
A12: 45485 | B12: G1730 | C12: 1.5L- Caps, 30mm Caps, 1.5L Shoper | E12: 2625 | F12: =F11-D12+E12 -> 1950
A13: 45638 | B13: G1761 | C13: Remaining amount | E13: 1415 | F13: =F12-D13+E13 -> 3365
A14: 19/12/24 | B14: G1825 | C14: Remaining amount | E14: 400 | F14: =F13-D14+E14 -> 3765
A15: 23/12/24 | B15: G1861 | C15: 500ml -Caps, 30mm Caps | E15: 1775 | F15: =F14-D15+E15 -> 5540
A16: 29/12/24 | B16: G1912 | C16: 6L+Caps | E16: 1476 | F16: =F15-D16+E16 -> 7016
A17: 31/12/24 | B17: G1926 | C17: 6L+Caps | E17: 1476 | F17: =F16-D17+E17 -> 8492 | M17: 27/01/24 | N17: Exp Sh | O17: Easypaisa | P17: 2000 | R17: =R9-P17+Q17 -> 91261
A18: 31/12/24 | B18: G1929 | C18: 6L+Caps | E18: 738 | F18: =F17-D18+E18 -> 9230 | M18: 28/01/24 | N18: F572 | O18: Cash Deposit | P18: 160 | R18: =R17-P18+Q18 -> 91101
A19: 45658 | B19: H08 | C19: Remaining amount | E19: 1899 | F19: =F18-D19+E19 -> 11129 | M19: 14/02/24 | N19: Exp Sh | O19: Cash Deposit | P19: 1000 | R19: =R18-P19+Q19 -> 90101
A20: 45748 | B20: H28 | C20: 6L+Caps | E20: 738 | F20: =F19-D20+E20 -> 11867 | M20: 21/7/24 | N20: G468 | O20: Remaining amount | Q20: 1015 | R20: =R19-P20+Q20 -> 91116
A21: 45778 | B21: H39 | C21: Cash deposited for Previous Bill | D21: 738 | F21: =F20-D21+E21 -> 11129 | M21: 27/7/24 | N21: G524 | O21: 1.5L - Caps, 500ml - Caps, 30mm Caps, 1.5L Shoper | Q21: 4740 | R21: =R20-P21+Q21 -> 95856
A22: 14/1/25 | B22: H225 | C22: Remaining amount | E22: 1851 | F22: =F21-D22+E22 -> 12980 | M22: 28/7/24 | N22: Exp Sh | P22: 4700 | R22: =R21-P22+Q22 -> 91156
A23: 15/1/25 | B23: H235 | C23: Remaining amount | E23: 515 | F23: =F22-D23+E23 -> 13495 | M23: 28/7/24 | N23: G534 | O23: 1.5L -Caps,1.5L Shoper, 30mm Caps | Q23: 3445 | R23: =R22-P23+Q23 -> 94601
A24: 45871 | B24: H453 | C24: Remaining amount | E24: 1770 | F24: =F23-D24+E24 -> 15265 | M24: 22/6/24 | N24: Exp Sh | O24: Cash Deposit | P24: 1100 | R24: =R23-P24+Q24 -> 93501
A25: 45871 | B25: H455 | C25: 30mm Caps, 19L Caps | E25: 1000 | F25: =F24-D25+E25 -> 16265 | M25: 45329 | N25: Exp Sh | O25: Cash Deposit | P25: 600 | R25: =R24-P25+Q25 -> 92901
A26: 45902 | B26: H465 | C26: Cash deposit as old Balance | D26: 1920 | F26: =F25-D26+E26 -> 14345 | M26: 45359 | N26: Exp Sh | O26: Cash Deposit | P26: 1750 | R26: =R25-P26+Q26 -> 91151
A27: 45993 | C27: NILL 50000 Cash in hand from which H496 Bill paid, credit amount 14345 detected | D27: 14345 | F27: =F26-D27+E27 -> 0 | M27: 45359 | N27: Exp Sh | O27: 500ml- caps | Q27: 1270 | R27: =R26-P27+Q27 -> 92421
A28: 18/3/25 | B28: H849 | C28: Remaining amount | E28: 1000 | F28: =F27-D28+E28 -> 1000
A29: 26/4/25 | B29: H1357 | C29: Remaining amount | E29: 225 | F29: =F28-D29+E29 -> 1225
F30: =F29-D30+E30 -> 1225
F31: =F30-D31+E31 -> 1225
F32: =F31-D32+E32 -> 1225
F33: =F32-D33+E33 -> 1225
F34: =F33-D34+E34 -> 1225
A35: GRAND TOTAL | F35: =F28-D35+E35 -> 1000

Sheet Ice Mountain 
A1: LEDGER
A3: Account Holder's Name | D3: Ice mountain (Zahid Sb)
A4: Pg # | C4: Old Reg(120)
A5: Date | B5: Ref No. | C5: Description | D5: Debit | E5: Credit | F5: Balance
A6: 45176 | C6: Old Balance | E6: 6600 | F6: =E6-D6 -> 6600
F7: =F6-D7+E7 -> 6600
F8: =F7-D8+E8 -> 6600
A9: GRAND TOTAL | F9: =F8-D9+E9 -> 6600

Sheet Just Pure
A1: LEDGER
A3: Account Holder's Name | D3: Just Pure (Salman sab)
A4: Pg # | C4: New Reg(116)
A5: Date | B5: Ref No. | C5: Description | D5: Debit | E5: Credit | F5: Balance
A6: 13/03/24 | B6: F1051 | C6: Memb 4*40 Agro Liks | E6: 88500 | F6: =E6 -> 88500
C7: Plant Wasing Memb,.. | E7: 7500 | F7: =F6-D7+E7 -> 96000
A8: 17/03/24 | B8: F1089 | C8: Gac 10" So Pure (10*400) | E8: 4000 | F8: =F7-D8+E8 -> 100000
A9: 45327 | B9: F1609 | C9: Gac 10" (10*500) | E9: 5000 | F9: =F8-D9+E9 -> 105000
A10: 45631 | B10: F1741 | C10: Gac 10" (02*450) | E10: 900 | F10: =F9-D10+E10 -> 105900
A11: 45297 | B11: G02 | C11: Gac 10" (10*450) | E11: 4500 | F11: =F10-D11+E11 -> 110400
A12: 45391 | B12: G634 | C12: Dosing Pump Repairing | E12: 4000 | F12: =F11-D12+E12 -> 114400
C13: Solar | D13: 114400 | F13: =F12-D13+E13 -> 0
A14: 30/9/24 | B14: G1100 | C14: Flow Valve, Tee (remaining amount) | E14: 700 | F14: =F13-D14+E14 -> 700
A15: 45637 | B15: G1495 | C15: Memb100G (2) | E15: 9000 | F15: =F14-D15+E15 -> 9700
A16: 26/11/24 | B16: G1632 | C16: Membrane 100G (1) | E16: 4500 | F16: =F15-D16+E16 -> 14200
A17: 19/12/24 | B17: G1823 | C17: 6G Tank (1), 150G Membrane (2) | E17: 20500 | F17: =F16-D17+E17 -> 34700
A18: 26/12/24 | B18: G1889 | C18: R.O Set (10Set) | E18: 11000 | F18: =F17-D18+E18 -> 45700
A19: 45689 | B19: H22 | C19: CTO 10", PPF 10" S/P | E19: 800 | F19: =F18-D19+E19 -> 46500
A20: 45778 | B20: H35 | C20: GAC(10),CTO(10),PPF(10) | E20: 14500 | F20: =F19-D20+E20 -> 61000
A21: 45962 | B21: H90 | C21: PPF,CTO Vit, GAC Vit | E21: 2400 | F21: =F20-D21+E21 -> 63400
A22: 29/1/25 | B22: H363 | C22: Chlorine tab, 5L + Caps, 1.5L + Caps | E22: 600 | F22: =F21-D22+E22 -> 64000
A23: 13/2/25 | B23: H508 | C23: Membrane 75G | E23: 3500 | F23: =F22-D23+E23 -> 67500
A24: 45963 | B24: H484 | C24: GAC (2), CTO (2), PPF (2) | E24: 1800 | F24: =F23-D24+E24 -> 69300
A25: 45781 | B25: H1018 | C25: 100G Membrane | E25: 5000 | F25: =F24-D25+E25 -> 74300
A26: 14/4/25 | B26: H1161 | C26: Tank 32G | E26: 5500 | F26: =F25-D26+E26 -> 79800
A27: 14/4/25 | B27: H1164 | C27: High Pressure Pump repairing | E27: 41000 | F27: =F26-D27+E27 -> 120800
C28: Deduction from panel | D28: 41000 | F28: =F27-D28+E28 -> 79800
A29: 45997 | B29: H113 | C29: Antiscalar | E29: 1100 | F29: =F28-D29+E29 -> 80900
A30: 13/7/25 | B30: I 339 | C30: Remaining Amount | E30: 900 | F30: =F29-D30+E30 -> 81800
A31: 19/7/25 | B31: I 408 | C31: CTO 10" | F31: =F30-D31+E31 -> 81800
A32: 45846 | B32: I 656 | C32: R.O | E32: 8500 | F32: =F31-D32+E32 -> 90300
A33: 13/1/26 | B33: j744 | C33: filter+membrane....... | E33: 209750 | F33: =F32-D33+E33 -> 300050
F34: =F33-D34+E34 -> 300050
F35: =F34-D35+E35 -> 300050
A36: GRAND TOTAL | F36: =F35-D36+E36 -> 300050

Sheet J Smart 
A1: LEDGER
A3: Account Holder's Name | D3: J Smart
A4: Pg # | C4: Old Reg(116)
A5: Date | B5: Ref No. | C5: Description | D5: Debit | E5: Credit | F5: Balance
A6: 13/06/23 | C6: Old Balance | E6: 62799 | F6: =E6-D6 -> 62799
F7: =F6-D7+E7 -> 62799
A8: GRAND TOTAL | F8: =F7-D8+E8 -> 62799

Sheet Kashif Askari Bank
A1: LEDGER
A3: Account Holder's Name | D3: Kashif Askari Bank
A4: Pg #
A5: Date | B5: Ref No. | C5: Description | D5: Debit | E5: Credit | F5: Balance
A6: 28/06/22 | B6: 2595 | C6: Old Balance | E6: 1625 | F6: =E6-D6 -> 1625
A7: 29/05/23 | B7: 1519 | C7: PPF,Gac,.. | E7: 1700 | F7: =F6-D7+E7 -> 3325
A8: 18/06/23 | B8: 1920 | C8: R.O Tank Used | E8: 5000 | F8: =F7-D8+E8 -> 8325
A9: 44936 | B9: E1435 | C9: CTO,PPf,.. | E9: 3600 | F9: =F8-D9+E9 -> 11925
F10: =F9-D10+E10 -> 11925
F11: =F10-D11+E11 -> 11925
F12: =F11-D12+E12 -> 11925
A13: GRAND TOTAL | F13: =F12-D13+E13 -> 11925

Sheet Moen Sb
A1: LEDGER
A3: Account Holder's Name | D3: Moen Sb
A4: Pg # | C4: New Reg(81)
A5: Date | B5: Ref No. | C5: Description | D5: Debit | E5: Credit | F5: Balance
A6: 15/06/23 | C6: Old Balnace | E6: 33098 | F6: =E6-D6 -> 33098
C7: Chand Agro Remaining Solar Lab | D7: 9000 | F7: =F6-D7+E7 -> 24098
A8: 19/02/24 | B8: Exp Sh | C8: Cash Deposit | D8: 2750 | F8: =F7-D8+E8 -> 21348
A9: 24/03/24 | B9: F1158 | C9: 500 ml Bottle | E9: 3500 | F9: =F8-D9+E9 -> 24848
A10: 27/03/24 | B10: Exp Sh | C10: Cash Deposit | D10: 3500 | F10: =F9-D10+E10 -> 21348
A11: 25/04/24 | C11: Dep Pyment from Solar Work of Head Rajkan | D11: 5000 | F11: =F10-D11+E11 -> 16348
A12: 27/04/24 | B12: F1550 | C12: 250 ml bottle | E12: 8780 | F12: =F11-D12+E12 -> 25128
A13: 29/04/24 | C13: Added From Solar Work | D13: 8780 | F13: =F12-D13+E13 -> 16348
A14: 45417 | B14: F1645 | C14: 250 ml bottle | E14: 6213 | F14: =F13-D14+E14 -> 22561
A15: 27/05/24 | B15: F1927 | C15: R.O filter Set,.. | E15: 20000 | F15: =F14-D15+E15 -> 42561
A16: 45418 | B16: Exp Sh | C16: Cash Deposit | D16: 6000 | F16: =F15-D16+E16 -> 36561
A17: 23/7/24 | C17: R.O diccount | D17: 8000 | F17: =F16-D17+E17 -> 28561
A18: 23/7/24 | C18: Solar deposit | D18: 18500 | F18: =F17-D18+E18 -> 10061
A19: 18/7/24 | B19: G451 | C19: 140ml - caps, PPF 10" | E19: 3900 | F19: =F18-D19+E19 -> 13961
A20: 45359 | B20: Exp Sh | C20: Cash Deposit | D20: 3000 | F20: =F19-D20+E20 -> 10961
A21: 45512 | C21: Bush, Seal | E21: 1900 | F21: =F20-D21+E21 -> 12861
A22: 45421 | B22: G655 | C22: Connecter, Breaker, Light, CT | E22: 2250 | F22: =F21-D22+E22 -> 15111
A23: 45635 | B23: G655/Exp Sheet | C23: Cash Deposit | D23: 2250 | F23: =F22-D23+E23 -> 12861
A24: 15/9/24 | B24: G837 | C24: 1.50ml Bottle, 30mm Seal | E24: 2315 | F24: =F23-D24+E24 -> 15176
A25: 18/9/24 | C25: Cash Deposit | D25: 2315 | F25: =F24-D25+E25 -> 12861
C26: Amount Received | D26: 12861 | F26: =F25-D26+E26 -> 0
C27: Inverter 3.5KW | E27: 20000 | F27: =F26-D27+E27 -> 20000
A28: 45362 | B28: G1407 | C28: Neck Seal | E28: 450 | F28: =F27-D28+E28 -> 20450
A29: 45485 | B29: G1719 | C29: 150ml Bottle, 30mm Seal | E29: 2325 | F29: =F28-D29+E29 -> 22775
A30: 45516 | B30: Exp Sh | C30: Cash Deposit | D30: 2300 | F30: =F29-D30+E30 -> 20475
F31: =F30-D31+E31 -> 20475
F32: =F31-D32+E32 -> 20475
F33: =F32-D33+E33 -> 20475
A34: GRAND TOTAL | F34: =F33-D34+E34 -> 20475

Sheet Mateen Sb
A1: LEDGER
A3: Account Holder's Name | D3: Mateen Sb
A4: Pg # | C4: New Reg(78)
A5: Date | B5: Ref No. | C5: Description | D5: Debit | E5: Credit | F5: Balance
C6: Old Balnace | E6: 20328 | F6: =E6-D6 -> 20328
A7: 15/01/24 | B7: Exp Sh | C7: IBFT | D7: 5000 | F7: =F6-D7+E7 -> 15328
A8: 45422 | B8: G1141 | C8: 150ml Bottle | E8: 1890 | F8: =F7-D8+E8 -> 17218
A9: 38270 | B9: G1198 | C9: 150ml Bottle | E9: 5625 | F9: =F8-D9+E9 -> 22843
A10: 30/11/24 | B10: G1656 | C10: 150ml Bottle | E10: 3750 | F10: =F9-D10+E10 -> 26593
A11: 45332 | C11: Disount | D11: 843 | F11: =F10-D11+E11 -> 25750
A12: 45332 | C12: IBFT | D12: 2000 | F12: =F11-D12+E12 -> 23750
A13: 21/12/24 | B13: G1835 | C13: 150ml Bottle | E13: 1875 | F13: =F12-D13+E13 -> 25625
A14: 25/12/24 | B14: Exp Sh | C14: IBFT | D14: 1875 | F14: =F13-D14+E14 -> 23750
A15: 28/12/24 | B15: G1897 | C15: 140ml Bottle | E15: 1875 | F15: =F14-D15+E15 -> 25625
A16: 45778 | B16: Exp Sh | C16: Cash deposit | D16: 1880 | F16: =F15-D16+E16 -> 23745
A17: 15/1/25 | B17: H240 | C17: 150ml Bottle | E17: 1875 | F17: =F16-D17+E17 -> 25620
A18: 19/1/25 | B18: Exp Sh | C18: Cash deposit | D18: 1850 | F18: =F17-D18+E18 -> 23770
A19: 26/1/25 | B19: H338 | C19: 30mm Seal | E19: 450 | F19: =F18-D19+E19 -> 24220
A20: 16/2/25 | B20: H543 | C20: 150ml Bottle | E20: 1875 | F20: =F19-D20+E20 -> 26095
A21: 22/2/25 | B21: H614 | C21: 150ml Bottle | E21: 3382 | F21: =F20-D21+E21 -> 29477
A22: 23/2/25 | B22: Exp Sh | C22: Cash deposit | D22: 3250 | F22: =F21-D22+E22 -> 26227
A23: 45750 | B23: H714 | C23: 150ml Bottle , 30mm Caps | E23: 800 | F23: =F22-D23+E23 -> 27027
A24: 45872 | B24: H752 | C24: 140ml Bottle, 30mm Seal | E24: 2220 | F24: =F23-D24+E24 -> 29247
A25: 30/3/25 | B25: H981 | C25: Botal 140ml | E25: 1890 | F25: =F24-D25+E25 -> 31137
A26: 45813 | C26: Cash deposit | D26: 20000 | F26: =F25-D26+E26 -> 11137
A27: 45935 | B27: Exp Sh | C27: Cash deposit | D27: 2460 | F27: =F26-D27+E27 -> 8677
F28: =F27-D28+E28 -> 8677
F29: =F28-D29+E29 -> 8677
F30: =F29-D30+E30 -> 8677
F31: =F30-D31+E31 -> 8677
F32: =F31-D32+E32 -> 8677
F33: =F32-D33+E33 -> 8677
F34: =F33-D34+E34 -> 8677
F35: =F34-D35+E35 -> 8677
A36: GRAND TOTAL | F36: =F35-D36+E36 -> 8677

Sheet Nero Water
A1: LEDGER
A3: Account Holder's Name | D3: Nero Water
A4: Pg # | C4: New Reg(54)
A5: Date | B5: Ref No. | C5: Description | D5: Debit | E5: Credit | F5: Balance
C6: Old Balnace | E6: 429389 | F6: =E6-D6 -> 429389
F7: =F6-D7+E7 -> 429389
A8: GRAND TOTAL | F8: =F7-D8+E8 -> 429389

Sheet Nonari
A1: LEDGER
A3: Account Holder's Name | D3: Nonari
A4: Pg # | C4: New Reg(94)
A5: Date | B5: Ref No. | C5: Description | D5: Debit | E5: Credit | F5: Balance
A6: 13/12/23 | C6: Old Balnace | E6: 73050 | F6: =E6-D6 -> 73050
A7: 23/12/23 | C7: Cash Deposit | D7: 50000 | F7: =F6-D7+E7 -> 23050
A8: 29/01/24 | B8: F525 | C8: Washing+Lab,… | E8: 10000 | F8: =F7-D8+E8 -> 33050
A9: 30/01/24 | B9: F531 | C9: Jambo | E9: 40500 | F9: =F8-D9+E9 -> 73550
A10: 31/01/24 | C10: IBFT | D10: 65000 | F10: =F9-D10+E10 -> 8550
A11: 31/01/24 | C11: Disc | D11: 8550 | F11: =F10-D11+E11 -> 0
A12: 24/02/24 | B12: F930 | C12: Washing of 4Plants,.. | E12: 75000 | F12: =F11-D12+E12 -> 75000
A13: 31/03/24 | C13: Cash Deposit | D13: 40000 | F13: =F12-D13+E13 -> 35000
C14: Cash Deposit | D14: 35000 | F14: =F13-D14+E14 -> 0
A15: GRAND TOTAL | F15: =F14-D15+E15 -> 0

Sheet National Water
A1: LEDGER
A3: Account Holder's Name | D3: National Water
A4: Pg # | C4: Old Reg(155)
A5: Date | B5: Ref No. | C5: Description | D5: Debit | E5: Credit | F5: Balance
A6: 28/02/23 | C6: Old Balance | E6: 335115 | F6: =E6-D6 -> 335115
A7: 14/7/23 | C7: IBFT | D7: 335115 | F7: =F6-D7+E7 -> 0
A8: GRAND TOTAL | F8: =F7-D8+E8 -> 0

Sheet Nayab Water
A1: LEDGER
A3: Account Holder's Name | D3: Nayab Water
A4: Pg # | C4: Old Reg(156)
A5: Date | B5: Ref No. | C5: Description | D5: Debit | E5: Credit | F5: Balance
C6: Old Balance | E6: 57300 | F6: =E6-D6 -> 57300
A7: 45387 | B7: F1613 | C7: Ca | E7: 1200 | F7: =F6-D7+E7 -> 58500
B8: F1613 | C8: E.P | D8: 1200 | F8: =F7-D8+E8 -> 57300
F9: =F8-D11+E9 -> 57300
A15: GRAND TOTAL | F15: =F9-D15+E15 -> 57300

Sheet Rohi Water
A1: LEDGER
A3: Account Holder's Name | D3: Rohi Water
A4: Pg # | C4: Old Reg (132)
A5: Date | B5: Ref No. | C5: Description | D5: Debit | E5: Credit | F5: Balance
A6: 44572 | C6: Old Balance | E6: 12116 | F6: =E6-D6 -> 12116
A7: 13/06/24 | B7: G139 | C7: Cash Dep | D7: 12000 | F7: =F6-D7+E7 -> 116
C8: Disc | D8: 116 | F8: =F7-D8+E8 -> 0
A9: 45839 | B9: H64 | C9: 19L Bush, PPF 10" | E9: 1500 | F9: =F8-D9+E9 -> 1500
A10: 45812 | B10: H1042 | C10: Remaining Amount | E10: 56600 | F10: =F9-D10+E10 -> 58100
A11: 45813 | C11: Cash Dep | D11: 56600 | F11: =F10-D11+E11 -> 1500
F12: =F11-D12+E12 -> 1500
F13: =F12-D13+E13 -> 1500
F14: =F13-D14+E14 -> 1500
F15: =F14-D15+E15 -> 1500
F16: =F15-D16+E16 -> 1500
A17: GRAND TOTAL | F17: =F16-D17+E17 -> 1500

Sheet  Shafi Water (Adnan sb)
A1: LEDGER
A3: Account Holder's Name | D3: Shafi Water (Adnan SB)
A4: Pg # | C4: New Reg(105)
A5: Date | B5: Ref No. | C5: Description | D5: Debit | E5: Credit | F5: Balance
A6: 25/11/23 | C6: Old Balnace | E6: 50115 | F6: =E6-D6 -> 50115
A7: 45328 | C7: IBFT | D7: 11500 | F7: =F6-D7+E7 -> 38615
A8: 45418 | B8: G57 | C8: Memb Washing Chemical | E8: 6000 | F8: =F7-D8+E8 -> 44615
A9: 22/8/24 | B9: G905 | C9: 19L Caps, 19L Lids, Jumbo PPF | E9: 2675 | F9: =F8-D9+E9 -> 47290
A10: 17/9/24 | B10: G857 | C10: 19L Caps | E10: 1500 | F10: =F9-D10+E10 -> 48790
A11: 45422 | C11: cash deposit | D11: 1500 | F11: =F10-D11+E11 -> 47290
A12: 16/11/24 | B12: G1539 | C12: Sand Silica, A.carbon, Gravel, Membrane8*40,… | E12: 139800 | F12: =F11-D12+E12 -> 187090
A13: 16/11/24 | C13: cash deposit | D13: 110000 | F13: =F12-D13+E13 -> 77090
A14: 19/11/24 | B14: G1567 | C14: Remaining Amou | E14: 100 | F14: =F13-D14+E14 -> 77190
A15: 45516 | B15: G905 | C15: Exp Sh Cash in Hand | D15: 2675 | F15: =F14-D15+E15 -> 74515
A16: 45516 | B16: G757 | C16: Exp Sh Cash in Hand | D16: 6000 | F16: =F15-D16+E16 -> 68515
A17: 45516 | C17: IBFT | D17: 45000 | F17: =F16-D17+E17 -> 23515
A18: 45516 | C18: Discount in Membrane | D18: 2000 | F18: =F17-D18+E18 -> 21515
A19: 45812 | B19: H1034 | C19: Remaining Amou | E19: 550 | F19: =F18-D19+E19 -> 22065
A20: 45967 | B20: H2000 | C20: Memb Washing Chemical | E20: 8000 | F20: =F19-D20+E20 -> 30065
A21: 45937 | C21: cash deposit | D21: 8000 | F21: =F20-D21+E21 -> 22065
A22: 45969 | B22: Exp Sheet | C22: cash deposit | D22: 550 | F22: =F21-D22+E22 -> 21515
F23: =F22-D23+E23 -> 21515
A24: GRAND TOTAL | F24: =F23-D24+E24 -> 21515

Sheet Sheikh Usman Sb
A1: LEDGER
A3: Account Holder's Name | D3: Sheikh Usman Sb
A4: Pg # | C4: 15
A5: Date | B5: Ref No. | C5: Description | D5: Debit | E5: Credit | F5: Balance
C6: Opening Balnace | E6: 40730 | F6: =E6-D6 -> 40730
A7: 30/01/24 | B7: F589 | C7: 19L Caps,.. | E7: 2100 | F7: =F6-D7+E7 -> 42830
A8: 45567 | B8: F683 | C8: 19L Caps,.. | E8: 1200 | F8: =F7-D8+E8 -> 44030
A9: 14/02/24 | C9: 1.5L Shoper | D9: 10000 | F9: =F8-D9+E9 -> 34030
A10: 17/02/24 | B10: F766 | C10: 19L Caps | E10: 1575 | F10: =F9-D10+E10 -> 35605
A11: 24/02/24 | B11: F847 | C11: 19L Bottle,.. | E11: 11050 | F11: =F10-D11+E11 -> 46655
A12: 29/02/24 | B12: F919 | C12: 30 mm Seal | E12: 2100 | F12: =F11-D12+E12 -> 48755
A13: 29/02/24 | B13: F919 | C13: Claim(53 Leak Bottle) | D13: 5300 | F13: =F12-D13+E13 -> 43455
A14: 45415 | B14: F965 | C14: 19L Stand +Nozzle | E14: 1000 | F14: =F13-D14+E14 -> 44455
A15: 20/03/24 | B15: F1112 | C15: 19L Seal | E15: 1240 | F15: =F14-D15+E15 -> 45695
A16: 25/03/24 | B16: F1167 | C16: 19L Caps | E16: 1310 | F16: =F15-D16+E16 -> 47005
A17: 45295 | B17: F1234 | C17: 19L Caps,Na | E17: 1350 | F17: =F16-D17+E17 -> 48355
A18: 45508 | B18: F1326 | C18: 19L Caps,.. | E18: 2250 | F18: =F17-D18+E18 -> 50605
A19: 18/04/24 | B19: F1438 | C19: 19L Caps,.. | E19: 1950 | F19: =F18-D19+E19 -> 52555
A20: 23/04/24 | B20: F1490 | C20: Carbon Bush,. | E20: 12900 | F20: =F19-D20+E20 -> 65455
A21: 25/04/24 | B21: F1523 | C21: 19L Caps,.. | E21: 2250 | F21: =F20-D21+E21 -> 67705
A22: 45437 | B22: F1644 | C22: 19L Caps,.. | E22: 2050 | F22: =F21-D22+E22 -> 69755
A23: 45540 | B23: F1708 | C23: 19L Caps,.. | E23: 2200 | F23: =F22-D23+E23 -> 71955
A24: 14/05/24 | B24: F1764 | C24: 19L Caps,.. | E24: 1600 | F24: =F23-D24+E24 -> 73555
A25: 21/05/24 | B25: F1836 | C25: 19L Caps,.. | E25: 1200 | F25: =F24-D25+E25 -> 74755
A26: 22/05/24 | B26: F1846 | C26: 19L Caps,.. | E26: 4600 | F26: =F25-D26+E26 -> 79355
C27: IBFT | D27: 12900 | F27: =F26-D27+E27 -> 66455
A28: 25/05/24 | B28: F1893 | C28: Sand Bag | E28: 7700 | F28: =F27-D28+E28 -> 74155
A29: 25/05/24 | B29: F1887 | C29: 19L Bottle,.. | E29: 20250 | F29: =F28-D29+E29 -> 94405
C30: Disc on bill 1893 | D30: 1700 | F30: =F29-D30+E30 -> 92705
A31: 30/05/24 | B31: F1973 | C31: 19L Caps | E31: 1900 | F31: =F30-D31+E31 -> 94605
A32: 30/05/24 | B32: F1979 | C32: 19L Bottle | E32: 6750 | F32: =F31-D32+E32 -> 101355
C33: 19L Bottle Discount | D33: 1000 | F33: =F32-D33+E33 -> 100355
A34: 45418 | C34: Net Cash Dep | D34: 40000 | F34: =F33-D34+E34 -> 60355
A35: 45449 | B35: G64 | C35: 19L Caps,.. | E35: 2500 | F35: =F34-D35+E35 -> 62855
A36: 45632 | B36: G137 | C36: 19L Caps,.. | E36: 2350 | F36: =F35-D36+E36 -> 65205
A37: 20/6/24 | B37: G186 | C37: 19L Caps, Lids | D37: 0 | E37: 1305 | F37: =F36-D37+E37 -> 66510
A38: 25/6/24 | B38: G241 | C38: 19L Caps,19L Lids,19L Seal | E38: 2200 | F38: =F37-D38+E38 -> 68710
A39: 29/6/24 | B39: G270 | C39: 19L Caps,19L Lids,19L Seal, Ca, Na | E39: 2560 | F39: =F38-D39+E39 -> 71270
A40: 45329 | B40: G308 | C40: 19Lcaps blue, 19L caps white | E40: 2850 | F40: =F39-D40+E40 -> 74120
A41: 45603 | C41: Cash Received | D41: 18000 | F41: =F40-D41+E41 -> 56120
C42: Discount | D42: 350 | F42: =F41-D42+E42 -> 55770
C43: Discount | D43: 220 | F43: =F42-D43+E43 -> 55550
A44: 13/7/24 | B44: G417 | C44: 19L caps, Lids | D44: 0 | E44: 3050 | F44: =F43-D44+E44 -> 58600
A45: 21/7/24 | B45: G470 | C45: 19L Caps, 19L Seal | E45: 2000 | F45: =F44-D45+E45 -> 60600
A46: 25/7/24 | B46: G510 | C46: 19L Caps, 19L Seal Na | E46: 3950 | F46: =F45-D46+E46 -> 64550
A47: 28/7/24 | B47: G542 | C47: 19L Caps, 19L tap | E47: 9850 | F47: =F46-D47+E47 -> 74400
A48: 45359 | B48: G589 | C48: 19L caps- lids, 19L seal | E48: 2250 | F48: =F47-D48+E48 -> 76650
A49: 45420 | B49: Exp Sheet | C49: Cash Received | D49: 9500 | F49: =F48-D49+E49 -> 67150
A50: 45573 | B50: G751 | C50: 19L caps, 19L seal | E50: 1650 | F50: =F49-D50+E50 -> 68800
A51: 15/8/24 | B51: G773 | C51: 19L seal, Mg | E51: 2400 | F51: =F50-D51+E51 -> 71200
A52: 20/8/24 | B52: G892 | C52: 19L caps, 19L Lids, Na | E52: 1850 | F52: =F51-D52+E52 -> 73050
A53: 45360 | B53: G624 | C53: 19L Caps, 19L Lids, 19L Nozel | E53: 2300 | F53: =F52-D53+E53 -> 75350
A54: 22/9/24 | B54: G1008 | C54: 19L Caps, 19L Seal, 19L Lids | E54: 2150 | F54: =F53-D54+E54 -> 77500
A55: 45422 | B55: G1142 | C55: 19L Caps, 19L Handle, Na, 19L Nozle | E55: 1787 | F55: =F54-D55+E55 -> 79287
A56: 45693 | C56: Ca, Lids (200PCs) | E56: 1075 | F56: =F55-D56+E56 -> 80362
A57: 45843 | B57: H1534 | C57: 19L Lids | E57: 650 | F57: =F56-D57+E57 -> 81012
A58: 45843 | B58: Exp Sheet | C58: Cash deposit | D58: 35000 | F58: =F57-D58+E58 -> 46012
A59: 25/5/25 | B59: H1783 | C59: 19L Lids | E59: 750 | F59: =F58-D59+E59 -> 46762
A60: 14/6/25 | B60: H148 | C60: 19L Seal, 19L Handle | E60: 1600 | F60: =F59-D60+E60 -> 48362
A61: 21/6/25 | B61: I 47 | C61: 19L Lids, 19L Stand | E61: 1050 | F61: =F60-D61+E61 -> 49412
A62: 25/6/25 | B62: Exp Sheet | C62: Cash deposit | D62: 10000 | F62: =F61-D62+E62 -> 39412
A63: 45845 | B63: I 246 | C63: Ca | E63: 1250 | F63: =F62-D63+E63 -> 40662
A64: 45937 | B64: I 314 | C64: Ca, Na, 19L Lids | E64: 4715 | F64: =F63-D64+E64 -> 45377
A65: 15/7/25 | C65: IBFT | D65: 10000 | F65: =F64-D65+E65 -> 35377
A66: 18/8/2025 | B66: I 798 | C66: 19 shoper | E66: 2625 | F66: =F65-D66+E66 -> 38002
A67: 19/8/2025 | B67: Exp Sheet | C67: Cash deposit | D67: 10000 | F67: =F66-D67+E67 -> 28002
A68: 45757 | B68: I 1496 | C68: Mg , Na | E68: 2500 | F68: =F67-D68+E68 -> 30502
A69: 13/12/25 | B69: j417 | C69: 19l stand+19l tape | E69: 550 | F69: =F68-D69+E69 -> 31052
A70: 15/10/2025 | C70: cash received waqas | D70: 10000 | F70: =F69-D70+E70 -> 21052
F71: =F70-D71+E71 -> 21052
F72: =F71-D72+E72 -> 21052
F73: =F72-D73+E73 -> 21052
A74: GRAND TOTAL | F74: =F73-D74+E74 -> 21052

Sheet TMA Ali Sb
A1: LEDGER
A3: Account Holder's Name | D3: Tma Ali Sb
A4: Pg # | C4: New Reg(22)
A5: Date | B5: Ref No. | C5: Description | D5: Debit | E5: Credit | F5: Balance
A6: 45445 | B6: F660 | C6: PPF+GAC+CTO+ Labour | E6: 1500 | F6: =E6-D6 -> 1500
A7: 45696 | B7: I583 | C7: ppf. CTO. PPY | E7: 1000 | F7: =F6-D7+E7 -> 2500
A8: GRAND TOTAL | F8: =F7-D8+E8 -> 2500

Sheet Umer Awan Sb
A1: LEDGER
A3: Account Holder's Name | D3: Umer Awan Sb
A4: Pg # | C4: Old reg(60)
A5: Date | B5: Ref No. | C5: Description | D5: Debit | E5: Credit | F5: Balance
A6: 45053 | B6: E237 | C6: Old Balance | E6: 37572 | F6: =E6-D6 -> 37572
C7: Multiport wall | E7: 4500 | F7: =E7-D7+F6 -> 42072
C8: Bad Bottles | D8: 6300 | F8: =E8-D8+F7 -> 35772 | K8: a
A9: GRAND TOTAL | F9: =E9-D9+F8 -> 35772

Sheet Urban Water
A1: LEDGER
A3: Account Holder's Name | D3: Urban Water
A4: Pg # | C4: New Reg
A5: Date | B5: Ref No. | C5: Description | D5: Debit | E5: Credit | F5: Balance
A6: 30/3/25 | B6: H987 | C6: 6L+Caps | E6: 3690 | F6: =E6-D6 -> 3690
A7: 45720 | B7: H996 | C7: 500ml | E7: 1615 | F7: =E7-D7+F6 -> 5305
A8: 29/3/25 | B8: H974 | C8: 1.5L Shoper | E8: 1100 | F8: =E8-D8+F7 -> 6405
A9: 45812 | B9: H1037 | C9: 1.5L, 500ml, 30mm Caps, 19L Caps,… | E9: 9515 | F9: =E9-D9+F8 -> 15920
A10: 45842 | B10: H1055 | C10: 6L+Caps, 1.5L Shoper | E10: 4790 | F10: =E10-D10+F9 -> 20710
A11: 13/4/25 | B11: H1140 | C11: 6L+ Caps, 1.5L Shoper | E11: 5890 | F11: =E11-D11+F10 -> 26600
A12: 45842 | B12: IBFT | C12: Cash deposit | D12: 20710 | F12: =E12-D12+F11 -> 5890
A13: 15/4/25 | B13: H1186 | C13: Mg | E13: 1250 | F13: =E13-D13+F12 -> 7140
A14: 19/4/25 | B14: H1252 | C14: 6L+Caps, 1.5L Shoper | E14: 13082 | F14: =E14-D14+F13 -> 20222
A15: 22/4/25 | B15: H1307 | C15: 1.5L-Caps, 500ml-Caps, 1.5L Shoper | E15: 6920 | F15: =E15-D15+F14 -> 27142
A16: 24/4/25 | B16: H1337 | C16: 1.5L, 500ml, Shoper | E16: 12700 | F16: =E16-D16+F15 -> 39842
A17: 24/4/25 | C17: IBFT | D17: 15000 | F17: =E17-D17+F16 -> 24842
A18: 26/4/25 | B18: H1356 | C18: 500ml-Caps, 30mm caps, 500ml Shoper | E18: 13075 | F18: =E18-D18+F17 -> 37917
A19: 27/4/25 | B19: H1374 | C19: 1.5L Shoper | E19: 1100 | F19: =E19-D19+F18 -> 39017
A20: 29/4/25 | B20: H1401 | C20: 500ml Shoper | E20: 1100 | F20: =E20-D20+F19 -> 40117
A21: 45662 | B21: H1426 | C21: 1.5L-Caps | E21: 1750 | F21: =E21-D21+F20 -> 41867
A22: 19/4/25 | C22: IBFT | D22: 10000 | F22: =E22-D22+F21 -> 31867
A23: 22/4/25 | C23: IBFT | D23: 4500 | F23: =E23-D23+F22 -> 27367
A24: 45721 | B24: H1451 | C24: 30mm Caps | E24: 4500 | F24: =E24-D24+F23 -> 31867
A25: 45782 | B25: H1491 | C25: 500ml Shoper, 1.5L Shoper | E25: 2200 | F25: =E25-D25+F24 -> 34067
A26: 45813 | B26: H1506 | C26: 1.5L-Caps, Na, Antiscalar | E26: 3550 | F26: =E26-D26+F25 -> 37617
A27: 45843 | C27: Easy Paisa | D27: 10000 | F27: =E27-D27+F26 -> 27617
A28: 45874 | B28: H1546 | C28: 30mm Seal, 1.5L Shoper, 19L Caps | E28: 1275 | F28: =E28-D28+F27 -> 28892
A29: 18/5/25 | B29: H1686 | C29: 1.5L-Caps, 1.5L Shoper | E29: 2300 | F29: =E29-D29+F28 -> 31192
A30: 28/5/2025 | B30: H 1833 | C30: IBFT | D30: 65000 | F30: =E30-D30+F29 -> -33808
A31: 19/5/25 | C31: 19L Bottle Printed | E31: 67500 | F31: =E31-D31+F30 -> 33692 | G31: Pending
A32: 19/5/25 | B32: H1697 | C32: 500ml-Caps, 1.5L- caps, 500ml Shoper | E32: 13860 | F32: =E32-D32+F31 -> 47552
A33: 20/2/25 | B33: H1708 | C33: 6L+Caps, 500ml -Caps, 30mm Caps, 500ml Shoper, 30mm Seal | E33: 18395 | F33: =E33-D33+F32 -> 65947
A34: 21/5/25 | B34: H1734 | C34: 500ml-Caps, 500ml Shoper | E34: 6880 | F34: =E34-D34+F33 -> 72827
A35: 21/5/25 | C35: IBFT | D35: 3000 | F35: =E35-D35+F34 -> 69827
A36: 23/5/25 | C36: IBFT Qazi Imran received | D36: 10000 | F36: =E36-D36+F35 -> 59827
A37: 24/5/25 | C37: IBFT | D37: 10000 | F37: =E37-D37+F36 -> 49827
A38: 25/5/25 | B38: H1787 | C38: Valve3/4, Labour | E38: 3000 | F38: =E38-D38+F37 -> 52827
A39: 26/5/25 | B39: H1790 | C39: 1.5L-Caps, 1.5L Shoper, 19L Caps | E39: 8750 | F39: =E39-D39+F38 -> 61577
A40: 28/5/25 | B40: H1838 | C40: 500ml -Caps | E40: 2890 | F40: =E40-D40+F39 -> 64467
A41: 28/5/25 | B41: H1833 | C41: 500ml Shoper, Dye Screen | E41: 4100 | F41: =E41-D41+F40 -> 68567
A42: 30/5/25 | C42: IBFT | D42: 10000 | F42: =E42-D42+F41 -> 58567
A43: 45694 | B43: H1897 | C43: 1.5L -Caps, 30mm Caps, 1.5L Shoper | E43: 5925 | F43: =E43-D43+F42 -> 64492
A44: 45997 | B44: H127 | C44: Burner | E44: 1500 | F44: =E44-D44+F43 -> 65992
A45: 45997 | B45: H129 | C45: 1.5L-Caps, 6L+Caps,… | E45: 7074 | F45: =E45-D45+F44 -> 73066
A46: 45997 | C46: IBFT | D46: 20000 | F46: =E46-D46+F45 -> 53066
A47: 14/6/25 | C47: IBFT | D47: 9000 | F47: =E47-D47+F46 -> 44066
A48: 16/6/25 | C48: IBFT | D48: 4000 | F48: =E48-D48+F47 -> 40066
A49: 21/6/25 | B49: I 54 | C49: Remaining Amount | E49: 300 | F49: =E49-D49+F48 -> 40366
A50: 24/6/25 | B50: I 89 | C50: Remaining Amount | E50: 7080 | F50: =E50-D50+F49 -> 47446
A51: 26/6/25 | C51: IBFT | D51: 7000 | F51: =E51-D51+F50 -> 40446
A52: 28/6/25 | B52: I 132 | C52: 30mm Caps, 1.5L - Caps, 19L - Caps, 1.5L Shoper | E52: 8137 | F52: =E52-D52+F51 -> 48583
A53: 29/6/2025 | B53: I 174 | C53: 1.5L Seals | E53: 1800 | F53: =E53-D53+F52 -> 50383
A54: 45846 | B54: I 666 | C54: 1.5L caps….. | E54: 337 | F54: =E54-D54+F53 -> 50720
A55: 13/8/2025 | B55: I 738 | C55: 1.5L Caps…. | E55: 218 | F55: =E55-D55+F54 -> 50938
A56: 45999 | B56: Exp sheet | C56: Cash deposit | D56: 5725 | F56: =E56-D56+F55 -> 45213
A57: 16/8/2025 | B57: I 772 | C57: 1.5L caps | E57: 1274 | F57: =E57-D57+F56 -> 46487
A58: 17/8/2025 | B58: Exp sheet | C58: Cash deposit | D58: 1000 | F58: =E58-D58+F57 -> 45487
A59: 18/8/2025 | B59: I 1007 | C59: 1.5L Shoper….. | E59: 1050 | F59: =E59-D59+F58 -> 46537
A60: 19/8/2025 | B60: I 1018 | C60: 1.5L Caps….. | E60: 13498 | F60: =E60-D60+F59 -> 60035
A61: 25/8/2025 | B61: I 873 | C61: 1.5L Caps….. | E61: 3027 | F61: =E61-D61+F60 -> 63062
A62: 30/8/025 | B62: I 935 | C62: 1.5L caps… | E62: 1970 | F62: =E62-D62+F61 -> 65032
A63: 16/9/2025 | C63: Bike Reamining Amount | D63: 35000 | F63: =E63-D63+F62 -> 30032
F64: =E64-D64+F63 -> 30032
F65: =E65-D65+F64 -> 30032
F66: =E66-D66+F65 -> 30032
F67: =E67-D67+F66 -> 30032
F68: =E68-D68+F67 -> 30032
F69: =E69-D69+F68 -> 30032
F70: =E70-D70+F69 -> 30032
A71: GRAND TOTAL | F71: =E71-D71+F70 -> 30032

Sheet Waleed Sb BVH
A1: LEDGER
A3: Account Holder's Name | D3: Waleed Sb BVH
A4: Pg # | C4: New Reg(160)
A5: Date | B5: Ref No. | C5: Description | D5: Debit | E5: Credit | F5: Balance
A6: 45505 | C6: Old Balance | E6: 6160 | F6: =E6-D6 -> 6160
A7: 15/1/2024 | B7: F489 | C7: PPF,.. | E7: 1260 | F7: =F6-D7+E7 -> 7420
A8: 25/01/24 | C8: IBFT | D8: 5000 | F8: =F7-D8+E8 -> 2420
A9: 28/01/24 | B9: F575 | C9: 1.5L Fill Pet | E9: 360 | F9: =F8-D9+E9 -> 2780
A10: 45353 | B10: F627 | C10: 1.5L Fill Pet | E10: 180 | F10: =F9-D10+E10 -> 2960
A11: 45445 | B11: F669 | C11: 1.5L Fill Pet | E11: 180 | F11: =F10-D11+E11 -> 3140
A12: 13/2/2024 | B12: F729 | C12: 1.5L Fill Pet | E12: 200 | F12: =F11-D12+E12 -> 3340
A13: 19/02/24 | B13: F796 | C13: 5L Filled Bottle | E13: 80 | F13: =F12-D13+E13 -> 3420
A14: 27/02/4 | B14: F892 | C14: 1.5L Filled Pet | E14: 180 | F14: =F13-D14+E14 -> 3600
A15: 29/2/2024 | B15: F920 | C15: 1.5L Filled Pet | E15: 180 | F15: =F14-D15+E15 -> 3780
A16: 45385 | B16: F959 | C16: 1.5L Filled Pet | E16: 180 | F16: =F15-D16+E16 -> 3960
A17: 45476 | B17: F1003 | C17: 1.5L Filled Pet | E17: 180 | F17: =F16-D17+E17 -> 4140
A18: 13/3/24 | B18: F1063 | C18: 500 ml Filled | E18: 1520 | F18: =F17-D18+E18 -> 5660
A19: 23/03/24 | B19: F1148 | C19: 500 ml Filled Pet | E19: 180 | F19: =F18-D19+E19 -> 5840
A20: 45295 | B20: F1228 | C20: PPF 10",CTO 10",.. | E20: 1500 | F20: =F19-D20+E20 -> 7340
A21: 45326 | B21: Exp Sh | C21: Net Cash Deposit | D21: 5000 | F21: =F20-D21+E21 -> 2340
A22: 45326 | B22: F1239 | C22: 1.5L Filled Pet | E22: 180 | F22: =F21-D22+E22 -> 2520
A23: 45326 | B23: F1238 | C23: PPF+Gac+CTO 10"+labr | E23: 1500 | F23: =F22-D23+E23 -> 4020
A24: 45416 | B24: F1313 | C24: Filled 500 ml ,.. | E24: 2025 | F24: =F23-D24+E24 -> 6045
A25: 45601 | B25: F1733 | C25: 1.5L Fill Pet | E25: 180 | F25: =F24-D25+E25 -> 6225
A26: 45571 | B26: G103 | C26: PPF 10",CTO 10",.. | E26: 1500 | F26: =F25-D26+E26 -> 7725
A27: 45450 | C27: IBFT | D27: 5000 | F27: =F26-D27+E27 -> 2725
A28: 27/7/24 | B28: G531 | C28: R.O Filteration | E28: 1500 | F28: =F27-D28+E28 -> 4225
A29: 45573 | B29: G748 | C29: R.O Filteration | E29: 1500 | F29: =F28-D29+E29 -> 5725
A30: 45360 | B30: G622 | C30: R.O Filteration + Labour | E30: 1500 | F30: =F29-D30+E30 -> 7225
A31: 45513 | B31: G679 | C31: Single Bush | E31: 500 | F31: =F30-D31+E31 -> 7725
A32: 19/9/24 | B32: G876 | C32: R.O Filteration + Labour | E32: 1540 | F32: =F31-D32+E32 -> 9265
A33: 22/9/24 | B33: G1011 | C33: Membrane , PPF | E33: 5400 | F33: =F32-D33+E33 -> 14665
A34: 26/9/24 | C34: cash deposit | D34: 5000 | F34: =F33-D34+E34 -> 9665
A35: 21/10/24 | B35: G1291 | C35: R.O Filteration | E35: 1500 | F35: =F34-D35+E35 -> 11165
A36: 23/1/25 | C36: IBFT | D36: 6000 | F36: =F35-D36+E36 -> 5165
A37: 45660 | B37: H685 | C37: R.O System | E37: 1900 | F37: =F36-D37+E37 -> 7065
C38: Filled Packet Receive from star Light | E38: 1440 | F38: =F37-D38+E38 -> 8505
A39: 20/5/25 | B39: H1714 | C39: PPF 10" (3),CTO 10", GAC 10"+ Labour | E39: 1800 | F39: =F38-D39+E39 -> 10305
A40: 19/7/25 | B40: I 415 | C40: R.O Set, Tank 6G, Flow Valve, Tank Valve | E40: 11400 | F40: =F39-D40+E40 -> 21705
A41: 45724 | B41: 588 | C41: 1.5L pet fill | E41: 800 | F41: =F40-D41+E41 -> 22505
A42: 45846 | B42: I 660 | C42: Labour | E42: 1500 | F42: =F41-D42+E42 -> 24005
A43: 45969 | B43: I 700 | C43: 1.5 Fill Pet | E43: 600 | F43: =F42-D43+E43 -> 24605
A44: 45817 | B44: I 1065 | C44: 1.5L Fill Pet | E44: 1000 | F44: =F43-D44+E44 -> 25605
A45: 14/9/2025 | B45: I 1210 | C45: R.O set PPF 10 | E45: 1900 | F45: =F44-D45+E45 -> 27505
A46: 46055 | B46: j963 | C46: R.O set PPF 10 | E46: 1900 | F46: =F45-D46+E46 -> 29405
A47: 22/7/25 | C47: cash received qazi sb | D47: 10000 | F47: =F46-D47+E47 -> 19405
F48: =F47-D48+E48 -> 19405
F49: =F48-D49+E49 -> 19405
F50: =F49-D50+E50 -> 19405
F51: =F50-D51+E51 -> 19405
F52: =F51-D52+E52 -> 19405
F53: =F52-D53+E53 -> 19405
F54: =F53-D54+E54 -> 19405
F55: =F54-D55+E55 -> 19405
F56: =F55-D56+E56 -> 19405
F57: =F56-D57+E57 -> 19405
A58: GRAND TOTAL | F58: =F57-D58+E58 -> 19405

Sheet Yasir Sb
A1: LEDGER
A3: Account Holder's Name | D3: Yasir Sb
A4: Pg # | C4: Old Reg(142)
A5: Date | B5: Ref No. | C5: Description | D5: Debit | E5: Credit | F5: Balance
A6: 44657 | C6: Old Balnace | F6: 266338
C7: Naran Kaghan Trip (20K Cash+ 15K Send toTourist) | D7: 35000 | F7: =F6-D7+E7 -> 231338
F8: =F7-D8+E8 -> 231338
F9: =F8-D9+E9 -> 231338
A10: GRAND TOTAL | F10: =F9-D10+E10 -> 231338

Sheet ZYNG 
A1: LEDGER
A3: Account Holder's Name | D3: ZYNg
A4: Pg # | C4: Old Reg (108)
A5: Date | B5: Ref No. | C5: Description | D5: Debit | E5: Credit | F5: Balance
C6: Old Balnace | E6: 52000 | F6: =E6-D6 -> 52000
A7: 45510 | B7: Purchase | C7: Dosing Pump +Label | D7: 23000 | F7: =F6-D7+E7 -> 29000
A8: 21/3/25 | B8: H883 | C8: Ampaler, Bush carbide,… | E8: 40800 | F8: =F7-D8+E8 -> 69800
A9: 26/3/25 | C9: IBFT | D9: 40800 | F9: =F8-D9+E9 -> 29000
F10: =F9-D10+E10 -> 29000
A11: GRAND TOTAL | F11: =F10-D11+E11 -> 29000

Sheet Zain Water
A1: LEDGER
A3: Account Holder's Name | D3: Zain Water
A4: Pg # | C4: Old Reg(71)
A5: Date | B5: Ref No. | C5: Description | D5: Debit | E5: Credit | F5: Balance
E6: 195000 | F6: 195000
F7: =E7-D7 -> 0
F8: =E8-D8 -> 0

Sheet Basharat Sb
A1: LEDGER
A3: Account Holder's Name | D3: Basharat Sb
A4: Pg #
A5: Date | B5: Ref No. | C5: Description | D5: Debit | E5: Credit | F5: Balance
A6: 45992 | B6: H 205 | C6: R.O Set | E6: 2050 | F6: =E6-D6 -> 2050
A7: 45904 | B7: H 1101 | C7: R.O Set, PPF | E7: 1900 | F7: =E7-D7+F6 -> 3950
A8: 28/5/25 | B8: H 1829 | C8: R.O Set, PPF 10", PPY 10", Adapter, Membrane 100G Labour | E8: 10900 | F8: =E8-D8+F7 -> 14850
A9: 45845 | B9: I 247 | C9: R.O Set, PPF 10", PPY 10", Membrane Cleaning,.. | E9: 2550 | F9: =E9-D9+F8 -> 17400
F10: =E10-D10+F9 -> 17400
A11: GRAND TOTAL | F11: =E11-D11+F10 -> 17400

Sheet Yes Water
B1: LEDGER
B2: Account Holder's Name | H2: Yes Water
B3: Pg # | G3: New Reg (47)
B4: Date | D4: Ref No. | G4: Description | H4: Debit | I4: Credit | J4: Balance
G5: Old Balnace | I5: 10305 | J5: 10305
B6: 20/01/24 | D6: F524 | G6: Ca,Mg,Na,.. | I6: 7270 | J6: =J5+I6-H6 -> 17575
D7: DiscountReturn on fiill pet | H7: 755 | J7: =J6+I7-H7 -> 16820
B8: 29/01/24 | D8: F582 | G8: 1.5L Shoper,.. | I8: 7400 | J8: =J7+I8-H8 -> 24220
B9: 12/2/2024 | D9: F721 | G9: 1.5L Shoper,.. | I9: 15900 | J9: =J8+I9-H9 -> 40120
B10: 14/02/2024 | D10: F745 | G10: Ca,Mg,Na | I10: 6600 | J10: =J9+I10-H10 -> 46720
B11: 22/02/24 | D11: F836 | G11: 19L Caps,.. | I11: 8800 | J11: =J10+I11-H11 -> 55520
B12: 3/3/2024 | D12: F950 | G12: Jambo PPF,.. | I12: 16170 | J12: =J11+I12-H12 -> 71690
B13: 4/3/2024 | D13: F963 | G13: 30 mm Caps | I13: 10600 | J13: =J12+I13-H13 -> 82290
B14: 9/3/2024 | D14: F1014 | G14: Ca,Mg,Na | I14: 6600 | J14: =J13+I14-H14 -> 88890
B15: 11/3/2024 | G15: IBFT | H15: 40000 | J15: =J14+I15-H15 -> 48890
B16: 13/03/24 | D16: F1050 | G16: 500 ml Shoper,. | I16: 26650 | J16: =J15+I16-H16 -> 75540
B17: 17/03/24 | D17: F1091 | G17: Cl,Antiscaler,.. | I17: 14150 | J17: =J16+I17-H17 -> 89690
B18: 17/03/24 | G18: IBFT | H18: 20000 | J18: =J17+I18-H18 -> 69690
B19: 21/03/23 | D19: F1147 | G19: 1.5L Shoper(Pure) | I19: 30500 | J19: =J18+I19-H19 -> 100190
B20: 27/03/24 | G20: IBFT | H20: 30000 | J20: =J19+I20-H20 -> 70190
B21: 28/03/24 | D21: F1197 | G21: Jambo PPF,.. | I21: 20550 | J21: =J20+I21-H21 -> 90740
B22: 28/03/24 | D22: F1197 | G22: Return 25kg Shoper | H22: 13000 | J22: =J21+I22-H22 -> 77740
B23: 1/4/2024 | D23: F1227 | G23: 19L Lids | I23: 1350 | J23: =J22+I23-H23 -> 79090
B24: 7/4/2024 | D24: Exp Sh | G24: Cash Deposit | H24: 30000 | J24: =J23+I24-H24 -> 49090
B25: 7/4/2024 | D25: F1308 | G25: Ca,Mg,Na,.. | I25: 20800 | J25: =J24+I25-H25 -> 69890
B26: 7/4/2024 | D26: F1309 | G26: Ca,Mg,Na,.. | I26: 6300 | J26: =J25+I26-H26 -> 76190
B27: 25/04/24 | D27: F1513 | G27: ca, Mg, Jambo Gold | I27: 5000 | J27: =J26+I27-H27 -> 81190
B28: 2/5/2024 | D28: F1601 | G28: Antiscaler,.. | I28: 5950 | J28: =J27+I28-H28 -> 87140
B29: 12/5/2024 | D29: F1743 | G29: Ca,Mg,.. | I29: 13200 | J29: =J28+I29-H29 -> 100340
B30: 15/05/24 | D30: F1778 | G30: 19L Seal | I30: 900 | J30: =J29+I30-H30 -> 101240
B31: 20/05/24 | D31: F1817 | G31: PPF10",.. | I31: 2150 | J31: =J30+I31-H31 -> 103390
C32: 45418 | G32: IBFT | H32: 63000 | J32: =J31+I32-H32 -> 40390
C33: 45449 | D33: G66 | G33: 19L Seal | I33: 100 | J33: =J32+I33-H33 -> 40490
C34: 45510 | D34: G78 | G34: 19L Lids | I34: 250 | J34: =J33+I34-H34 -> 40740
C35: 45605 | G35: IBFT | H35: 20000 | J35: =J34+I35-H35 -> 20740
C36: 23/10/24 | G36: Claim | H36: 7000 | J36: =J35+I36-H36 -> 13740
C37: 23/10/25 | G37: Cash Deposit | H37: 13740 | J37: =J36+I37-H37 -> 0
J38: =J37+I38-H38 -> 0
B39: GRAND TOTAL | J39: =J38+I39-H39 -> 0

Sheet Misclenous Customer List
A1: Miscelleneous Customer List | I1: Pending Bills
A4: Date | B4: Ref No. | C4: Customer Name | D4: Cr Amt | E4: Deposit | F4: R.Amt | I4: Date | K4: Bill No | L4: Customer Name | M4: Cr mount | N4: Sataus
A5: 30/05/22 | C5: Old Balnace | D5: 4143 | F5: 4143
A6: 13/9/22 | B6: 3739 | C6: Shahab Sb Model Town A | D6: 12205 | F6: =D6-E6 -> 12205 | I6: 45508 | K6: F1310 | L6: Aqua Refine | M6: 20000 | N6: Paid
A7: 44995 | B7: E1473 | C7: S.D High School | D7: 8500 | E7: 5000 | F7: =D7-E7 -> 3500
A8: 13/12/23 | B8: F169 | C8: S.D High School | D8: 1500 | F8: =D8-E8 -> 1500
A9: 18/04/24 | B9: F1426 | C9: S.D High School | D9: 3000 | F9: =D9-E9 -> 3000
A10: 45179 | B10: E1586 | C10: Shahid Sb (Excise Home) | D10: 2050 | E10: 2050 | F10: =D10-E10 -> 0
A11: 21/03/24 | B11: F1134 | C11: Shahid Sb (Excise Home) | D11: 2700 | E11: 2700 | F11: =D11-E11 -> 0
A12: 22/01/24 | B12: F538 | C12: Taj Aqua | D12: 7500 | E12: 2240 | F12: =D12-E12 -> 5260
A13: 28/01/24 | B13: F578 | C13: Taj Aqua | D13: 1500 | F13: =D13-E13 -> 1500
A14: 25/01/24 | B14: F552 | C14: DTL BWP | D14: 7000 | F14: =D14-E14 -> 7000
A15: 28/06/22 | B15: 2595 | C15: Kashif Askari Bank | D15: 1625 | F15: =D15-E15 -> 1625
A16: 29/05/23 | B16: 1519 | C16: Kashif Askari Bank | D16: 1700 | F16: =D16-E16 -> 1700
A17: 18/06/23 | B17: 1920 | C17: Kashif Askari Bank | D17: 5000 | F17: =D17-E17 -> 5000
A18: 44936 | B18: E1435 | C18: Kashif Askari Bank | D18: 3600 | F18: =D18-E18 -> 3600
A19: 19/02/24 | B19: F798 | C19: Master Mukhtar Sb | D19: 7200 | E19: 3800 | F19: =D19-E19 -> 3400
A20: 26/02/24 | B20: F875 | C20: Ishfaq Ahmed sb A.P | D20: 40000 | F20: =D20-E20 -> 40000
A21: 45354 | B21: F945 | C21: Jeo Water | D21: 12880 | F21: =D21-E21 -> 12880
A22: 29/04/24 | B22: F1565 | C22: arshad Ajwah Water | D22: 12400 | F22: =D22-E22 -> 12400
A23: 20/05/24 | B23: F1829 | C23: Al Safina Watet | D23: 900 | F23: =D23-E23 -> 900
A24: 22/05/24 | B24: F1844 | C24: Asfand Sb | D24: 1500 | F24: =D24-E24 -> 1500
A25: 45297 | B25: G5 | C25: Hamad Sb | D25: 1200 | F25: =D25-E25 -> 1200
A26: 25/6/24 | B26: G232 | C26: Aman sab | D26: 1500 | F26: =D26-E26 -> 1500
A27: 27/6/24 | B27: G249 | C27: Naseer Ahmad sab | D27: 236993 | E27: 236993 | F27: =D27-E27 -> 0
A28: 30/6/24 | B28: G286 | C28: Waqar sab Ecofina | D28: 10000 | F28: =D28-E28 -> 10000
A29: 21/7/24 | B29: G476 | C29: Kifayat | D29: 10094 | E29: 5000 | F29: =D29-E29 -> 5094
A30: 30/7/24 | B30: G557 | C30: Prof. Nasir Sb | D30: 1500 | E30: 1500 | F30: =D30-E30 -> 0
A31: 24/8/24 | B31: G917 | C31: Zahid sab | D31: 7000 | F31: =D31-E31 -> 7000
A32: 29/8/24 | B32: G969 | C32: Irshad Shah sab | D32: 2200 | F32: =D32-E32 -> 2200
A33: 26/9/24 | B33: G1064 | C33: Fasial Dewan sab | D33: 5500 | F33: =D33-E33 -> 5500
A34: 26/9/24 | B34: G1069 | C34: Irshad Shah sab | D34: 2050 | E34: 600 | F34: =D34-E34 -> 1450
A35: 28/9/24 | B35: G1079 | C35: 7/Blue (Naveed) | D35: 4820 | E35: 4820 | F35: =D35-E35 -> 0
A36: 13/10/24 | B36: G1210 | C36: Asghar Awan | D36: 9700 | E36: 9700 | F36: =D36-E36 -> 0
A37: 45300 | B37: G996 | C37: Master Abdul Ghafoor sab | D37: 79890 | F37: =D37-E37 -> 79890
A38: 28/10/24 | B38: G1354 | C38: Dr Jameel Sb LD | D38: 15415 | E38: 6500 | F38: =D38-E38 -> 8915
A39: 30/10/24 | B39: G1374 | C39: Mahar Ejaz sb | D39: 1500 | E39: 1500 | F39: =D39-E39 -> 0
A40: 31/10/24 | B40: G1384 | C40: Al Shifa Ghulam Yaseen sb | D40: 14000 | E40: 14000 | F40: =D40-E40 -> 0
A41: 16/11/24 | B41: G1540 | C41: Asif sb (Sukkur) | D41: 6000 | F41: =D41-E41 -> 6000
A42: 18/11/24 | B42: G1551 | C42: Ikrama Perwaz Water | D42: 1554 | F42: =D42-E42 -> 1554
A43: 20/11/24 | B43: G1581 | C43: Ishfaq Abasi sb | D43: 1600 | F43: =D43-E43 -> 1600
A44: 24/11/24 | B44: G1607 | C44: Pro Esencia | D44: 4050 | E44: 4050 | F44: =D44-E44 -> 0
A45: 28/11/24 | B45: G1647 | C45: Dialysis Unit | D45: 1000 | F45: =D45-E45 -> 1000
A46: 24/11/24 | B46: G1614 | C46: Control Shed Lodhran | D46: 37600 | F46: =D46-E46 -> 37600
A47: 30/11/24 | B47: G1660 | C47: Paka Bara | D47: 12000 | F47: =D47-E47 -> 12000
A48: 45363 | B48: G1686 | C48: Masood (House) | D48: 7600 | F48: =D48-E48 -> 7600
A49: 23/11/24 | B49: G1595 | C49: Ahmed Pur Shehroz Lodhi Control Shed | D49: 12000 | F49: =D49-E49 -> 12000
A50: 45424 | B50: G1711 | C50: Imran Ullah sb | D50: 1500 | F50: =D50-E50 -> 1500
A51: 45363 | B51: G1689 | C51: Saleem Abbas Nagar | D51: 8075 | E51: 8075 | F51: =D51-E51 -> 0 | G51: extra amount paid by qazi sb
A52: 45363 | B52: G1695 | C52: Yousaf Nurani sb | D52: 5550 | F52: =D52-E52 -> 5550
A53: 45485 | B53: G1721 | C53: Munawar Dewan | D53: 1500 | F53: =D53-E53 -> 1500
A54: 19/12/24 | B54: G1822 | C54: Pro Esencia | D54: 4050 | E54: 4050 | F54: =D54-E54 -> 0
A55: 21/12/24 | B55: G1836 | C55: Pro Esencia | D55: 3000 | E55: 3000 | F55: =D55-E55 -> 0 | G55: 2575 amount received in Bill H20 as remaining amount
A56: 22/12/2024 | B56: G1848 | C56: Bilal sb Liaqatpur | D56: 5200 | F56: =D56-E56 -> 5200
A57: 24/11/24 | B57: G1614 | C57: Sibat e Alam | D57: 37600 | E57: 37600 | F57: =D57-E57 -> 0 | G57: received IBFT
A58: 25/12/24 | B58: G1882 | C58: Shahid Sb (Excise Home) | D58: 8500 | F58: =D58-E58 -> 8500
A59: 26/12/24 | B59: G1887 | C59: Akhtar Awan sb | D59: 1700 | F59: =D59-E59 -> 1700
A60: 28/12/24 | B60: G1899 | C60: Pro Esencia | D60: 3745 | E60: 3745 | F60: =D60-E60 -> 0
A61: 28/12/24 | B61: G1905 | C61: Arslan sb (Remaining Amount) | F61: =D61-E61 -> 0
A62: 29/12/24 | B62: G1931 | C62: MD Foods | D62: 23310 | E62: 23310 | F62: =D62-E62 -> 0 | G62: 45658
A63: 29/12/24 | B63: G1915 | C63: Noman sb (Wapda Office) | D63: 740 | F63: =D63-E63 -> 740
A64: 30/12/24 | B64: G1919 | C64: TMA (BWP) | D64: 300 | F64: =D64-E64 -> 300
A65: 31/12/24 | B65: G1927 | C65: Post Graduate College | D65: 2500 | E65: 2500 | F65: =D65-E65 -> 0
A66: 45689 | B66: H18 | C66: MD Foods | D66: 7770 | E66: 7770 | F66: =D66-E66 -> 0
A67: 45748 | B67: H26 | C67: Saood House | D67: 7500 | E67: 7500 | F67: =D67-E67 -> 0
A68: 45809 | B68: H54 | C68: Yousaf Nurani sb | D68: 500 | E68: 500 | F68: =D68-E68 -> 0
A69: 45839 | B69: H69 | C69: Hamad sb | D69: 550 | F69: =D69-E69 -> 550
A70: 45870 | B70: H73 | C70: Al Safina Water LD | D70: 2750 | F70: =D70-E70 -> 2750
A71: 45901 | B71: H87 | C71: Pro Esencia (Remaining Amount) | D71: 3050 | E71: 3050 | F71: =D71-E71 -> 0
A72: 15/1/25 | B72: H237 | C72: Professor Abdul Nasir sb | D72: 800 | F72: =D72-E72 -> 800
A73: 16/1/25 | B73: H248 | C73: Control Shed Kashif Bano Feed | D73: 19000 | E73: 19000 | F73: =D73-E73 -> 0 | G73: IBFT Received
A74: 16/1/25 | B74: H256 | C74: Ahsan sb (Mobile Shop) | D74: 1200 | F74: =D74-E74 -> 1200
A75: 21/1/25 | B75: H287 | C75: Al Safa Water (Ghulam Muheudeen sb ) | D75: 14000 | E75: 14000 | F75: =D75-E75 -> 0
A76: 25/1/25 | B76: H325 | C76: Pro Esencia (Remaining Amount) | D76: 3470 | E76: 3370 | F76: =D76-E76 -> 100
A77: 27/1/25 | B77: H345 | C77: Ikram sb (Asia Pure Water) Lodhran | D77: 2600 | E77: 2600 | F77: =D77-E77 -> 0
A78: 27/1/25 | B78: H346 | C78: Qazi Anas sb Tuck Shop | D78: 12900 | F78: =D78-E78 -> 12900
A79: 28/1/25 | B79: H357 | C79: Usman sb | D79: 13085 | F79: =D79-E79 -> 13085
A80: 28/1/25 | B80: H361 | C80: Dr Tariq Dental | D80: 1000 | E80: 1000 | F80: =D80-E80 -> 0
A81: 28/1/25 | B81: H362 | C81: RohimWater | D81: 1810 | F81: =D81-E81 -> 1810
A82: 45749 | B82: H420 | C82: Saood House | D82: 7500 | E82: 7500 | F82: =D82-E82 -> 0
A83: 45690 | B83: H1936 | C83: Pro Esencia | D83: 4190 | E83: 4050 | F83: =D83-E83 -> 140
A84: 45810 | B84: H442 | C84: Pro Esencia | D84: 3370 | E84: 3370 | F84: =D84-E84 -> 0
A85: 45993 | B85: H495 | C85: Saleem Chishti sb | D85: 1500 | E85: 1500 | F85: =D85-E85 -> 0
A86: 45993 | B86: H501 | C86: Itifaq Carton Factory | D86: 2250 | E86: 2250 | F86: =D86-E86 -> 0
A87: 13/2/25 | B87: H510 | C87: Pro Esencia | D87: 4000 | E87: 4000 | F87: =D87-E87 -> 0
A88: 13/2/25 | B88: H521 | C88: Munawar Dewan | D88: 1500 | F88: =D88-E88 -> 1500
A89: 45902 | B89: H467 | C89: Yaseen sb Tailor | D89: 2450 | F89: =D89-E89 -> 2450
A90: 13/2/25 | B90: H509 | C90: Sibat e Alam | D90: 1500 | F90: =D90-E90 -> 1500
A91: 15/2/25 | B91: H530 | C91: Professor Shaheen sb | D91: 7800 | E91: 7500 | F91: =D91-E91 -> 300
A92: 17/2/25 | B92: H551 | C92: Asia Pure Water | D92: 8050 | F92: =D92-E92 -> 8050
A93: 18/2/25 | B93: H564 | C93: Ahmed sb (DTL) | D93: 2150 | F93: =D93-E93 -> 2150
A94: 18/2/25 | B94: H572 | C94: Asghar sb Jesh Mohammad | D94: 3388 | F94: =D94-E94 -> 3388
A95: 20/2/25 | B95: H588 | C95: Comprehensive School | D95: 27450 | E95: 27450 | F95: =D95-E95 -> 0
A96: 22/2/25 | B96: H599 | C96: Irtaza Smart Water | D96: 2800 | F96: =D96-E96 -> 2800
A97: 22/2/25 | B97: H611 | C97: Satluj Water | D97: 4070 | F97: =D97-E97 -> 4070
A98: 24/2/25 | B98: H628 | C98: Asia Pure Water | D98: 3450 | F98: =D98-E98 -> 3450
A99: 25/2/25 | B99: H648 | C99: Qari Sheikh Yaqoob Sb | D99: 2400 | F99: =D99-E99 -> 2400
A100: 26/2/25 | B100: H652 | C100: Haji Sb Maroot Ice Factory | D100: 21600 | F100: =D100-E100 -> 21600
A101: 26/2/25 | B101: H659 | C101: Al Safina | D101: 900 | F101: =D101-E101 -> 900
A102: 27/2/25 | B102: H664 | C102: Usmania Protein LHR | D102: 15100 | E102: 15100 | F102: =D102-E102 -> 0
...

Sheet MD Foods
A1: LEDGER
A3: Account Holder's Name | D3: M/D Foods
A4: Pg #
A5: Date | B5: Ref No. | C5: Description | D5: Debit | E5: Credit
A6: 22/9/2025 | B6: I 1347 | C6: M/D Foods ( Sajid sb) Paid | D6: 31920
A7: 28/9/2025 | B7: I 1408 | C7: MD Foods | E7: 30996 | F7: =F6+E7-D7 -> 30996
A8: 45667 | B8: I 1462 | C8: MD Foods | E8: 30300 | F8: =F7+E8-D8 -> 61296
A9: 45698 | B9: I 1483 | C9: MD Foods | E9: 29520 | F9: =F8+E9-D9 -> 90816
A10: 45879 | B10: I 1569 | C10: MD Foods | E10: 17556 | F10: =F9+E10-D10 -> 108372
C11: MD Foods IBFT | D11: 50000 | F11: =F10+E11-D11 -> 58372
C12: MD Foods IBFT | D12: 50000 | F12: =F11+E12-D12 -> 8372
A13: 13/10/25 | B13: I 1616 | C13: 6L+ caps | E13: 30240 | F13: =F12+E13-D13 -> 38612
A14: 13/10/2025 | B14: I 1621 | C14: Jumbo PPF | E14: 2000 | F14: =F13+E14-D14 -> 40612
A15: 16/10/25 | B15: I 1657 | C15: Membrane washing…. | E15: 5500 | F15: =F14+E15-D15 -> 46112
A16: 20/10/25 | B16: I 1713 | C16: 5L+caps | E16: 31920 | F16: =F15+E16-D16 -> 78032
C17: 6L+caps(351 Bottles Returen) | D17: 14742 | F17: =F16+E17-D17 -> 63290
A18: 22/11/25 | B18: EXP sheet | F18: =F17+E18-D18 -> 63290
C19: received by qazi sb | D19: 50000 | F19: =F18+E19-D19 -> 13290
A20: 22/11/25 | C20: bank transfer to qazi sb | D20: 13000 | F20: =F19+E20-D20 -> 290
A21: 30/11/25 | B21: j254 | C21: 1.5l bottle+shoper | E21: 0 | F21: 0
A22: 22/11/25 | B22: j163 | C22: s.s filling nupzle | E22: 2400 | F22: =F21+E22-D22 -> 2400
A23: 28/1/26 | B23: j902 | C23: jumboppf+sand +gravel +vessel | E23: 20200 | F23: =F22+E23-D23 -> 22600
A24: 46236 | B24: j1055 | C24: elbow | E24: 1500 | F24: =F23+E24-D24 -> 24100
A25: 46267 | C25: finael etc... | E25: 18500 | F25: =F24+E25-D25 -> 42600
F26: =F25+E26-D26 -> 42600
F27: =F26+E27-D27 -> 42600
F28: =F27+E28-D28 -> 42600
F29: =F28+E29-D29 -> 42600
F30: =F29+E30-D30 -> 42600
F31: =F30+E31-D31 -> 42600
F32: =F31+E32-D32 -> 42600
F33: =F32+E33-D33 -> 42600
F34: =F33+E34-D34 -> 42600
A35: Grand tatal | F35: =F34+E35-D35 -> 42600

Sheet Gysing Pak Water
A1: LEDGER
A3: Account Holder's Name | D3: Gysing Pak Water
A4: Pg # | C4: New Reg(35) | M4: 1785
A5: Date | B5: Ref No. | C5: Description | D5: Debit | E5: Credit | F5: Balance
C6: Old Balance | E6: 157180 | F6: =E6-D6 -> 157180
A7: 25/01/24 | B7: Exp Sh | C7: Cash Deposit | D7: 97300 | F7: =F6-D7+E7 -> 59880
A8: 45293 | B8: F605 | C8: 12L Bottle | E8: 27500 | F8: =F7-D8+E8 -> 87380
A9: 45445 | B9: F661 | C9: 1.5L Bottle,.. | E9: 54600 | F9: =F8-D9+E9 -> 141980
A10: 15/02/24 | B10: F757 | C10: 12L Bottle | E10: 27000 | F10: =F9-D10+E10 -> 168980
A11: 15/02/24 | B11: Exp Sh | C11: Cash Deposit | D11: 109200 | F11: =F10-D11+E11 -> 59780
A12: 18/02/4 | B12: F786 | C12: 1.5L Bottle,.. | E12: 50400 | F12: =F11-D12+E12 -> 110180
A13: 45294 | C13: Cash Deposit | D13: 104000 | F13: =F12-D13+E13 -> 6180
A14: 45294 | C14: Discount | D14: 6180 | F14: =F13-D14+E14 -> 0
A15: 45385 | B15: F953 | C15: 1.5L Bottle,.. | E15: 39020 | F15: =F14-D15+E15 -> 39020
A16: 45385 | B16: F954 | C16: 500 ml Bottle | E16: 36460 | F16: =F15-D16+E16 -> 75480
A17: 14/03/24 | B17: F1069 | C17: 12L Bottle | E17: 32450 | F17: =F16-D17+E17 -> 107930
A18: 16/3/24 | B18: Exp Sh | C18: Cash Deposit | D18: 25000 | F18: =F17-D18+E18 -> 82930
A19: 20/03/24 | B19: F1113 | C19: 6L Bottle | E19: 6840 | F19: =F18-D19+E19 -> 89770
A20: 25/03/24 | B20: F1162 | C20: 500 ml Bottle | E20: 36460 | F20: =F19-D20+E20 -> 126230
A21: 25/03/24 | B21: F1161 | C21: 1.5L Bottle | E21: 46830 | F21: =F20-D21+E21 -> 173060
A22: 25/03/24 | B22: Exp Sh | C22: Net Cash Dep | D22: 27700 | F22: =F21-D22+E22 -> 145360
A23: 25/03/24 | B23: Exp Sh | C23: Discount | D23: 180 | F23: =F22-D23+E23 -> 145180
C24: 19L Bad Bottle(226B) | D24: 22600 | F24: =F23-D24+E24 -> 122580
A25: 45386 | B25: Exp Sh | C25: Cash Deposit | D25: 100000 | F25: =F24-D25+E25 -> 22580
A26: 45386 | B26: Exp Sh | C26: Discount | D26: 300 | F26: =F25-D26+E26 -> 22280
A27: 45386 | B27: F1263 | C27: 1.5L Bottle | E27: 47040 | F27: =F26-D27+E27 -> 69320
A28: 45386 | B28: F1266 | C28: 500 ml Bottle | E28: 36720 | F28: =F27-D28+E28 -> 106040
A29: 18/04/24 | B29: F1424 | C29: 12L Bottle | E29: 27000 | F29: =F28-D29+E29 -> 133040
A30: 18/04/24 | B30: F1425 | C30: 1.5L Bottle | E30: 55125 | F30: =F29-D30+E30 -> 188165
A31: 17/04/24 | B31: Exp Sh | C31: Cash Deposit | D31: 100000 | F31: =F30-D31+E31 -> 88165
A32: 45387 | C32: Cash Deposit | D32: 88000 | F32: =F31-D32+E32 -> 165
A33: 45387 | C33: Discount | D33: 165 | F33: =F32-D33+E33 -> 0
A34: 45478 | B34: F1675 | C34: 1.5L Bottle | E34: 63000 | F34: =F33-D34+E34 -> 63000
A35: 45478 | B35: F1676 | C35: 500 ml Bottle | E35: 49300 | F35: =F34-D35+E35 -> 112300
A36: 45478 | B36: F1664 | C36: Ca,Na | E36: 700 | F36: =F35-D36+E36 -> 113000
A37: 45601 | B37: F1718 | C37: 500 ml Bottle,.. | E37: 19440 | F37: =F36-D37+E37 -> 132440
A38: 22/05/24 | C38: Cash Deposit | D38: 131740 | F38: =F37-D38+E38 -> 700
A39: 22/05/24 | C39: Discount | D39: 300 | F39: =F38-D39+E39 -> 400
A40: 16/05/24 | B40: F1789 | C40: 1.5L Bottle | E40: 62720 | F40: =F39-D40+E40 -> 63120
A41: 23/05/24 | B41: F1867 | C41: 19Lpineo,.. | E41: 68000 | F41: =F40-D41+E41 -> 131120
A42: 25/05/24 | B42: F1896 | C42: 1.5L Bottle | E42: 11760 | F42: =F41-D42+E42 -> 142880
A43: 27/05/24 | B43: F1929 | C43: 6L Bottle | E43: 12798 | F43: =F42-D43+E43 -> 155678
A44: 28/05/24 | B44: F1355 | C44: Pump Seal,.. | E44: 5500 | F44: =F43-D44+E44 -> 161178
A45: 29/05/24 | B45: F1361 | C45: 12L Bottle | E45: 42644 | F45: =F44-D45+E45 -> 203822
A46: 45297 | B46: F1992 | C46: 1.5L Bottle | E46: 64400 | F46: =F45-D46+E46 -> 268222
A47: 45328 | B47: G22 | C47: 500 ml Bottle | E47: 51000 | F47: =F46-D47+E47 -> 319222
A48: 45328 | B48: Exp Sh | C48: Cash Deposit | D48: 100000 | F48: =F47-D48+E48 -> 219222
A49: 45510 | B49: Exp Sh | C49: Cash Deposit | D49: 65500 | F49: =F48-D49+E49 -> 153722
A50: 45510 | B50: G88 | C50: 6L Bottle | E50: 9950 | F50: =F49-D50+E50 -> 163672
A51: 45632 | B51: G125 | C51: 500 ml Bottle | E51: 31875 | F51: =F50-D51+E51 -> 195547
A52: 45632 | B52: G126 | C52: 1.5L Bottle | E52: 9660 | F52: =F51-D52+E52 -> 205207
A53: 15/6/24 | B53: G156 | C53: 6L Bottle + Caps | E53: 9954 | F53: =F52-D53+E53 -> 215161
A54: 16/6/24 | B54: Exp Sh | C54: Cash Deposit | D54: 100000 | F54: =F53-D54+E54 -> 115161
A55: 25/6/24 | B55: G239 | C55: 12L Bottle | E55: 8100 | F55: =F54-D55+E55 -> 123261
A56: 27/6/24 | B56: G262 | C56: 1.5L-Caps | E56: 27370 | F56: =F55-D56+E56 -> 150631
A57: 45329 | B57: G306 | C57: 1.5L -Caps | E57: 40250 | F57: =F56-D57+E57 -> 190881
A58: 45329 | B58: G307 | C58: 500ml- caps | E58: 35700 | F58: =F57-D58+E58 -> 226581
A59: 45572 | B59: G401 | C59: 1.5L-Caps | E59: 16100 | F59: =F58-D59+E59 -> 242681
A60: 14/7/24 | B60: G428 | C60: 1.5L-Caps | E60: 64400 | F60: =F59-D60+E60 -> 307081
A61: 20/7/24 | B61: G456 | C61: 500ml- caps, 1.5-caps | E61: 29525 | F61: =F60-D61+E61 -> 336606
A62: 20/7/24 | B62: G457 | C62: 30mm caps | E62: 5200 | F62: =F61-D62+E62 -> 341806
A63: 45572 | C63: exp sheet | D63: 100000 | F63: =F62-D63+E63 -> 241806
A64: 23/7/24 | C64: Cash Deposit | D64: 70000 | F64: =F63-D64+E64 -> 171806
A65: 23/7/24 | C65: 19L Bad Bottle difference | D65: 3000 | F65: =F64-D65+E65 -> 168806
A66: 27/7/24 | B66: G522 | C66: 500ml - caps | E66: 38250 | F66: =F65-D66+E66 -> 207056
A67: 27/7/24 | B67: G523 | C67: 1.5L-Caps | E67: 32200 | F67: =F66-D67+E67 -> 239256
A68: 45359 | B68: G586 | C68: 1.5L- caps | E68: 12075 | F68: =F67-D68+E68 -> 251331
A69: 45542 | B69: Exp Sh | C69: Cash Deposit | D69: 3950 | F69: =F68-D69+E69 -> 247381
A70: 45512 | C70: Cash Deposit | D70: 150000 | F70: =F69-D70+E70 -> 97381
A71: 45573 | B71: G738 | C71: 1.5L- caps, 500ml - caps | E71: 35425 | F71: =F70-D71+E71 -> 132806
A72: 15/8/2024 | C72: Cash Deposit | D72: 15000 | F72: =F71-D72+E72 -> 117806
A73: 15/8/2024 | C73: Cash Deposit | D73: 1000 | F73: =F72-D73+E73 -> 116806
A74: 15/8/2024 | B74: G778 | C74: 1 1/2 L Bottle | E74: 8400 | F74: =F73-D74+E74 -> 125206
A75: 19/8/2024 | B75: G779 | C75: 1.5L- caps, 500ml - caps | E75: 11875 | F75: =F74-D75+E75 -> 137081
A76: 21/8/2024 | B76: G778 | C76: Discount | D76: 350 | F76: =F75-D76+E76 -> 136731
A77: 21/8/24 | C77: Cash Deposit | D77: 43475 | F77: =F76-D77+E77 -> 93256
A78: 25/8/24 | B78: G937 | C78: 500ml - caps, 1.5L - caps, 6L + Caps | E78: 43715 | F78: =F77-D78+E78 -> 136971
A79: 45482 | B79: G667 | C79: 1.5L- caps, 500ml - caps | E79: 38380 | F79: =F78-D79+E79 -> 175351
A80: 21/9/24 | C80: Cash Deposit | D80: 120000 | F80: =F79-D80+E80 -> 55351
A81: 23/9/24 | B81: G1030 | C81: PPF 10" | E81: 600 | F81: =F80-D81+E81 -> 55951
A82: 26/9/24 | B82: G1055 | C82: 1.5L - Caps | E82: 11270 | F82: =F81-D82+E82 -> 67221
A83: 28/9/24 | B83: G1082 | C83: 1.5L- Caps | E83: 11270 | F83: =F82-D83+E83 -> 78491
A84: 21/9/24 | B84: G885 | C84: 500ml- caps | E84: 51000 | F84: =F83-D84+E84 -> 129491
A85: 45361 | C85: Cash Deposit | D85: 600 | F85: =F84-D85+E85 -> 128891
A86: 45361 | C86: Cash Deposit | D86: 40000 | F86: =F85-D86+E86 -> 88891
A87: 45361 | B87: G1138 | C87: 1.5L- Caps | E87: 28175 | F87: =F86-D87+E87 -> 117066
A88: 45514 | B88: G1179 | C88: 500ml- Caps | E88: 7650 | F88: =F87-D88+E88 -> 124716
A89: 17/10/24 | C89: Cash Deposit | D89: 51000 | F89: =F88-D89+E89 -> 73716
A90: 17/10/24 | B90: G1261 | C90: 500ml - Caps, 1.5L - Caps | E90: 47105 | F90: =F89-D90+E90 -> 120821
A91: 19/10/24 | C91: Cash Deposit | D91: 15000 | F91: =F90-D91+E91 -> 105821
A92: 24/10/24 | B92: G1314 | C92: Jumbo Gold, | E92: 3000 | F92: =F91-D92+E92 -> 108821
A93: 29/10/24 | B93: Exp Sh | C93: Cash Deposit | D93: 3000 | F93: =F92-D93+E93 -> 105821
A94: 45393 | B94: G1424 | C94: 12L Bottle Pet | E94: 56000 | F94: =F93-D94+E94 -> 161821
A95: 45393 | B95: G1425 | C95: 500ml - Caps | E95: 12750 | F95: =F94-D95+E95 -> 174571
A96: 45423 | B96: G1433 | C96: 500ml - Caps | E96: 6375 | F96: =F95-D96+E96 -> 180946
A97: 45484 | C97: Cash Deposit | D97: 70000 | F97: =F96-D97+E97 -> 110946
A98: 45333 | B98: G1453 | C98: 1.5L - Caps | E98: 16100 | F98: =F97-D98+E98 -> 127046
A99: 16/11/24 | C99: Cash Deposit | D99: 47000 | F99: =F98-D99+E99 -> 80046
A100: 16/11/24 | B100: G1531 | C100: 500ml - Caps, Jumbo PPF Gold, Slim PPF Gold | E100: 27000 | F100: =F99-D100+E100 -> 107046
A101: 19/11/24 | B101: G1563 | C101: 1.5L - Caps | E101: 12880 | F101: =F100-D101+E101 -> 119926
...

Sheet Usman Zubair.
A1: LEDGER
A3: Account Holder's Name | D3: Usman Zubair
A4: Pg #
A5: Date | B5: Ref No. | C5: Description | D5: Debit | E5: Credit
A6: 45880 | B6: I1987 | C6: Remaining Amount | E6: 19038 | F6: 19038
A7: 15/11/25 | B7: j82 | C7: Remaining Amount | E7: 500 | F7: =F6+E7-D7 -> 19538
A8: 19/11/25 | B8: j99 | C8: cash deposit | D8: 500 | F8: =F7+E8-D8 -> 19038
A9: 19/11/25 | B9: j125 | C9: Remaining Amount | E9: 520 | F9: =F8+E9-D9 -> 19558
A10: 22/11/25 | B10: j157 | C10: Remaining Amount | E10: 175 | F10: =F9+E10-D10 -> 19733
A11: 24/11/25 | B11: j190 | C11: Remaining Amount | E11: 556 | F11: =F10+E11-D11 -> 20289
A12: 26/11/25 | B12: EXp sheet | C12: cash deposit | D12: 556 | F12: =F11+E12-D12 -> 19733
A13: 29/11/25 | B13: j251 | C13: Remaining Amount | E13: 1130 | F13: =F12+E13-D13 -> 20863
A14: 30/11/25 | B14: EXp sheet | C14: cash deposit | D14: 500 | F14: =F13+E14-D14 -> 20363
A15: 30/11/25 | B15: EXp sheet | C15: cash deposit | D15: 450 | F15: =F14+E15-D15 -> 19913
A16: 45820 | B16: j337 | C16: Remaining Amount | E16: 4660 | F16: =F15+E16-D16 -> 24573
A17: 45820 | B17: j358 | C17: Remaining Amount | E17: 55 | F17: =F16+E17-D17 -> 24628
A18: 45759 | B18: j324 | C18: 1.5l shoper | E18: 1760 | F18: =F17+E18-D18 -> 26388
A19: 45881 | B19: EXp sheet | C19: cash deposit | D19: 7350 | F19: =F18+E19-D19 -> 19038
A20: 45881 | B20: j367 | C20: Remaining Amount | E20: 4810 | F20: =F19+E20-D20 -> 23848
A21: 45942 | B21: EXp sheet | C21: cash deposit | D21: 4800 | F21: =F20+E21-D21 -> 19048
A22: 45942 | B22: j391 | C22: Remaining Amount | E22: 380 | F22: =F21+E22-D22 -> 19428
A23: 45942 | B23: j392 | C23: 1.5l label | E23: 3600 | F23: =F22+E23-D23 -> 23028
A24: 24/1/26 | B24: j870 | C24: 1.5+caps... | E24: 6000 | F24: =F23+E24-D24 -> 29028
A25: 27/1/26 | B25: EXp sheet | C25: easy paisa | D25: 5000 | F25: =F24+E25-D25 -> 24028
A26: 27/1/26 | B26: EXp sheet | C26: cash deposit | D26: 1000 | F26: =F25+E26-D26 -> 23028
A27: 46055 | B27: j962 | C27: Remaining Amount | E27: 8965 | F27: =F26+E27-D27 -> 31993
A28: 46083 | B28: EXp sheet | C28: easy paisa | D28: 8500 | F28: =F27+E28-D28 -> 23493
A29: 46114 | B29: EXp sheet | C29: cash deposit | D29: 465 | F29: =F28+E29-D29 -> 23028
A30: 46114 | B30: j1009 | C30: Remaining Amount | E30: 23500 | F30: =F29+E30-D30 -> 46528
A31: 46144 | C31: received by qazi sb cash in hand | D31: 23500 | F31: =F30+E31-D31 -> 23028
A32: 46267 | B32: j1063 | C32: 1.5l+caps+500ml +caps | E32: 24158 | F32: =F31+E32-D32 -> 47186
A33: 46267 | B33: EXp sheet | C33: easy paisa | D33: 6000 | F33: =F32+E33-D33 -> 41186
A34: 46297 | B34: EXp sheet | C34: jazz cash | D34: 4000 | F34: =F33+E34-D34 -> 37186
A35: 46328 | B35: EXp sheet | C35: cash deposit | D35: 3400 | F35: =F34+E35-D35 -> 33786
A36: 46328 | B36: EXp sheet | C36: easy paisa | D36: 3500 | F36: =F35+E36-D36 -> 30286
A37: 46358 | B37: j1111 | C37: cash deposit | D37: 5170 | F37: =F36+E37-D37 -> 25116
A38: 16/2/26 | B38: j1154 | C38: 6l | E38: 3690 | F38: =F37+E38-D38 -> 28806
A39: 16/2/26 | B39: EXp sheet | C39: cash deposit | D39: 19038 | F39: =F38+E39-D39 -> 9768
A40: 46357 | B40: EXp sheet | C40: cash deposit | D40: 1900 | F40: =F39+E40-D40 -> 7868
A41: 18/2/26 | B41: j1189 | C41: 1.5l +caps.... | E41: 7265 | F41: =F40+E41-D41 -> 15133
F42: =F41+E42-D42 -> 15133
F43: =F42+E43-D43 -> 15133
F44: =F43+E44-D44 -> 15133
F45: =F44+E45-D45 -> 15133
F46: =F45+E46-D46 -> 15133
F47: =F46+E47-D47 -> 15133
A48: Grand Total | F48: =F47+E48-D48 -> 15133

Sheet Dr.Jameel Sab
A1: LEDGER
A3: Account Holder's Name | D3: Dr. Jameel Sab
A4: Pg # | C4: Old Reg(98)
A5: Date | B5: Ref No. | C5: Description | D5: Deposit | E5: Credit | F5: Balance
A6: 28/10/2024 | B6: G 1354 | D6: 6500 | E6: 15415 | F6: =E6-D6 -> 8915
A7: 19/6/2025 | B7: I 39 | C7: 1.5L caps…. | E7: 14599 | F7: 23514
A8: 45997 | B8: Ex Sheet | C8: Cash Deposit | D8: 5450 | F8: =F7+E8-D8 -> 18064
A9: 14/6/2025 | B9: H 132 | C9: 1.5L Labour… | E9: 7500 | F9: =F8+E9-D9 -> 25564
A10: 14/6/2025 | B10: Ex Sheet | C10: Cash Deposit | D10: 1250 | F10: =F9+E10-D10 -> 24314
A11: 15/6/2025 | B11: H 155 | C11: 1.5L shoper…. | E11: 13575 | F11: =F10+E11-D11 -> 37889
A12: 15/6/2025 | B12: Ex Sheet | C12: Cash Deposit | D12: 7500 | F12: =F11+E12-D12 -> 30389
A13: 17/6/2025 | B13: H 200 | C13: 500ml caps…. | E13: 22081 | F13: =F12+E13-D13 -> 52470
A14: 17/6/2025 | B14: Ex Sheet | C14: Cash Deposit | D14: 10000 | F14: =F13+E14-D14 -> 42470
C15: Cash Deposit | D15: 3000 | F15: =F14+E15-D15 -> 39470
A16: 19/6/2025 | B16: Ex Sheet | C16: Cash Deposit | D16: 22000 | F16: =F15+E16-D16 -> 17470
A17: 21/6/2025 | B17: I 59 | C17: 1.5L shoper…. | E17: 1900 | F17: =F16+E17-D17 -> 19370
A18: 22/6/2025 | B18: Ex Sheet | C18: Cash Deposit | D18: 7600 | F18: =F17+E18-D18 -> 11770
C19: B.T | D19: 5400 | F19: =F18+E19-D19 -> 6370
A20: 23/6/2025 | B20: Ex Sheet | C20: Cash Deposit | D20: 3500 | F20: =F19+E20-D20 -> 2870
A21: 23/6/2025 | B21: I 72 | C21: 1.5L shoper…. | E21: 2800 | F21: =F20+E21-D21 -> 5670
A22: 25/6/2025 | B22: Ex Sheet | C22: Cash Deposit | D22: 2800 | F22: =F21+E22-D22 -> 2870
C23: B.T | D23: 2000 | F23: =F22+E23-D23 -> 870
A24: 25/6/2025 | B24: I 93 | C24: 1.5L shoper…. | E24: 6932 | F24: =F23+E24-D24 -> 7802
A25: 30/6/2025 | B25: Ex Sheet | C25: Cash Deposit | D25: 6000 | F25: =F24+E25-D25 -> 1802
A26: 45723 | B26: I 209 | C26: 500ml Seals… | E26: 2600 | F26: =F25+E26-D26 -> 4402
A27: 45876 | B27: I 266 | C27: 30mm caps | E27: 4250 | F27: =F26+E27-D27 -> 8652
A28: 45937 | B28: I 299 | C28: 1.5L shoper…. | E28: 4566 | F28: =F27+E28-D28 -> 13218
A29: 45998 | B29: I 327 | C29: 1.5L caps…. | E29: 7777 | F29: =F28+E29-D29 -> 20995
A30: 45998 | B30: Ex Sheet | C30: Cash Deposit | D30: 500 | F30: =F29+E30-D30 -> 20495
C31: B.T | D31: 4000 | F31: =F30+E31-D31 -> 16495
A32: 15/7/2025 | B32: Ex Sheet | C32: Cash Deposit B.T | D32: 2700 | F32: =F31+E32-D32 -> 13795
A33: 16/7/2025 | B33: I 374 | C33: 500L caps….. | E33: 5480 | F33: =F32+E33-D33 -> 19275
A34: 26/7/2025 | B34: I 493 | C34: 1.5L caps…. | E34: 11009 | F34: =F33+E34-D34 -> 30284
A35: 26/7/2025 | B35: Ex Sheet | C35: Cash Deposit | D35: 4300 | F35: =F34+E35-D35 -> 25984
C36: Cash Deposit | D36: 2500 | F36: =F35+E36-D36 -> 23484
A37: 28/7/2025 | B37: Ex Sheet | C37: Cash Deposit | D37: 8000 | F37: =F36+E37-D37 -> 15484
A38: 28/7/2025 | B38: I 524 | C38: 1.5L caps…. | E38: 16929 | F38: =F37+E38-D38 -> 32413
A39: 17/8/2025 | B39: I 782 | C39: 1.5L caps…. | E39: 4220 | F39: =F38+E39-D39 -> 36633
A40: 19/8/2025 | B40: I 1025 | C40: 1.5L caps…. | E40: 9844 | F40: =F39+E40-D40 -> 46477
A41: 19/8/2025 | B41: Ex Sheet | C41: Cash Deposit | D41: 4210 | F41: =F40+E41-D41 -> 42267
A42: 20/8/2025 | B42: Ex Sheet | C42: Cash Deposit | D42: 6000 | F42: =F41+E42-D42 -> 36267
A43: 20/8/2025 | B43: I 812 | C43: 30mm caps | E43: 2600 | F43: =F42+E43-D43 -> 38867
A44: 23/8/2025 | B44: Ex Sheet | C44: Cash Deposit | D44: 5000 | F44: =F43+E44-D44 -> 33867
A45: 23/8/2025 | B45: Ex Sheet | C45: Cash Deposit | D45: 1500 | F45: =F44+E45-D45 -> 32367
A46: 23/8/2025 | B46: I 842 | C46: 1.5L caps…. | E46: 8646 | F46: =F45+E46-D46 -> 41013
A47: 24/8/2025 | B47: I 860 | C47: 1.5L caps…. | E47: 11275 | F47: =F46+E47-D47 -> 52288
A48: 25/8/2025 | B48: Ex Sheet | C48: Cash Deposit | D48: 11200 | F48: =F47+E48-D48 -> 41088
A49: 24/8/2025 | B49: Ex Sheet | C49: Cash Deposit B.T | D49: 9500 | F49: =F48+E49-D49 -> 31588
A50: 25/8/2025 | B50: I 876 | C50: Cash Deposit | E50: 11246 | F50: =F49+E50-D50 -> 42834
A51: 28/8/2025 | B51: Exp Sheet | C51: Cash Deposit | D51: 7500 | F51: =F50+E51-D51 -> 35334
C52: B.T | D52: 2975 | F52: =F51+E52-D52 -> 32359
A53: 28/8/2025 | B53: I 924 | C53: 1.5L caps…. | E53: 10946 | F53: =F52+E53-D53 -> 43305
A54: 45725 | B54: I 993 | C54: 1.5L caps…. | E54: 1881 | F54: =F53+E54-D54 -> 45186
A55: 18/9/2025 | B55: I 1297 | C55: 1.5L caps…. | E55: 11452 | F55: =F54+E55-D55 -> 56638
A56: 20/9/2025 | B56: I 1315 | C56: 500ml - caps | E56: 3466 | F56: =F55+E56-D56 -> 60104
A57: 20/9/2025 | B57: Ex Sheet | C57: Cash Deposit | D57: 12000 | F57: =F56+E57-D57 -> 48104
B58: Ex Sheet | C58: IBFT | D58: 3466 | F58: =F57+E58-D58 -> 44638
A59: 29/9/2025 | B59: Ex Sheet | C59: Cash deposit | D59: 3460 | F59: =F58+E59-D59 -> 41178
A60: 30/9/2025 | B60: I 1456 | C60: Pending | E60: 56625 | F60: =F59+E60-D60 -> 97803
A61: 45942 | C61: shell old | D61: 15000 | F61: =F60+E61-D61 -> 82803
A62: 45942 | C62: membrane advance | D62: 10000 | F62: =F61+E62-D62 -> 72803
A63: 45942 | C63: old Advance deposit | D63: 5000 | F63: =F62+E63-D63 -> 67803
A64: 27/1/26 | B64: j893 | C64: 1.5l-caps | E64: 8035 | F64: =F63+E64-D64 -> 75838
A65: 29/1/26 | B65: Exp Sheet | C65: easy paisa | D65: 8035 | F65: =F64+E65-D65 -> 67803
A66: 29/1/26 | B66: j916 | C66: 1.5L caps…. | E66: 11496 | F66: =F65+E66-D66 -> 79299
F67: =F66+E67-D67 -> 79299
F68: =F67+E68-D68 -> 79299
F69: =F68+E69-D69 -> 79299
F70: =F69+E70-D70 -> 79299
F71: =F70+E71-D71 -> 79299
B72: Grand Total | F72: =F71+E72-D72 -> 79299

Sheet HB Water.
A1: LEDGER
A3: Account Holder's Name | D3: HB Water
A4: Pg #
A5: Date | B5: Ref No. | C5: Description | D5: Debit | E5: Credit | F5: Balance
A6: 26/7/25 | B6: I 498 | C6: HB Water | D6: 9828 | E6: 9828 | F6: =E6-D6 -> 0
A7: 30/7/2025 | B7: I 547 | C7: Remn Amnt | E7: 8000 | F7: =F6-D7+E7 -> 8000
A8: 30/7/25 | B8: I 547 | C8: Media Lable 6L (paid) | D8: 8000 | F8: =F7-D8+E8 -> 0
A9: 13/8/2025 | B9: Exp Sheet | C9: IBFT | D9: 13500 | F9: =F8-D9+E9 -> -13500
A10: 19/8/2025 | B10: I 1014 | C10: HB Water (Remn Amnt) | E10: 17640 | F10: =F9-D10+E10 -> 4140
A11: 23/8/2025 | B11: Exp Sheet | C11: IBFT | D11: 6500 | F11: =F10-D11+E11 -> -2360
A12: 24/8/2025 | B12: I 870 | C12: Remn Amnt | E12: 26908 | F12: =F11-D12+E12 -> 24548
A13: 26/8/2025 | B13: Exp Sheet | C13: IBFT | D13: 16000 | F13: =F12-D13+E13 -> 8548
A14: 28/8/2025 | B14: Exp Sheet | C14: HB Water BIFT | D14: 8900 | F14: =F13-D14+E14 -> -352
A15: 31/8/2025 | B15: I 950 | C15: HB Water (Remn Amnt) | E15: 15060 | F15: =F14-D15+E15 -> 14708
A16: 31/8/2025 | B16: Exp Sheet | C16: HB Water | D16: 1640 | F16: =F15-D16+E16 -> 13068
A17: 45725 | B17: I 1040 | C17: HB Water (Remn Amnt) | E17: 25628 | F17: =F16-D17+E17 -> 38696
A18: 45725 | B18: Exp Sheet | C18: Cash Deposit | D18: 15000 | F18: =F17-D18+E18 -> 23696
A19: 45909 | B19: Exp Sheet | C19: IBFT | D19: 15000 | F19: =F18-D19+E19 -> 8696
A20: 45970 | B20: I 1166 | C20: HB Water Remn Amnt | E20: 42550 | F20: =F19-D20+E20 -> 51246
A21: 13/9/2025 | B21: Exp Sheet | C21: IBFT | D21: 42550 | F21: =F20-D21+E21 -> 8696
A22: 45970 | B22: I 1143 | C22: Remn Amnt | E22: 11530 | F22: =F21-D22+E22 -> 20226
A23: 13/9/2025 | B23: I 1201 | C23: Remn Amnt | E23: 14664 | F23: =F22-D23+E23 -> 34890
A24: 13/9/2025 | B24: Exp Sheet | C24: HB Water (IBFT) | D24: 3900 | F24: =F23-D24+E24 -> 30990
A25: 17/9/2025 | B25: Exp Sheet | C25: HB Water IBFT | D25: 30000 | F25: =F24-D25+E25 -> 990
A26: 18/9/2025 | B26: I 1307 | C26: Remaining Amount | E26: 22950 | F26: =F25-D26+E26 -> 23940
A27: 22/9/2025 | B27: Exp Sheet | C27: IBFT | D27: 15000 | F27: =F26-D27+E27 -> 8940
A28: 24/9/2025 | B28: I 1377 | C28: Remaining Amount | E28: 24260 | F28: =F27-D28+E28 -> 33200
A29: 30/9/2025 | B29: Exp Sheet | C29: Cash Deposit | D29: 20000 | F29: =F28-D29+E29 -> 13200
A30: 45667 | B30: I 1476 | C30: Remaining Amount | E30: 24000 | F30: =F29-D30+E30 -> 37200
A31: 45757 | B31: Exp Sheet | C31: Cash Deposit | D31: 11000 | F31: =F30-D31+E31 -> 26200
A32: 45787 | B32: Exp Sheet | C32: Cash Deposit | D32: 4000 | F32: =F31-D32+E32 -> 22200
A33: 45879 | B33: I 1573 | C33: Remaining Amount | E33: 16300 | F33: =F32-D33+E33 -> 38500
A34: 45971 | B34: Exp Sheet | C34: IBFT | D34: 9200 | F34: =F33-D34+E34 -> 29300
A35: 46001 | B35: I 1610 | C35: 500ml seal…. | E35: 1450 | F35: =F34-D35+E35 -> 30750
A36: 46001 | B36: Exp Sheet | C36: IBFT | D36: 3000 | F36: =F35-D36+E36 -> 27750
A37: 13/10/25 | B37: I 1625 | C37: Remn Amnt | E37: 10460 | F37: =F36-D37+E37 -> 38210
A38: 15/10/25 | B38: Exp Sheet | C38: Cash Deposit | D38: 19000 | F38: =F37-D38+E38 -> 19210
A39: 18/10/2025 | B39: I 1683 | C39: Remn Amnt | E39: 18580 | F39: =F38-D39+E39 -> 37790
A40: 21/10/25 | B40: Exp Sheet | C40: IBFT | D40: 10000 | F40: =F39-D40+E40 -> 27790
A41: 23/10/25 | B41: Exp Sheet | C41: IBFT | D41: 4500 | F41: =F40-D41+E41 -> 23290
A42: 23/10/25 | B42: Exp Sheet | C42: Cash Deposit | D42: 3500 | F42: =F41-D42+E42 -> 19790
A43: 23/10/25 | B43: I 1757 | C43: Remn Amnt | E43: 18680 | F43: =F42-D43+E43 -> 38470
A44: 27/10/25 | B44: Exp Sheet | C44: Cash Deposit | D44: 18000 | F44: =F43-D44+E44 -> 20470
A45: 30/10/25 | B45: Exp Sheet | C45: Cash Deposit | D45: 18000 | F45: =F44-D45+E45 -> 2470
A46: 30/10/25 | B46: I 1862 | C46: Remn Amnt | E46: 18790 | F46: =F45-D46+E46 -> 21260
A47: 45758 | B47: Exp Sheet | C47: Cash Deposit | D47: 21000 | F47: =F46-D47+E47 -> 260
A48: 45758 | B48: I 1926 | C48: Remn Amnt | E48: 17840 | F48: =F47-D48+E48 -> 18100
A49: 45819 | B49: I 1957 | C49: 500ml + caps…. | E49: 5590 | F49: =F48-D49+E49 -> 23690
A50: 45911 | B50: I1990 | C50: 1.5ltr+500ml | E50: 25448 | F50: =F49-D50+E50 -> 49138
A51: 45911 | B51: Exp Sheet | C51: easy paisa | D51: 17000 | F51: =F50-D51+E51 -> 32138
A52: 13/11/25 | B52: Exp Sheet | C52: bank transfer | D52: 20000 | F52: =F51-D52+E52 -> 12138
A53: 45819 | B53: Exp Sheet | C53: bank transfer | D53: 5590 | F53: =F52-D53+E53 -> 6548
A54: 15/11/25 | B54: Exp Sheet | C54: Cash Deposit | D54: 1500 | F54: =F53-D54+E54 -> 5048
A55: 15/11/25 | B55: Exp Sheet | C55: easy paisa | D55: 3500 | F55: =F54-D55+E55 -> 1548
A56: 15/11/25 | B56: j74 | C56: 1.5ltr+500ml | E56: 26108 | F56: =F55-D56+E56 -> 27656
A57: 16/11/25 | B57: Exp Sheet | C57: Cash Deposit | D57: 9000 | F57: =F56-D57+E57 -> 18656
A58: 17/11/25 | B58: Exp Sheet | C58: Cash Deposit | D58: 11100 | F58: =F57-D58+E58 -> 7556
A59: 17/11/25 | B59: j107 | C59: 1.5Ltr+500ml+6ltr | E59: 27288 | F59: =F58-D59+E59 -> 34844
A60: 22/11/25 | B60: Exp Sheet | C60: easy paisa | D60: 6000 | F60: =F59-D60+E60 -> 28844
A61: 22/11/25 | B61: Exp Sheet | C61: Cash Deposit | D61: 10070 | F61: =F60-D61+E61 -> 18774
A62: 22/11/25 | B62: j159 | C62: 500ml + caps…. | E62: 27238 | F62: =F61-D62+E62 -> 46012
A63: 22/11/25 | B63: j164 | C63: ozone generator | E63: 35000 | F63: =F62-D63+E63 -> 81012
A64: 22/11/25 | B64: Exp Sheet | C64: Cash Deposit | D64: 10000 | F64: =F63-D64+E64 -> 71012
A65: 23/11/25 | B65: j176 | C65: washing chemical,flunch jan | E65: 8500 | F65: =F64-D65+E65 -> 79512
A66: 26/11/25 | B66: Exp Sheet | C66: cash deposit | D66: 27000 | F66: =F65-D66+E66 -> 52512
A67: 26/11/25 | B67: j217 | C67: 1.5Ltr+500ml+6ltr | E67: 29748 | F67: =F66-D67+E67 -> 82260
A68: 45820 | B68: Exp Sheet | C68: Cash Deposit | D68: 29500 | F68: =F67-D68+E68 -> 52760
A69: 45820 | B69: j342 | C69: 1.5Ltr+500ml+6ltr | E69: 26834 | F69: =F68-D69+E69 -> 79594
A70: 16/12/25 | B70: Exp Sheet | C70: Cash Deposit | D70: 26900 | F70: =F69-D70+E70 -> 52694
A71: 16/12/25 | B71: j434 | C71: 1.5ltr+500ml | E71: 28355 | F71: =F70-D71+E71 -> 81049
A72: 25/12/25 | B72: Exp Sheet | C72: cash deposit +bank transfer | D72: 28050 | F72: =F71-D72+E72 -> 52999
A73: 21/12/25 | B73: j496 | C73: 1.5l shoper | E73: 120 | F73: =F72-D73+E73 -> 53119
A74: 25/12/25 | B74: j545 | C74: 1.5+caps....... | E74: 29516 | F74: =F73-D74+E74 -> 82635
A75: 46023 | B75: Exp Sheet | C75: cash deposit | D75: 29500 | F75: =F74-D75+E75 -> 53135
A76: 46023 | B76: j619 | C76: 1.5+caps....... | E76: 30364 | F76: =F75-D76+E76 -> 83499
A77: 13/1/26 | B77: j757 | C77: 1.5+caps....... | E77: 31766 | F77: =F76-D77+E77 -> 115265
A78: 13/1/26 | B78: Exp Sheet | C78: cash deposit | D78: 25000 | F78: =F77-D78+E78 -> 90265
A79: 13/1/26 | B79: Exp Sheet | C79: easy paisa | D79: 3500 | F79: =F78-D79+E79 -> 86765
A80: 13/1/26 | B80: Exp Sheet | C80: easy paisa | D80: 5000 | F80: =F79-D80+E80 -> 81765
A81: 20/1/26 | B81: Exp Sheet | C81: Cash Deposit | D81: 12000 | F81: =F80-D81+E81 -> 69765
A82: 20/1/26 | B82: Exp Sheet | C82: bank transfer | D82: 16800 | F82: =F81-D82+E82 -> 52965
A83: 20/1/26 | B83: j826 | C83: 1.5+caps....... | E83: 31176 | F83: =F82-D83+E83 -> 84141
A84: 46205 | C84: 6ltr label | D84: 3380 | F84: =F83-D84+E84 -> 80761
A85: 46205 | B85: Exp Sheet | C85: bank transfer | D85: 31000 | F85: =F84-D85+E85 -> 49761
A86: 46205 | B86: Exp Sheet | C86: Cash Deposit | D86: 1650 | F86: =F85-D86+E86 -> 48111
A87: 46205 | B87: Exp Sheet | C87: easy paisa | D87: 1350 | F87: =F86-D87+E87 -> 46761
A88: 46205 | B88: j1028 | C88: 1.5ltr+500ml | E88: 31846 | F88: =F87-D88+E88 -> 78607
A89: 16/2/26 | B89: j1148 | C89: 500ml+1.5l+shoper... | E89: 40825 | F89: =F88-D89+E89 -> 119432
A90: 16/2/26 | B90: Exp Sheet | C90: Cash Deposit | D90: 8300 | F90: =F89-D90+E90 -> 111132
A91: 16/2/26 | B91: Exp Sheet | C91: easy paisa | D91: 14600 | F91: =F90-D91+E91 -> 96532
A92: 18/2/26 | B92: j1182 | C92: 30mm caps+1.5l seal | E92: 3495 | F92: =F91-D92+E92 -> 100027
A93: 18/2/26 | B93: Exp Sheet | C93: easy paisa | D93: 10000 | F93: =F92-D93+E93 -> 90027
A94: 18/2/26 | B94: Exp Sheet | C94: 1.5l shoper | E94: 750 | F94: =F93-D94+E94 -> 90777
F95: =F94-D95+E95 -> 90777
F96: =F95-D96+E96 -> 90777
F97: =F96-D97+E97 -> 90777
F98: =F97-D98+E98 -> 90777
F99: =F98-D99+E99 -> 90777
F100: =F99-D100+E100 -> 90777
F101: =F100-D101+E101 -> 90777
...

Sheet Sheet1
A1: Miscelleneous Customer List
A4: Date | B4: Ref No. | C4: Customer Name | D4: Cr Amt | E4: Deposit | F4: R.Amt
A5: 13/9/22 | B5: 3739 | C5: Shahab Sb Model Town A | D5: 12205 | F5: =D5-E5 -> 12205
A6: 44996 | B6: D264 | C6: Bhatti Girls Hostel | D6: 600 | F6: =D6-E6 -> 600
A7: 18/06/23 | B7: 1213 | C7: Akhter Awan Sb | D7: 1300 | E7: 1300 | F7: =D7-E7 -> 0
A8: 18/05/23 | B8: 1376 | C8: M Usman (Tall) | D8: 2770 | E8: 700 | F8: =D8-E8 -> 2070
A9: 21/06/23 | B9: E37 | C9: Eng Naeem Sb BVH | D9: 1100 | E9: 1100 | F9: =D9-E9 -> 0
A10: 45385 | B10: F962 | C10: Eng Naeem Sb BVH | D10: 2500 | E10: 2500 | F10: =D10-E10 -> 0
A11: 18/07/23 | B11: E471 | C11: Ahmed Sb Sheri Chowk | D11: 1500 | F11: =D11-E11 -> 1500
A12: Ref: Sir Imran | C12: Nafy Water(Danial ) Pump Rep | D12: 6000 | F12: =D12-E12 -> 6000
A13: 28/08/23 | B13: E961 | C13: Zafar Khan Sb | D13: 13850 | E13: 12000 | F13: =D13-E13 -> 1850
A14: 45025 | B14: E1062 | C14: Masjid Sageer ul Yousaf | D14: 650 | F14: =D14-E14 -> 650
A15: 45239 | B15: E11760 | C15: Madrasa Dar ul Salam | D15: 2500 | F15: =D15-E15 -> 2500
A16: 24/09/23 | B16: E1343 | C16: Bilal Sb Liaquat Pur | D16: 3600 | F16: =D16-E16 -> 3600
A17: 31/10/23 | B17: F1781 | C17: Bilal Sb Liaquat Pur | D17: 12000 | F17: =D17-E17 -> 12000
A18: 44936 | B18: E1437 | C18: Bashrat Sb 1Unit | D18: 1500 | E18: 1500 | F18: =D18-E18 -> 0
A19: 45240 | B19: E1624 | C19: Bashrat Sb 1Unit | D19: 4500 | E19: 4500 | F19: =D19-E19 -> 0
A20: 44995 | B20: E1473 | C20: S.D High School | D20: 8500 | E20: 5000 | F20: =D20-E20 -> 3500
A21: 31/10/23 | B21: E1782 | C21: S.D High School | D21: 1500 | E21: 1500 | F21: =D21-E21 -> 0
A22: 13/12/23 | B22: F169 | C22: S.D High School | D22: 1500 | F22: =D22-E22 -> 1500
A23: 24/04/24 | B23: F1502 | C23: S.D High School | D23: 1000 | E23: 1000 | F23: =D23-E23 -> 0
A24: 18/04/24 | B24: F1426 | C24: S.D High School | D24: 3000 | F24: =D24-E24 -> 3000
A25: 45170 | B25: E1588 | C25: S.E Clg | D25: 2500 | E25: 2500 | F25: =D25-E25 -> 0
A26: 45446 | B26: F975 | C26: S.E Clg | D26: 3000 | E26: 3000 | F26: =D26-E26 -> 0
A27: 45476 | B27: F990 | C27: S.E Clg | D27: 13000 | E27: 13000 | F27: =D27-E27 -> 0
A28: 45179 | B28: E1586 | C28: Shahid Sb (Excise Home) | D28: 2050 | F28: =D28-E28 -> 2050
A29: 21/03/24 | B29: F1134 | C29: Shahid Sb (Excise Home) | D29: 2700 | F29: =D29-E29 -> 2700
A30: 20/04/24 | B30: F1444 | C30: Shahid Sb (Excise Office | D30: 3300 | E30: 3300 | F30: =D30-E30 -> 0
A31: 29/04/24 | B31: F1563 | C31: Excice office | D31: 15000 | E31: 10000 | F31: =D31-E31 -> 5000
A32: 16/10/23 | B32: E1666 | C32: Ch Masood Sb | D32: 3300 | F32: =D32-E32 -> 3300
A33: 45058 | B33: F100 | C33: Ahmed Sb DTL | D33: 1500 | F33: =D33-E33 -> 1500
A34: 45028 | B34: F84 | C34: Master Abdul Shakoor Sb | D34: 7500 | E34: 7500 | F34: =D34-E34 -> 0
A35: 24/12/23 | B35: F281 | C35: Yaseen Bhai Tailor | D35: 1300 | F35: =D35-E35 -> 1300
A36: 30/12/23 | B36: F346 | C36: Thanda Pani (Asif Sb) | D36: 2000 | E36: 2000 | F36: =D36-E36 -> 0
A37: 15/02/24 | B37: F761 | C37: Thanda Pani (Irfan) | D37: 8250 | E37: 11000 | F37: =D37-E37 -> -2750
A38: 14/04/24 | B38: F1361 | C38: Thanda Pani (Asif Sb) | F38: =D38-E38 -> 0
A39: 25/05/24 | B39: F1892 | C39: Thanda Pani (Asif Sb) | D39: 10000 | F39: =D39-E39 -> 10000
A40: 45566 | B40: F443 | C40: Safa Water (G.M) | D40: 8400 | E40: 8400 | F40: =D40-E40 -> 0
A41: 17/01/24 | B41: F500 | C41: Safa Water (G.M) | D41: 120 | E41: 120 | F41: =D41-E41 -> 0
A42: 22/01/24 | B42: F538 | C42: Taj Aqua | D42: 7500 | F42: =D42-E42 -> 7500
A43: 28/01/24 | B43: F578 | C43: Taj Aqua | D43: 1500 | F43: =D43-E43 -> 1500
A44: 23/01/24 | B44: F540 | C44: Haji Akbar | D44: 750 | F44: =D44-E44 -> 750
A45: 24/01/24 | B45: F548 | C45: PCRWR | D45: 1615 | E45: 1600 | F45: =D45-E45 -> 15
A46: 25/01/24 | B46: F552 | C46: DTL BWP | D46: 7000 | F46: =D46-E46 -> 7000
A47: 28/01/24 | B47: F576 | C47: Sheikh Uncle | D47: 6500 | E47: 5000 | F47: =D47-E47 -> 1500
A48: 45353 | B48: F625 | C48: M.D Foods (Sajid Sb) | D48: 14400 | F48: =D48-E48 -> 14400
A49: 26/07/23 | B49: E569 | C49: Saleem Chishti Sb | D49: 4800 | E49: 4800 | F49: =D49-E49 -> 0
A50: 44993 | B50: E663 | C50: Saleem Chishti Sb | D50: 7000 | E50: 7000 | F50: =D50-E50 -> 0
A51: 19/09/23 | B51: E1293 | C51: Saleem Chishti Sb | D51: 8200 | E51: 8200 | F51: =D51-E51 -> 0
A52: 14/11/23 | B52: E1832 | C52: Saleem Chishti Sb | D52: 400 | E52: 400 | F52: =D52-E52 -> 0
A53: 28/06/22 | B53: 2595 | C53: Kashif Askari Bank | D53: 1625 | F53: =D53-E53 -> 1625
A54: 29/05/23 | B54: 1519 | C54: Kashif Askari Bank | D54: 1700 | F54: =D54-E54 -> 1700
A55: 18/06/23 | B55: 1920 | C55: Kashif Askari Bank | D55: 5000 | F55: =D55-E55 -> 5000
A56: 44936 | B56: E1435 | C56: Kashif Askari Bank | D56: 3600 | F56: =D56-E56 -> 3600
A57: 17/02/24 | B57: F777 | C57: Esencia Water(Asad Sb) | D57: 1500 | E57: 1500 | F57: =D57-E57 -> 0
A58: 19/02/24 | B58: F798 | C58: Master Mukhtar Sb | D58: 7200 | E58: 3000 | F58: =D58-E58 -> 4200
A59: 20/02/24 | B59: F811 | C59: Esencia Water(Asad Sb) | D59: 320 | E59: 320 | F59: =D59-E59 -> 0
A60: 24/02/24 | B60: F856 | C60: Esencia Water(Asad Sb) | D60: 3520 | E60: 3520 | F60: =D60-E60 -> 0
A61: 18/05/24 | B61: F1790 | C61: Esencia Water | D61: 110 | E61: 110 | F61: =D61-E61 -> 0
A62: 45325 | B62: F929 | C62: Star Light | D62: 27520 | E62: 27520 | F62: =D62-E62 -> 0
A63: 45476 | B63: F994 | C63: Star Light | D63: 2100 | E63: 2100 | F63: =D63-E63 -> 0
A64: 26/3/2024 | B64: F1172 | C64: Star Light | D64: 1800 | E64: 1800 | F64: =D64-E64 -> 0
A65: 45541 | B65: G91 | C65: Star Light | D65: 3150 | E65: 3150 | F65: =D65-E65 -> 0
A66: 14/03/24 | B66: F1072 | C66: Wasif Ali/Danish Cofee | D66: 910 | E66: 910 | F66: =D66-E66 -> 0
A67: 13/03/24 | B67: F1049 | C67: Munawar Dewan Sb | D67: 1500 | E67: 1500 | F67: =D67-E67 -> 0
A68: 45448 | B68: F1649 | C68: Munawar Dewan Sb | D68: 1500 | E68: 1500 | F68: =D68-E68 -> 0
A69: 17/03/24 | B69: F1087 | C69: Mubarik Pur (Akram Sb) | D69: 1500 | F69: =D69-E69 -> 1500
A70: 19/03/24 | B70: F1107 | C70: Mahar Ijaz Sb | D70: 1100 | E70: 1100 | F70: =D70-E70 -> 0
A71: 26/02/24 | B71: F875 | C71: Ishfaq Ahmed sb A.P | D71: 40000 | F71: =D71-E71 -> 40000
A72: 45354 | B72: F945 | C72: Jeo Water | D72: 12880 | F72: =D72-E72 -> 12880
A73: 45385 | B73: F956 | C73: Al Khidmat (Asif Sb) | D73: 550 | E73: 550 | F73: =D73-E73 -> 0
A74: 45415 | B74: F973 | C74: Prof. Nasir Sb | D74: 1000 | E74: 1000 | F74: =D74-E74 -> 0
A75: 45476 | B75: F991 | C75: Respected Sir Haji Hassan | D75: 425000 | F75: =D75-E75 -> 425000
A76: 27/03/24 | B76: F1184 | C76: Basit Ali Sb (Danish Bhai) | D76: 910 | E76: 900 | F76: =D76-E76 -> 10
A77: 27/03/24 | B77: F1183 | C77: Abad ul Rehman | D77: 10000 | E77: 10000 | F77: =D77-E77 -> 0
A78: 45447 | B78: F1294 | C78: Sadam Sb | D78: 4500 | E78: 4500 | F78: =D78-E78 -> 0
A79: 45508 | B79: F1312 | C79: MAhar Faraz Sb | D79: 13150 | F79: =D79-E79 -> 13150
A80: 17/04/24 | B80: F1416 | C80: Nector Water Fall | D80: 3040 | E80: 3040 | F80: =D80-E80 -> 0
A81: 23/04/24 | B81: F1479 | C81: Prof. Abdul Nabi Sb | D81: 5000 | E81: 5000 | F81: =D81-E81 -> 0
A82: 25/04/24 | B82: F1516 | C82: Fida Hussain Sb | D82: 850 | E82: 850 | F82: =D82-E82 -> 0
A83: 22/05/24 | B83: F1845 | C83: Fida Hussain Sb | D83: 750 | E83: 750 | F83: =D83-E83 -> 0
A84: 25/04/24 | B84: F1518 | C84: Uch Shareef | D84: 5400 | E84: 5400 | F84: =D84-E84 -> 0
A85: 25/04/24 | B85: F1519 | C85: Anees | D85: 535 | E85: 535 | F85: =D85-E85 -> 0
A86: 29/04/24 | B86: F1565 | C86: arshad Ajwah Water | D86: 12400 | F86: =D86-E86 -> 12400
A87: 30/04/24 | B87: F1577 | C87: Aqua Refine | D87: 7300 | E87: 7300 | F87: =D87-E87 -> 0
A88: 30/04/24 | B88: F1582 | C88: DTL BWP | D88: 11100 | E88: 11100 | F88: =D88-E88 -> 0
A89: 30/04/24 | B89: F1588 | C89: Aqua Refine | D89: 2750 | E89: 2750 | F89: =D89-E89 -> 0
A90: 45296 | B90: F1594 | C90: Nimra Masjid LD | D90: 2750 | F90: =D90-E90 -> 2750
A91: 45296 | B91: F1595 | C91: Aqua Refine | D91: 64100 | E91: 64100 | F91: =D91-E91 -> 0
A92: 45327 | B92: F1607 | C92: Dr Adeel Sb | D92: 5700 | E92: 5700 | F92: =D92-E92 -> 0
A93: 45417 | B93: F1648 | C93: Yousaf Norani Sb | D93: 1800 | E93: 1700 | F93: =D93-E93 -> 100
A94: 45478 | B94: F1674 | C94: 12 Bs High School | D94: 2000 | F94: =D94-E94 -> 2000
A95: 45540 | B95: F1707 | C95: Al Safina Watet | D95: 3050 | E95: 3050 | F95: =D95-E95 -> 0
A96: 20/05/24 | B96: F1829 | C96: Al Safina Watet | D96: 900 | F96: =D96-E96 -> 900
A97: 14/5/2024 | B97: F1768 | C97: abdul Haq Fresco | D97: 6050 | F97: =D97-E97 -> 6050
A98: 45387 | B98: F1612 | C98: Hafiz Sb | D98: 1500 | F98: =D98-E98 -> 1500
A99: 22/05/24 | B99: F1844 | C99: Asfand Sb | D99: 1500 | F99: =D99-E99 -> 1500
A100: 27/05/24 | B100: F1933 | C100: Mahad Rafiq | D100: 30000 | F100: =D100-E100 -> 30000
A101: 45297 | B101: G5 | C101: Hamad Sb | D101: 1200 | F101: =D101-E101 -> 1200
A102: 30/05/24 | B102: F1983 | C102: Imran Lasani Water | D102: 950 | E102: 950 | F102: =D102-E102 -> 0
...

Sheet Saboor sb Opal Water
A1: LEDGER
A3: Account Holder's Name | D3: Saboor sb Opal Water
A4: Pg # | C4: New Reg(180) | BC4: 550
A5: Date | B5: Ref No. | C5: Description | D5: Debit | E5: Credit | F5: Balance
A6: 18/5/24 | B6: F1794 | C6: 19L Caps | E6: 600 | F6: =E6 -> 600
A7: 25/5/24 | B7: F1890 | C7: 19L Caps | E7: 1150 | F7: =E7+F6 -> 1750
A8: 25/5/24 | B8: F1845 | C8: 1.5L Bottle,… | E8: 6075 | F8: =E8+F7 -> 7825
A9: 28/5/24 | B9: F1937 | C9: 1.5L Shoper,.. | E9: 550 | F9: =E9+F8 -> 8375
A10: 29/5/24 | B10: F1969 | C10: 1.5L Shoper,.. | E10: 2380 | F10: =E10+F9 -> 10755
A11: 29/5/24 | C11: IBFT | D11: 6600 | F11: =E11+F10-D11 -> 4155
A12: 45297 | B12: F1988 | C12: 500ml Bottles,.. | E12: 16440 | F12: =E12+F11-D12 -> 20595
A13: 45297 | C13: Cash deposit | D13: 6500 | F13: =E13+F12-D13 -> 14095
A14: 45357 | C14: Cash deposit | D14: 5050 | F14: =E14+F13-D14 -> 9045
A15: 45388 | B15: G743 | C15: 500ml Bottles,.. | E15: 1100 | F15: =E15+F14-D15 -> 10145
A16: 45388 | B16: G744 | C16: 30mm Seal | E16: 500 | F16: =E16+F15-D16 -> 10645
A17: 45418 | B17: Exp Sh | C17: Cash deposit | D17: 5500 | F17: =E17+F16-D17 -> 5145
A18: 45510 | B18: G81 | C18: 30mm Caps | E18: 700 | F18: =E18+F17-D18 -> 5845
A19: 45571 | B19: Exp Sh | C19: Cash deposit | D19: 5000 | F19: =E19+F18-D19 -> 845
A20: 45602 | B20: G118 | C20: 500ml Bottles,.. | E20: 29420 | F20: =E20+F19-D20 -> 30265
A21: 45632 | B21: Exp Sh | C21: cash deposit | D21: 5000 | F21: =E21+F20-D21 -> 25265
A22: 16/6/24 | B22: Exp Sh | C22: Cash deposit | D22: 5000 | F22: =E22+F21-D22 -> 20265
A23: 22/6/24 | B23: G211 | C23: Saboor sab (Opel Water) | E23: 6112 | F23: =E23+F22-D23 -> 26377
A24: 23/6/24 | B24: Exp Sh | C24: Cash Deposit | D24: 1700 | F24: =E24+F23-D24 -> 24677
A25: 25/6/24 | B25: G240 | C25: Saboor sab (Opel Water) | E25: 44337 | F25: =E25+F24-D25 -> 69014
A26: 26/6/24 | C26: Cash Deposit | D26: 20000 | F26: =E26+F25-D26 -> 49014
A27: 26/6/24 | B27: Exp Sh | C27: Cash Deposit | D27: 8240 | F27: =E27+F26-D27 -> 40774
A28: 27/6/24 | B28: G259 | C28: Saboor sab (Opel Water) | E28: 1000 | F28: =E28+F27-D28 -> 41774
A29: 27/6/24 | B29: G261 | C29: Saboor sab (Opel Water) | E29: 5300 | F29: =E29+F28-D29 -> 47074
C30: Cash Deposit | D30: 5000 | F30: =E30+F29-D30 -> 42074
A31: 28/6/24 | B31: Exp Sh | C31: Cash Deposit | D31: 14000 | F31: =E31+F30-D31 -> 28074
A32: 29/6/24 | B32: G274 | C32: Saboor sab (Opel Water) | E32: 2160 | F32: =E32+F31-D32 -> 30234
A33: 7/724 | B33: G367 | C33: Opel Water (Saboor sab) | E33: 10847 | F33: =E33+F32-D33 -> 41081
A34: 45480 | C34: Cash Deposit | D34: 6300 | F34: =E34+F33-D34 -> 34781
A35: 45511 | E35: 5040 | F35: =E35+F34-D35 -> 39821
A36: 45542 | E36: 500 | F36: =E36+F35-D36 -> 40321
A37: 45603 | C37: IBFT | D37: 500 | F37: =E37+F36-D37 -> 39821
A38: 45299 | C38: IBFT | D38: 3000 | F38: =E38+F37-D38 -> 36821
A39: 45299 | C39: IBFT | D39: 720 | F39: =E39+F38-D39 -> 36101
A40: 45637 | B40: Exp Sh | C40: Cash Deposit | D40: 5000 | F40: =E40+F39-D40 -> 31101
A41: 21/11/24 | B41: Exp Sh | C41: Cash Deposit | D41: 3000 | F41: =E41+F40-D41 -> 28101
A42: 20/11/24 | B42: G1578 | C42: 1.5L - Caps, 500ml - Caps | E42: 4969 | F42: =E42+F41-D42 -> 33070
A43: 23/11/24 | B43: Exp Sh | C43: Cash Deposit | D43: 1969 | F43: =E43+F42-D43 -> 31101
A44: 25/11/24 | B44: G1624 | C44: 1.5L - Caps, 30mm Caps | E44: 8250 | F44: =E44+F43-D44 -> 39351
A45: 26/11/24 | B45: G1635 | C45: 500ml -Caps | E45: 6162 | F45: =E45+F44-D45 -> 45513
A46: 26/11/24 | B46: Exp Sh | C46: Cash Deposit | D46: 3000 | F46: =E46+F45-D46 -> 42513
A47: 28/11/24 | B47: G1642 | C47: 500ml -Caps, 6L + Caps | E47: 1952 | F47: =E47+F46-D47 -> 44465
A48: 30/11/24 | B48: G1664 | C48: Remaining Amount | E48: 2542 | F48: =E48+F47-D48 -> 47007
A49: 30/11/24 | B49: Exp Sh | C49: Cash Deposit | D49: 1950 | F49: =E49+F48-D49 -> 45057
A50: 30/11/24 | B50: Exp Sh | C50: Cash Deposit | D50: 6160 | F50: =E50+F49-D50 -> 38897
A51: 45334 | B51: Exp Sh | C51: Cash Deposit | D51: 7783 | F51: =E51+F50-D51 -> 31114
A52: 45394 | B52: G1698 | C52: Remaining Amount | E52: 4839 | F52: =E52+F51-D52 -> 35953
A53: 45424 | B53: Exp Sh | C53: Cash Deposit | D53: 4840 | F53: =E53+F52-D53 -> 31113
A54: 45485 | B54: G1722 | C54: 1.5L - Caps, 500ml - Caps | E54: 7055 | F54: =E54+F53-D54 -> 38168
A55: 45547 | B55: G1741 | C55: 6L + Caps, 500ml - Caps, 1.5L - Caps | E55: 4181 | F55: =E55+F54-D55 -> 42349
A56: 45547 | B56: Exp Sh | C56: Cash Deposit | D56: 7055 | F56: =E56+F55-D56 -> 35294
A57: 45577 | B57: Exp Sh | C57: Cash Deposit | D57: 4180 | F57: =E57+F56-D57 -> 31114
A58: 45608 | B58: G1752 | C58: 6L + Caps, 30mm Caps | E58: 3660 | F58: =E58+F57-D58 -> 34774
A59: 45638 | B59: Exp Sh | C59: Cash Deposit | D59: 3300 | F59: =E59+F58-D59 -> 31474
A60: 14/12/24 | B60: G1773 | C60: 1.5-L Caps, 500ml- Caps | E60: 3920 | F60: =E60+F59-D60 -> 35394
A61: 14/12/24 | B61: G1774 | C61: 5L + Caps | E61: 1512 | F61: =E61+F60-D61 -> 36906
A62: 16/12/24 | B62: G1787 | C62: 1.5L- Caps,500ml - Caps,5L + Caps | E62: 4796 | F62: =E62+F61-D62 -> 41702
A63: 16/12/24 | B63: Exp Sh | C63: Cash Deposit | D63: 5430 | F63: =E63+F62-D63 -> 36272
A64: 17/12/24 | B64: Exp Sh | C64: Cash Deposit | D64: 4800 | F64: =E64+F63-D64 -> 31472
A65: 45483 | C65: IBFT | D65: 5000 | F65: =E65+F64-D65 -> 26472
A66: 19/12/24 | B66: G1829 | C66: 1.5L, 500ml, 6L E+C | E66: 5412 | F66: =E66+F65-D66 -> 31884
A67: 21/12/24 | B67: G1837 | C67: Remaining Amount | E67: 315 | F67: =E67+F66-D67 -> 32199
A68: 22/12/24 | B68: Exp Sh | C68: Cash Deposit | D68: 5720 | F68: =E68+F67-D68 -> 26479
A69: 22/12/24 | B69: G1850 | C69: 1.5L- Caps,500ml - Caps,6L + Caps | E69: 4179 | F69: =E69+F68-D69 -> 30658
A70: 23/12/24 | B70: G1866 | C70: 1.5L-Caps,500ml -Caps | E70: 2807 | F70: =E70+F69-D70 -> 33465
A71: 23/12/24 | B71: Exp Sh | C71: Cash Deposit (Bill no 1850+274) | D71: 6339 | F71: =E71+F70-D71 -> 27126
A72: 25/12/24 | B72: G1885 | C72: Remaining Amount | E72: 4550 | F72: =E72+F71-D72 -> 31676
A73: 26/12/24 | B73: G1888 | C73: Saboor sab (Opel Water) | E73: 1000 | F73: =E73+F72-D73 -> 32676
A74: 26/12/24 | B74: Exp Sh | C74: Cash deposit | D74: 1000 | F74: =E74+F73-D74 -> 31676
A75: 45658 | B75: H12 | C75: Remaining Amount | E75: 1247 | F75: =E75+F74-D75 -> 32923
A76: 45689 | B76: Exp Sh | C76: Cash deposit | D76: 1247 | F76: =E76+F75-D76 -> 31676
A77: 18/12/24 | B77: G1813 | C77: 0.5L, Caps | E77: 7662 | F77: =E77+F76-D77 -> 39338
A78: 45778 | B78: H38 | C78: 6L+Caps, 1.5L-Caps,500ml-Caps | E78: 4179 | F78: =E78+F77-D78 -> 43517
A79: 45809 | B79: Exp Sh | C79: Cash deposit | D79: 4179 | F79: =E79+F78-D79 -> 39338
A80: 45809 | B80: H50 | C80: 1.5L- Caps,500ml-Caps, 30mm Caps | E80: 3019 | F80: =E80+F79-D80 -> 42357
A81: 45839 | B81: H57 | C81: 1.5L-Caps,6L+ Caps | E81: 3802 | F81: =E81+F80-D81 -> 46159
A82: 45992 | B82: H207 | C82: 500ml-Caps,6L+ Caps | E82: 1952 | F82: =E82+F81-D82 -> 48111
A83: 45992 | B83: Exp Sh | C83: IBFT | D83: 5750 | F83: =E83+F82-D83 -> 42361
A84: 14/1/25 | B84: H232 | C84: 1.5L - Caps, 500ml - Caps | E84: 3252 | F84: =E84+F83-D84 -> 45613
A85: 15/1/25 | B85: H244 | C85: Remaining Amount | E85: 2839 | F85: =E85+F84-D85 -> 48452
A86: 15/1/25 | B86: Exp Sh | C86: Cash deposit | D86: 3252 | F86: =E86+F85-D86 -> 45200
A87: 18/1/25 | B87: Exp Sh | C87: Cash Deposit | D87: 2830 | F87: =E87+F86-D87 -> 42370
A88: 22/1/25 | B88: H300 | C88: 1.5L- Caps, 500ml - Caps | E88: 4040 | F88: =E88+F87-D88 -> 46410
A89: 23/1/25 | B89: Exp Sh | C89: Cash Deposit | D89: 4040 | F89: =E89+F88-D89 -> 42370
A90: 20/6/24 | B90: G199 | C90: Cash Deposit | D90: 10563 | F90: =E90+F89-D90 -> 31807
A91: 26/1/25 | B91: Exp Sh | C91: cash deposit | D91: 5826 | F91: =E91+F90-D91 -> 25981
A92: 25/1/25 | B92: H329 | C92: 500ml-Caps, 1.5L- Caps | E92: 4827 | F92: =E92+F91-D92 -> 30808
A93: 26/1/25 | B93: H340 | C93: 1.5L- Caps, 500ml - Caps | E93: 5272 | F93: =E93+F92-D93 -> 36080
A94: 27/1/25 | B94: Exp Sh | C94: Cash deposit | D94: 10100 | F94: =E94+F93-D94 -> 25980
A95: 28/1/25 | B95: H356 | C95: 30mm Caps, 1.5L- Caps, 500ml - Caps | E95: 7427 | F95: =E95+F94-D95 -> 33407
A96: 45659 | B96: Exp Sh | C96: Cash deposited against Bill No 1885 | D96: 4050 | F96: =E96+F95-D96 -> 29357
A97: 45659 | B97: H396 | C97: 500ml- Caps, 1.5L- Caps, 30mm Caps | E97: 8559 | F97: =E97+F96-D97 -> 37916
A98: 45718 | B98: H414 | C98: 1.5L-Caps, 500ml - Caps, 6L + Caps | E98: 6542 | F98: =E98+F97-D98 -> 44458
A99: 45718 | C99: Cash deposit | D99: 8559 | F99: =E99+F98-D99 -> 35899
A100: 45718 | C100: Cash deposit | D100: 6542 | F100: =E100+F99-D100 -> 29357
A101: 45659 | B101: Exp Sh | C101: Cash deposit | D101: 7427 | F101: =E101+F100-D101 -> 21930
...

Sheet Star Light
A1: LEDGER
A3: Account Holder's Name | D3: Star Light
A4: Pg #
A5: Date | B5: Ref No. | C5: Description | D5: Debit | E5: Credit | F5: Balance
A6: 45576 | B6: I 743 | C6: 30mm Caps, 19L Caps | E6: 4550 | F6: =E6-D6 -> 4550
A7: 45607 | B7: G1486 | C7: 30mm Caps | E7: 1800 | F7: =F6-D7+E7 -> 6350
A8: 24/11/24 | B8: G1609 | C8: Stand+ Guage | E8: 1800 | F8: =F7-D8+E8 -> 8150
A9: 27/11/24 | B9: G1637 | C9: 30mm Caps | E9: 1800 | F9: =F8-D9+E9 -> 9950
A10: 45363 | B10: G1684 | C10: 30mm Caps | E10: 1800 | F10: =F9-D10+E10 -> 11750
A11: 18/12/24 | B11: G1814 | C11: 19L Caps, Antiscalar, Jumbo PPF | E11: 4150 | F11: =F10-D11+E11 -> 15900
A12: 23/12/24 | B12: G1855 | C12: 1.5L Shoper | E12: 4400 | F12: =F11-D12+E12 -> 20300
A13: 25/12/24 | B13: G1879 | C13: 30mm Caps | E13: 1800 | F13: 700
A14: 45839 | B14: H62 | C14: 1.5L Shoper | E14: 5500 | F14: =F13-D14+E14 -> 6200
A15: 45962 | B15: H96 | C15: 30mm Caps, Antiscalar | E15: 2350 | F15: =F14-D15+E15 -> 8550
A16: 14/1/25 | B16: H219 | C16: 19L Caps, 19L Lids | E16: 3500 | F16: =F15-D16+E16 -> 12050
A17: 20/1/25 | B17: H282 | C17: 6L + Caps | E17: 4100 | F17: =F16-D17+E17 -> 16150
A18: 28/1/25 | B18: H353 | C18: 1.5L Shoper | E18: 5500 | F18: =F17-D18+E18 -> 21650
A19: 45871 | B19: H459 | C19: Jumbo PPF, 1.5L Shoper,.. | E19: 6800 | F19: =F18-D19+E19 -> 28450
A20: 45933 | B20: H764 | C20: 19L caps | E20: 10200 | F20: =F19-D20+E20 -> 38650
A21: 45933 | C21: 19L Bottles Printed 200 | E21: 250000 | F21: =F20-D21+E21 -> 288650
A22: 13/3/25 | C22: Cash deposit in hand | D22: 200000 | F22: =F21-D22+E22 -> 88650
A23: 22/3/25 | B23: H884 | C23: 30mm Caps | E23: 5500 | F23: =F22-D23+E23 -> 94150
A24: 19/3/25 | C24: IBFT | D24: 60000 | F24: =F23-D24+E24 -> 34150
A25: 16/4/25 | C25: IBFT | D25: 15000 | F25: =F24-D25+E25 -> 19150
A26: 20/4/25 | B26: H1274 | C26: 1.5L Shoper, Antiscalar | E26: 3300 | F26: =F25-D26+E26 -> 22450
A27: 45752 | B27: H1474 | C27: 1.5L Shoper | E27: 5500 | F27: =F26-D27+E27 -> 27950
A28: 45448 | B28: H1505 | C28: 19L Caps, 30mm Caps, 1.5L Shoper,…. | E28: 11200 | F28: =F27-D28+E28 -> 39150
A29: 45833 | C29: IBFT | D29: 20000 | F29: =F28-D29+E29 -> 19150
A30: 45874 | B30: H1553 | C30: 1.5L Shoper,500ml Shoper | E30: 6740 | F30: =F29-D30+E30 -> 25890
A31: 45935 | B31: H1566 | C31: 1.5L Shoper | E31: 5300 | F31: =F30-D31+E31 -> 31190
A32: 45966 | B32: H1590 | C32: Jumbo PPF, 1.5L Shoper,.. | E32: 3550 | F32: =F31-D32+E32 -> 34740
A33: 13/5/25 | B33: H1626 | C33: 1.5L Shoper Pure | E33: 13200 | F33: =F32-D33+E33 -> 47940
A34: 22/5/25 | C34: 1.5L Filled pet @250 | D34: 25000 | F34: =F33-D34+E34 -> 22940
A35: 24/5/25 | B35: H1762 | C35: 1.5LShoper, 30mm Seal | E35: 14675 | F35: =F34-D35+E35 -> 37615
A36: 26/5/25 | B36: H1801 | C36: 500ml Shoper | E36: 2575 | F36: =F35-D36+E36 -> 40190
A37: 27/5/25 | B37: H1810 | C37: Burner | E37: 1500 | F37: =F36-D37+E37 -> 41690
A38: 28/5/25 | C38: IBFT | D38: 30000 | F38: =F37-D38+E38 -> 11690
A39: 29/5/25 | B39: H1857 | C39: 1.5L Shoper Pure, 500ml Shoper pure | E39: 55000 | F39: =F38-D39+E39 -> 66690
A40: 30/5/25 | C40: IBFT | D40: 30000 | F40: =F39-D40+E40 -> 36690
A41: 31/5/25 | B41: H1877 | C41: 1.5L Pure, 500 Pure | E41: 158900 | F41: =F40-D41+E41 -> 195590
A42: 29/5/25 | C42: IBFT | D42: 130000 | F42: =F41-D42+E42 -> 65590
A43: 45694 | B43: H1902 | C43: 19L Caps, 19L Lids | E43: 6850 | F43: =F42-D43+E43 -> 72440
A44: 45935 | B44: H1986 | C44: Antiscalar | E44: 550 | F44: =F43-D44+E44 -> 72990
A45: 45997 | C45: IBFT | D45: 100000 | F45: =F44-D45+E45 -> -27010
A46: 13/6/25 | C46: IBFT | D46: 100000 | F46: =F45-D46+E46 -> -127010
A47: 14/6/25 | B47: H133 | C47: 30mm Caps | E47: 5200 | F47: =F46-D47+E47 -> -121810
A48: 17/6/25 | B48: H184 | C48: 30mm Caps | E48: 2250 | F48: =F47-D48+E48 -> -119560
A49: 18/6/26 | B49: I 4 | C49: 1.5L Bottle | E49: 176000 | F49: =F48-D49+E49 -> 56440
A50: 18/6/25 | B50: I16 | C50: 30mm caps, 30mmcaps white | E50: 10000 | F50: =F49-D50+E50 -> 66440
A51: 21/6/25 | B51: I 50 | C51: 1.5L Caps Pure, 30mm caps pure | E51: 20800 | F51: =F50-D51+E51 -> 87240
A52: 24/6/25 | B52: Exp Sheet | C52: IBFT | D52: 30000 | F52: =F51-D52+E52 -> 57240
A53: 26/6/25 | B53: I 125 | C53: Remaining Amount | E53: 10170 | F53: =F52-D53+E53 -> 67410
A54: 29/6/25 | B54: I 141 | C54: Antiscalar | E54: 550 | F54: =F53-D54+E54 -> 67960
A55: 30/6/25 | B55: I 162 | C55: Quad, Rod, UV Pannel double, Jumbo PPF | E55: 31100 | F55: =F54-D55+E55 -> 99060
A56: 30/6/25 | B56: I 161 | C56: Fittings | E56: 3963 | F56: =F55-D56+E56 -> 103023
A57: 30/6/25 | C57: Fitting return | D57: 4850 | F57: =F56-D57+E57 -> 98173
A58: 45664 | B58: I 187 | C58: 10mm value | E58: 1200 | F58: =F57-D58+E58 -> 99373
A59: 45845 | B59: I 252 | C59: 1.5L Shoper | E59: 5200 | F59: =F58-D59+E59 -> 104573
A60: 45907 | C60: Cash deposit in hand | D60: 75000 | F60: =F59-D60+E60 -> 29573
A61: 45907 | B61: I 294 | C61: 1.5L Shoper | E61: 13000 | F61: =F60-D61+E61 -> 42573
A62: 17/7/25 | B62: I 385 | C62: Antiscalar | E62: 550 | F62: =F61-D62+E62 -> 43123
A63: 19/7/25 | B63: I 409 | C63: 19L Caps | E63: 5500 | F63: =F62-D63+E63 -> 48623
A64: 21/7/25 | B64: I 435 | C64: Jumbo PPF Gold | E64: 2400 | F64: =F63-D64+E64 -> 51023
A65: 22/7/25 | B65: I 461 | C65: 1.5L Shoper | E65: 13750 | F65: =F64-D65+E65 -> 64773
A66: 22/7/25 | B66: I 453 | C66: 1.5L -Caps, 500ml - Caps | E66: 234250 | F66: =F65-D66+E66 -> 299023
A67: 15/7/25 | C67: IBFT to Plas Pak | D67: 250000 | F67: =F66-D67+E67 -> 49023
A68: 30/7/25 | B68: I 548 | C68: 1.5L Shoper | E68: 13000 | F68: =F67-D68+E68 -> 62023
A69: 30/7/25 | B69: Exp Sheet | C69: IBFT | D69: 40000 | F69: =F68-D69+E69 -> 22023
A70: 45696 | B70: 579 | C70: Ball valu"P.socket….. | E70: 2479 | F70: =F69-D70+E70 -> 24502
A71: 45755 | B71: I 602 | C71: Antiscalar | E71: 550 | F71: =F70-D71+E71 -> 25052
A72: 45846 | B72: I 653 | C72: 1.5L Shoper | E72: 2080 | F72: =F71-D72+E72 -> 27132
A73: 13/8/2025 | B73: I 731 | C73: 1.5L shoper | E73: 13000 | F73: =F72-D73+E73 -> 40132
A74: 17/8/2025 | B74: I 784 | C74: 19L Lids | E74: 750 | F74: =F73-D74+E74 -> 40882
A75: 17/8/2025 | B75: I 795 | C75: 1.5L caps pure.. | E75: 17650 | F75: =F74-D75+E75 -> 58532
A76: 20/8/2025 | B76: I 814 | C76: 30mm Caps | E76: 150 | F76: =F75-D76+E76 -> 58682
A77: 21/8/2025 | B77: I 821 | C77: Antiscalar | E77: 1750 | F77: =F76-D77+E77 -> 60432
A78: 28/8/2025 | B78: I 921 | C78: 500ml Bottles we Received | D78: 7920 | F78: =F77-D78+E78 -> 52512
A79: 31/8/2025 | B79: I 941 | C79: 19L Lids….. | E79: 8450 | F79: =F78-D79+E79 -> 60962
A80: 45666 | B80: I 965 | C80: 1.5L Shoper Mix | E80: 2600 | F80: =F79-D80+E80 -> 63562
A81: 45697 | B81: I 969 | C81: 500ml Shoper | E81: 13250 | F81: =F80-D81+E81 -> 76812
A82: 45725 | B82: I 992 | C82: 1.5L Shoper Pure | E82: 13250 | F82: =F81-D82+E82 -> 90062
A83: 45725 | B83: I1031 | C83: 1.5L Shoper | E83: 5250 | F83: =F82-D83+E83 -> 95312
A84: 45847 | B84: I 1072 | C84: 1.5L Pure ,, 500 ml Pure | E84: 275000 | F84: =F83-D84+E84 -> 370312
A85: 22/8/2025 | C85: IBFT | D85: 300000 | F85: =F84-D85+E85 -> 70312
A86: 45786 | C86: Truk Fare | D86: 10000 | F86: =F85-D86+E86 -> 60312
A87: 16/9/2025 | B87: I 1256 | C87: 1.5L shoper | E87: 5200 | F87: =F86-D87+E87 -> 65512
A88: 18/9/2025 | B88: I 1290 | C88: 30mm seal | E88: 1700 | F88: =F87-D88+E88 -> 67212
A89: 21/9/2025 | C89: Cash deposit in hand | D89: 20000 | F89: =F88-D89+E89 -> 47212
C90: Bottles Discount | D90: 23000 | F90: =F89-D90+E90 -> 24212
A91: 29/9/2025 | B91: I 1435 | C91: 500ml - caps Pure (we recived) | D91: 63360 | F91: =F90-D91+E91 -> -39148
A92: 45818 | B92: I 1533 | C92: 500ml Shoper | E92: 13000 | F92: =F91-D92+E92 -> -26148
A93: 45848 | B93: I 1547 | C93: 30mm caps | E93: 625 | F93: =F92-D93+E93 -> -25523
A94: 45971 | B94: I 1598 | C94: 500ml Shoper | E94: 12050 | F94: =F93-D94+E94 -> -13473
A95: 46001 | B95: I 1608 | C95: 1.5L sfoper…. | E95: 31200 | F95: =F94-D95+E95 -> 17727
A96: 21/10/25 | B96: I 1729 | C96: 1.5L shoper | E96: 7800 | F96: =F95-D96+E96 -> 25527
A97: 25/10/25 | B97: I 1766 | C97: 500ml - caps | E97: 12750 | F97: =F96-D97+E97 -> 38277
A98: 28/10/25 | B98: I 1820 | C98: 30mm seal | E98: 1800 | F98: =F97-D98+E98 -> 40077
A99: 28/10/25 | B99: I 1821 | C99: 1.5L shoper | E99: 9950 | F99: =F98-D99+E99 -> 50027
A100: 30/10/25 | B100: I 1847 | C100: 1.5L Shoper…. | E100: 9550 | F100: =F99-D100+E100 -> 59577
A101: 45699 | B101: I 1904 | C101: F.Socket 1/2…. | E101: 1090 | F101: =F100-D101+E101 -> 60667
...

Sheet New SalSabeel BWP
A1: LEDGER
A3: Account Holder's Name | D3: New Salsabeel BWP
A4: Pg # | C4: New Reg(200)
A5: Date | B5: Ref No. | C5: Description | D5: Debit | E5: Credit | F5: Balance
A6: 45872 | B6: H745 | C6: Remaining Amount | E6: 17350 | F6: =E6-D6 -> 17350
A7: 45903 | B7: Exp Sh | C7: Cash deposit | D7: 19300 | F7: =E7-D7+F6 -> -1950
A8: 45903 | B8: H755 | C8: 500ml Seal, 500ml Seal | E8: 2000 | F8: =E8-D8+F7 -> 50
A9: 9//3/25 | B9: H760 | C9: Remaining Amount | E9: 55000 | F9: =E9-D9+F8 -> 55050
A10: 45994 | B10: H787 | C10: 19L Bush | E10: 1200 | F10: =E10-D10+F9 -> 56250
A11: 13/3/25 | B11: H797 | C11: Membrane 100G, Flow Valve, CTO,…. | E11: 6550 | F11: =E11-D11+F10 -> 62800
A12: 18/3/25 | B12: H857 | C12: 500ml+ Caps | E12: 1530 | F12: =E12-D12+F11 -> 64330
A13: 22/3/25 | B13: Exp Sh | C13: Cash deposit | D13: 1200 | F13: =E13-D13+F12 -> 63130
A14: 22/3/25 | B14: Exp Sh | C14: Cash deposit | D14: 1530 | F14: =E14-D14+F13 -> 61600
A15: 22/3/25 | B15: Exp Sh | C15: Cash deposit against Bill 760 | D15: 35000 | F15: =E15-D15+F14 -> 26600
A16: 45904 | B16: H1087 | C16: Chlorine Tab | E16: 500 | F16: =E16-D16+F15 -> 27100
A17: 14/4/25 | B17: H1167 | C17: Mg | E17: 250 | F17: =E17-D17+F16 -> 27350
A18: 15/4/25 | B18: H1176 | C18: Jumbo Housing | E18: 7500 | F18: =E18-D18+F17 -> 34850
A19: 17/4/25 | B19: Exp Sh | C19: Cash deposit | D19: 20000 | F19: =E19-D19+F18 -> 14850
F20: =E20-D20+F19 -> 14850
A21: 17/4/25 | B21: H1231 | C21: 1.5LCaps, 500mlcaps, 1.5L Shoper | E21: 7915 | F21: =E21-D21+F20 -> 22765
F22: =E22-D22+F21 -> 22765
F23: =E23-D23+F22 -> 22765
F24: =E24-D24+F23 -> 22765
A25: GRAND TOTAL | F25: =E25-D25+F24 -> 22765

Sheet Qazi Irfan
A1: LEDGER
A3: Account Holder's Name | D3: Qazi Irfan Sb
A4: Pg #
A5: Date | B5: Ref No. | C5: Description | D5: Debit | E5: Credit | F5: Balance
A6: 19/6/25 | B6: I 24 | C6: RO Axtron | E6: 32000 | F6: =E6-D6 -> 32000
C7: Flow Valve + Labour | E7: 800 | F7: =F6-D7+E7 -> 32800
A8: 45938 | B8: I694 | C8: Labour | E8: 1500 | F8: =F7-D8+E8 -> 34300
A9: 46143 | D9: 34300 | F9: =F8-D9+E9 -> 0
A10: 18/2/26 | B10: j1177 | C10: tank replace +r.o set | E10: 5500 | F10: =F9-D10+E10 -> 5500
F11: =F10-D11+E11 -> 5500
F12: =F11-D12+E12 -> 5500
F13: =F12-D13+E13 -> 5500
F14: =F13-D14+E14 -> 5500
F15: =F14-D15+E15 -> 5500
F16: =F15-D16+E16 -> 5500
F17: =F16-D17+E17 -> 5500
F18: =F17-D18+E18 -> 5500
F19: =F18-D19+E19 -> 5500
F20: =F19-D20+E20 -> 5500
A21: GRAND TOTAL | F21: =F20-D21+E21 -> 5500

Sheet Harpal pure
A1: Ledger
A2: Account Holder's Name | D2: Harpal pure
A3: PG#
A4: Date | B4: Ref.No | C4: Description | D4: Debit | E4: Credit | F4: Balance
A5: 46002 | C5: 30mm caps (5ctn) | D5: 22550 | F5: -22550
A6: 46002 | B6: j50 | C6: 1.5ltr shoper+500ml shoper | E6: 9600 | F6: =F5+E6-D6 -> -12950
A7: 46002 | C7: 30mm caps | E7: 4400 | F7: =F6+E7-D7 -> -8550
C8: 30mm cap | E8: 2200 | F8: =F7+E8-D8 -> -6350
A9: 24/11/25 | B9: j194 | C9: 30mm caps+500ml shoper | E9: 6350 | F9: =F8+E9-D9 -> 0
F10: =F9+E10-D10 -> 0
F11: =F10+E11-D11 -> 0
F12: =F11+E12-D12 -> 0
F13: =F12+E13-D13 -> 0
F14: =F13+E14-D14 -> 0
F15: =F14+E15-D15 -> 0
F16: =F15+E16-D16 -> 0
F17: =F16+E17-D17 -> 0
F18: =F17+E18-D18 -> 0
F19: =F18+E19-D19 -> 0
F20: =F19+E20-D20 -> 0
F21: =F20+E21-D21 -> 0
F22: =F21+E22-D22 -> 0
A23: Grand Total | F23: =F22+E23-D23 -> 0

Sheet Al azam
A1: کھاتہ بنام
A2: ال اعظم واٹر | D2: اکاونٹ ہولڈر کا نام
A3: نیا رجسٹر165/ | E3: صفحہ نمبر
A4: بقایا | B4: نکاس | C4: آمد | D4: تفصیل | E4: صفحہ نمبر | F4: تاریخ
A5: 35350 | B5: 35350 | D5: ہاف لیٹر بوتل | E5: i1384 | F5: 26/09/2023
A6: =A5+B6-C6 -> 40350 | B6: 5000 | D6: ہاف لیٹر ڈھکن | E6: i1378 | F6: 26/09/2023
A7: =A6+B7-C7 -> 25350 | C7: 15000 | D7: جمع رقم | E7: EXp sh. | F7: 44995
A8: =A7+B8-C8 -> 30600 | B8: 5250 | D8: بال وال 1'' | E8: i1645 | F8: 14/10/23
A9: =A8+B9-C9 -> 36100 | B9: 5500 | D9: ہاف لیٹر ڈھکن | E9: i1803 | F9: 44937
A10: =A9+B10-C10 -> 42100 | B10: 6000 | D10: ٹی 1'' | E10: i1971 | F10: 20/11/23
A11: =A10+B11-C11 -> 43200 | B11: 1100 | D11: سوڈیم وغیرہ | E11: f35 | F11: 28/11/23
A12: =A11+B12-C12 -> 45400 | B12: 2200 | D12: اینٹی سکیلر | E12: f580 | F12: 29/01/23
A13: =A12+B13-C13 -> 163000 | B13: 117600 | D13: 1.5لیٹر بوتل | F13: 15/02/24
A14: =A13+B14-C14 -> 217400 | B14: 54400 | D14: ہاف لیٹر بوتل | F14: 15/02/24
A15: =A14+B15-C15 -> 82400 | C15: 135000 | D15: بینک ٹرانسفر | F15: 15/02/24
A16: =A15+B16-C16 -> 42400 | C16: 40000 | D16: بینک ٹرانسفر | F16: 20/02/24
A17: =A16+B17-C17 -> 70440 | B17: 28040 | D17: ہاف لیٹر کیپ | E17: f1025 | F17: 45568
A18: =A17+B18-C18 -> 70950 | B18: 510 | E18: f1141 | F18: 23/03/24
A19: =A18+B19-C19 -> 68500 | C19: 2450 | D19: ڈسکاونٹ | F19: 28/04/24
A20: =A19+B20-C20 -> 18500 | C20: 50000 | D20: نقد رقم جمع | F20: 28/04/24
A21: =A20+B21-C21 -> 60660 | B21: 42160 | D21: وال ساکٹ 1/2 | F21: 28/04/24
A22: =A21+B22-C22 -> 25660 | C22: 35000 | D22: فیڈ پمپ
A23: =A22+B23-C23 -> 5660 | C23: 20000 | D23: نقد رقم جمع | F23: 24/07/24
A24: =A23+B24-C24 -> 45785 | B24: 40125 | D24: ہاف لیٹر+ڈیڑھ لیٹر+500ملی لیٹر شاپر | E24: g840 | F24: 15/09/24
A25: =A24+B25-C25 -> 46160 | B25: 375 | D25: بقایا رقم | E25: h58 | F25: 45839
A26: =A25+B26-C26 -> 47660 | B26: 1500 | D26: جمبو پی پی واے | E26: H935 | F26: 26/03/25
A27: =A26+B27-C27 -> 68090 | B27: 20430 | D27: جمبو پی پی ایف+اینٹی سکیلر+بال وال1'' | E27: i255 | F27: 45845
A28: =A27+B28-C28 -> 70840 | B28: 2750 | D28: 1۔5لیٹرشاپر | E28: i641 | F28: 45816
A29: =A28+B29-C29 -> 53840 | C29: 17000 | D29: نقد رقم جمع | E29: i255 | F29: 45845
A30: =A29+B30-C30 -> 38840 | C30: 15000 | D30: گندم 6من
A31: =A30+B31-C31 -> 34840 | C31: 4000 | D31: آٹا1من
A32: =A31+B32-C32 -> 30340 | C32: 4500 | D32: آٹا1من | F32: 46113
A33: =A32+B33-C33 -> 30340
A34: =A33+B34-C34 -> 30340
A35: =A34+B35-C35 -> 30340
A36: =A35+B36-C36 -> 30340
A37: =A36+B37-C37 -> 30340
A38: 34840 | B38: کل ٹوٹل

Sheet just pure 2
A1: LEDGER
A3: Account Holder's Name | D3: Just Pure (Salman sab)
A4: Pg # | C4: New Reg(116)
A5: Date | B5: Ref No. | C5: Description | D5: Debit | E5: Credit | F5: Balance
A6: 13/03/24 | B6: F1051 | C6: Memb 4*40 Agro Liks | E6: 88500 | F6: =E6 -> 88500
C7: Plant Wasing Memb,.. | E7: 7500 | F7: =F6-D7+E7 -> 96000
A8: 17/03/24 | B8: F1089 | C8: Gac 10" So Pure | E8: 4000 | F8: =F7-D8+E8 -> 100000
A9: 45327 | B9: F1609 | C9: Gac 10" | E9: 5000 | F9: =F8-D9+E9 -> 105000
A10: 45631 | B10: F1741 | C10: Gac 10" | E10: 900 | F10: =F9-D10+E10 -> 105900
A11: 45297 | B11: G02 | C11: Gac 10" | E11: 4500 | F11: =F10-D11+E11 -> 110400
A12: 45391 | B12: G634 | C12: Dosing Pump Repairing | E12: 4000 | F12: =F11-D12+E12 -> 114400
A14: 30/9/24 | B14: G1100 | C14: Flow Valve, Tee (remaining amount) | E14: 700 | F14: =F12-D14+E14 -> 115100
A15: 45637 | B15: G1495 | C15: Memb100G | E15: 9000 | F15: =F14-D15+E15 -> 124100
A16: 26/11/24 | B16: G1632 | C16: Membrane 100G | E16: 4500 | F16: =F15-D16+E16 -> 128600
A17: 19/12/24 | B17: G1823 | C17: 6G Tank, 150G Membrane | E17: 20500 | F17: =F16-D17+E17 -> 149100
A18: 26/12/24 | B18: G1889 | C18: R.O Set | E18: 11000 | F18: =F17-D18+E18 -> 160100
A19: 45689 | B19: H22 | C19: CTO 10", PPF 10" S/P | E19: 800 | F19: =F18-D19+E19 -> 160900
A20: 45778 | B20: H35 | C20: R.O Set | E20: 14500 | F20: =F19-D20+E20 -> 175400
A21: 45962 | B21: H90 | C21: PPF,CTO Vit, GAC Vit | E21: 2400 | F21: =F20-D21+E21 -> 177800
A22: 29/1/25 | B22: H363 | C22: Chlorine tab, 5L + Caps, 1.5L + Caps | E22: 600 | F22: =F21-D22+E22 -> 178400
A23: 13/2/25 | B23: H508 | C23: Membrane 75G | E23: 3500 | F23: =F22-D23+E23 -> 181900
A24: 45963 | B24: H484 | C24: R.O Set | E24: 1800 | F24: =F23-D24+E24 -> 183700
A25: 45781 | B25: H1018 | C25: 100G Membrane | E25: 5000 | F25: =F24-D25+E25 -> 188700
A26: 14/4/25 | B26: H1161 | C26: Tank 32G | E26: 5500 | F26: =F25-D26+E26 -> 194200
F27: =F26-D27+E27 -> 194200
F28: =F27-D28+E28 -> 194200
F29: =F28-D29+E29 -> 194200
F30: =F29-D30+E30 -> 194200
F31: =F30-D31+E31 -> 194200
F32: =F31-D32+E32 -> 194200
F33: =F32-D33+E33 -> 194200
F34: =F33-D34+E34 -> 194200
F35: =F34-D35+E35 -> 194200
A36: GRAND TOTAL | F36: =F35-D36+E36 -> 194200
